Workbook
Name CT_RACEINCOME: #REF!
Name LA_DEMO: 'County PopulationPovertyRacial '!$A$1138:$L$1202
Name MD_KIN: 'MD Data'!$A$118:$D$143
Name MI_RACEINCOME: #REF!
Name CA_DEMO: 'County PopulationPovertyRacial '!$A$198:$L$256
Name AZ_RACEINCOME: #REF!
Name MD_FOSTER: 'MD Data'!$A$89:$D$114
Name PA_DEMO: 'County PopulationPovertyRacial '!$A$2289:$L$2356
Name MO_RACEINCOME: #REF!
Name TN_RACEINCOME: #REF!
Name VA_DEMO: 'County PopulationPovertyRacial '!$A$2873:$L$3006
Name CA_RACEINCOME: #REF!
Name MS_RACEINCOME: #REF!
Name MD_INHOME: 'MD Data'!$A$61:$D$87
Name CT_DEMO: 'County PopulationPovertyRacial '!$A$322:$L$330
Name NM_DEMO: 'County PopulationPovertyRacial '!$A$1833:$L$1866
Name OK_DEMO: 'County PopulationPovertyRacial '!$A$2174:$L$2251
Name RI_RACEINCOME: #REF!
Name AR_DEMO: 'County PopulationPovertyRacial '!$A$122:$L$197
Name MD_INCARE: 'MD Data'!$A$2:$D$27
Name ID_DEMO: 'County PopulationPovertyRacial '!$A$570:$L$614
Name MT_DEMO: 'County PopulationPovertyRacial '!$A$1631:$L$1687
Name IA_RACEINCOME: #REF!
Name TX_DEMO: 'County PopulationPovertyRacial '!$A$2573:$L$2827
Name AL_DEMO: 'County PopulationPovertyRacial '!$A$7:$L$74
Name TN_DEMO: 'County PopulationPovertyRacial '!$A$2477:$L$2572
Name MN_RACEINCOME: #REF!
Name MI_DEMO: 'County PopulationPovertyRacial '!$A$1260:$L$1343
Name MD_DEMO: 'County PopulationPovertyRacial '!$A$1220:$L$1244
Name MT_RACEINCOME: #REF!
Name OK_RACEINCOME: #REF!
Name ND_DEMO: 'County PopulationPovertyRacial '!$A$2031:$L$2084
Name IA_DEMO: 'County PopulationPovertyRacial '!$A$811:$L$910
Name VT_RACEINCOME: #REF!
Name WA_DEMO: 'County PopulationPovertyRacial '!$A$3007:$L$3046
Name TX_RACEINCOME: #REF!
Name LA_RACEINCOME: #REF!
Name AK_RACEINCOME: #REF!
Name GA_DEMO: 'County PopulationPovertyRacial '!$A$404:$L$563
Name MS_DEMO: 'County PopulationPovertyRacial '!$A$1432:$L$1514
Name AK_DEMO: 'County PopulationPovertyRacial '!$A$75:$L$105
Name AL_RACEINCOME: #REF!
Name NH_RACEINCOME: #REF!
Name FL_RACEINCOME: #REF!
Name CO_DEMO: 'County PopulationPovertyRacial '!$A$257:$L$321
Name OH_DEMO: 'County PopulationPovertyRacial '!$A$2085:$L$2173
Name SC_RACEINCOME: #REF!
Name NE_RACEINCOME: #REF!
Name NJ_DEMO: 'County PopulationPovertyRacial '!$A$1811:$L$1832
Name ME_RACEINCOME: #REF!
Name VT_DEMO: 'County PopulationPovertyRacial '!$A$2858:$L$2872
Name IN_RACEINCOME: #REF!
Name WV_DEMO: 'County PopulationPovertyRacial '!$A$3047:$L$3102
Name PA_RACEINCOME: #REF!
Name NJ_RACEINCOME: #REF!
Name NV_RACEINCOME: #REF!
Name WY_RACEINCOME: #REF!
Name NM_RACEINCOME: #REF!
Name SD_RACEINCOME: #REF!
Name HI_RACEINCOME: #REF!

Sheet All Data Connect
A1: id | B1: is_national | C1: is_state | D1: is_county | E1: state_code | F1: county_code | G1: county_state_code | H1: county_name | I1: state_name_full | J1: state_name_abv | K1: county_state | L1: number of children in care | M1: average beds per family | N1: number of children in foster care | O1: number of children in kinship care | P1: number of children placed out-of-county | Q1: number of foster and kinship homes | R1: number of children waiting for adoption | S1: number of children with 80+ connections made | T1: biological family reunification rate | U1: number of family preservation cases | V1: number of adoptive families | W1: number of biological families | X1: number of wraparound supporters | Y1: number of churches | Z1: foster family retention rate
A2: 1 | B2: 1
A3: 2 | C3: 1 | E3: 1 | I3: Alabama | J3: AL | L3: {=Alabama!C71:Q71} -> 5844 | M3: NULL | N3: NULL | O3: NULL | P3: NULL | Q3: 1989 | R3: 399 | S3: NULL | T3: NULL | U3: 4558 | V3: NULL | W3: NULL | X3: NULL | Y3: 0 | Z3: NULL
A4: 3 | D4: 1 | E4: 1 | F4: 1 | G4: =CONCATENATE(TEXT($E4,"00"),TEXT($F4,"000")) -> 01001 | H4: Autauga | I4: Alabama | J4: AL | K4: =CONCATENATE(H4,", ",J4) -> Autauga, AL | L4: {=Alabama!C3:Q69} -> NULL | M4: NULL | N4: NULL | O4: NULL | P4: NULL | Q4: NULL | R4: NULL | S4: NULL | T4: NULL | U4: NULL | V4: NULL | W4: NULL | X4: NULL | Y4: NULL | Z4: NULL
A5: 4 | D5: 1 | E5: 1 | F5: 3 | G5: =CONCATENATE(TEXT($E5,"00"),TEXT($F5,"000")) -> 01003 | H5: Baldwin | I5: Alabama | J5: AL | K5: =CONCATENATE(H5,", ",J5) -> Baldwin, AL | M5: NULL | N5: NULL | O5: NULL | P5: NULL | Q5: NULL | R5: NULL | S5: NULL | T5: NULL | U5: NULL | V5: NULL | W5: NULL | X5: NULL | Y5: NULL | Z5: NULL
A6: 5 | D6: 1 | E6: 1 | F6: 5 | G6: =CONCATENATE(TEXT($E6,"00"),TEXT($F6,"000")) -> 01005 | H6: Barbour | I6: Alabama | J6: AL | K6: =CONCATENATE(H6,", ",J6) -> Barbour, AL | M6: NULL | N6: NULL | O6: NULL | P6: NULL | Q6: NULL | R6: NULL | S6: NULL | T6: NULL | U6: NULL | V6: NULL | W6: NULL | X6: NULL | Y6: NULL | Z6: NULL
A7: 6 | D7: 1 | E7: 1 | F7: 7 | G7: =CONCATENATE(TEXT($E7,"00"),TEXT($F7,"000")) -> 01007 | H7: Bibb | I7: Alabama | J7: AL | K7: =CONCATENATE(H7,", ",J7) -> Bibb, AL | M7: NULL | N7: NULL | O7: NULL | P7: NULL | Q7: NULL | R7: NULL | S7: NULL | T7: NULL | U7: NULL | V7: NULL | W7: NULL | X7: NULL | Y7: NULL | Z7: NULL
A8: 7 | D8: 1 | E8: 1 | F8: 9 | G8: =CONCATENATE(TEXT($E8,"00"),TEXT($F8,"000")) -> 01009 | H8: Blount | I8: Alabama | J8: AL | K8: =CONCATENATE(H8,", ",J8) -> Blount, AL | M8: NULL | N8: NULL | O8: NULL | P8: NULL | Q8: NULL | R8: NULL | S8: NULL | T8: NULL | U8: NULL | V8: NULL | W8: NULL | X8: NULL | Y8: NULL | Z8: NULL
A9: 8 | D9: 1 | E9: 1 | F9: 11 | G9: =CONCATENATE(TEXT($E9,"00"),TEXT($F9,"000")) -> 01011 | H9: Bullock | I9: Alabama | J9: AL | K9: =CONCATENATE(H9,", ",J9) -> Bullock, AL | M9: NULL | N9: NULL | O9: NULL | P9: NULL | Q9: NULL | R9: NULL | S9: NULL | T9: NULL | U9: NULL | V9: NULL | W9: NULL | X9: NULL | Y9: NULL | Z9: NULL
A10: 9 | D10: 1 | E10: 1 | F10: 13 | G10: =CONCATENATE(TEXT($E10,"00"),TEXT($F10,"000")) -> 01013 | H10: Butler | I10: Alabama | J10: AL | K10: =CONCATENATE(H10,", ",J10) -> Butler, AL | M10: NULL | N10: NULL | O10: NULL | P10: NULL | Q10: NULL | R10: NULL | S10: NULL | T10: NULL | U10: NULL | V10: NULL | W10: NULL | X10: NULL | Y10: NULL | Z10: NULL
A11: 10 | D11: 1 | E11: 1 | F11: 15 | G11: =CONCATENATE(TEXT($E11,"00"),TEXT($F11,"000")) -> 01015 | H11: Calhoun | I11: Alabama | J11: AL | K11: =CONCATENATE(H11,", ",J11) -> Calhoun, AL | M11: NULL | N11: NULL | O11: NULL | P11: NULL | Q11: NULL | R11: NULL | S11: NULL | T11: NULL | U11: NULL | V11: NULL | W11: NULL | X11: NULL | Y11: NULL | Z11: NULL
A12: 11 | D12: 1 | E12: 1 | F12: 17 | G12: =CONCATENATE(TEXT($E12,"00"),TEXT($F12,"000")) -> 01017 | H12: Chambers | I12: Alabama | J12: AL | K12: =CONCATENATE(H12,", ",J12) -> Chambers, AL | M12: NULL | N12: NULL | O12: NULL | P12: NULL | Q12: NULL | R12: NULL | S12: NULL | T12: NULL | U12: NULL | V12: NULL | W12: NULL | X12: NULL | Y12: NULL | Z12: NULL
A13: 12 | D13: 1 | E13: 1 | F13: 19 | G13: =CONCATENATE(TEXT($E13,"00"),TEXT($F13,"000")) -> 01019 | H13: Cherokee | I13: Alabama | J13: AL | K13: =CONCATENATE(H13,", ",J13) -> Cherokee, AL | M13: NULL | N13: NULL | O13: NULL | P13: NULL | Q13: NULL | R13: NULL | S13: NULL | T13: NULL | U13: NULL | V13: NULL | W13: NULL | X13: NULL | Y13: NULL | Z13: NULL
A14: 13 | D14: 1 | E14: 1 | F14: 21 | G14: =CONCATENATE(TEXT($E14,"00"),TEXT($F14,"000")) -> 01021 | H14: Chilton | I14: Alabama | J14: AL | K14: =CONCATENATE(H14,", ",J14) -> Chilton, AL | M14: NULL | N14: NULL | O14: NULL | P14: NULL | Q14: NULL | R14: NULL | S14: NULL | T14: NULL | U14: NULL | V14: NULL | W14: NULL | X14: NULL | Y14: NULL | Z14: NULL
A15: 14 | D15: 1 | E15: 1 | F15: 23 | G15: =CONCATENATE(TEXT($E15,"00"),TEXT($F15,"000")) -> 01023 | H15: Choctaw | I15: Alabama | J15: AL | K15: =CONCATENATE(H15,", ",J15) -> Choctaw, AL | M15: NULL | N15: NULL | O15: NULL | P15: NULL | Q15: NULL | R15: NULL | S15: NULL | T15: NULL | U15: NULL | V15: NULL | W15: NULL | X15: NULL | Y15: NULL | Z15: NULL
A16: 15 | D16: 1 | E16: 1 | F16: 25 | G16: =CONCATENATE(TEXT($E16,"00"),TEXT($F16,"000")) -> 01025 | H16: Clarke | I16: Alabama | J16: AL | K16: =CONCATENATE(H16,", ",J16) -> Clarke, AL | M16: NULL | N16: NULL | O16: NULL | P16: NULL | Q16: NULL | R16: NULL | S16: NULL | T16: NULL | U16: NULL | V16: NULL | W16: NULL | X16: NULL | Y16: NULL | Z16: NULL
... A70: 69 | D70: 1 | E70: 1 | F70: 133 | G70: =CONCATENATE(TEXT($E70,"00"),TEXT($F70,"000")) -> 01133 | H70: Winston | I70: Alabama | J70: AL | K70: =CONCATENATE(H70,", ",J70) -> Winston, AL | M70: NULL | N70: NULL | O70: NULL | P70: NULL | Q70: NULL | R70: NULL | S70: NULL | T70: NULL | U70: NULL | V70: NULL | W70: NULL | X70: NULL | Y70: NULL | Z70: NULL
A71: 70 | C71: 1 | E71: 2 | G71: =CONCATENATE(TEXT($E71,"00"),TEXT($F71,"000")) -> 02000 | I71: Alaska | J71: AK | L71: {=Alaska!C9:Q9} -> 2261 | M71: 2.08 | N71: 1112 | O71: 1117 | P71: NULL | Q71: 1486 | R71: 853 | S71: NULL | T71: 0.4878 | U71: NULL | V71: NULL | W71: NULL | X71: NULL | Y71: 210 | Z71: NULL
A72: 71 | D72: 1 | E72: 2 | F72: 13 | G72: =CONCATENATE(TEXT($E72,"00"),TEXT($F72,"000")) -> 02013 | H72: Aleutians East | I72: Alaska | J72: AK | K72: =CONCATENATE(H72,", ",J72) -> Aleutians East, AK | L72: {=Alaska!C3:Q7} -> 858 | M72: NULL | N72: 431 | O72: 418 | P72: NULL | Q72: NULL | R72: 280 | S72: NULL | T72: 0.524 | U72: NULL | V72: NULL | W72: 0.524 | X72: NULL | Y72: 210 | Z72: NULL
A73: 72 | D73: 1 | E73: 2 | F73: 16 | G73: =CONCATENATE(TEXT($E73,"00"),TEXT($F73,"000")) -> 02016 | H73: Aleutians West | I73: Alaska | J73: AK | K73: =CONCATENATE(H73,", ",J73) -> Aleutians West, AK | L73: 440 | M73: NULL | N73: 242 | O73: 193 | P73: NULL | Q73: NULL | R73: 174 | S73: NULL | T73: 0.534 | U73: NULL | V73: NULL | W73: 0.534 | X73: NULL | Y73: NULL | Z73: NULL
A74: 73 | D74: 1 | E74: 2 | F74: 20 | G74: =CONCATENATE(TEXT($E74,"00"),TEXT($F74,"000")) -> 02020 | H74: Anchorage | I74: Alaska | J74: AK | K74: =CONCATENATE(H74,", ",J74) -> Anchorage, AK | L74: 562 | M74: NULL | N74: 261 | O74: 290 | P74: NULL | Q74: NULL | R74: 277 | S74: NULL | T74: NULL | U74: NULL | V74: NULL | W74: 0.498 | X74: NULL | Y74: NULL | Z74: NULL
A75: 74 | D75: 1 | E75: 2 | F75: 50 | G75: =CONCATENATE(TEXT($E75,"00"),TEXT($F75,"000")) -> 02050 | H75: Bethel | I75: Alaska | J75: AK | K75: =CONCATENATE(H75,", ",J75) -> Bethel, AK | L75: 146 | M75: NULL | N75: 76 | O75: 68 | P75: NULL | Q75: NULL | R75: 42 | S75: NULL | T75: NULL | U75: NULL | V75: NULL | W75: 0.397 | X75: NULL | Y75: NULL | Z75: NULL
A76: 75 | D76: 1 | E76: 2 | F76: 60 | G76: =CONCATENATE(TEXT($E76,"00"),TEXT($F76,"000")) -> 02060 | H76: Bristol Bay | I76: Alaska | J76: AK | K76: =CONCATENATE(H76,", ",J76) -> Bristol Bay, AK | L76: 255 | M76: NULL | N76: 102 | O76: 148 | P76: NULL | Q76: NULL | R76: 80 | S76: NULL | T76: NULL | U76: NULL | V76: NULL | W76: 0.486 | X76: NULL | Y76: NULL | Z76: NULL
A77: 76 | D77: 1 | E77: 2 | F77: 63 | G77: =CONCATENATE(TEXT($E77,"00"),TEXT($F77,"000")) -> 02063 | H77: Chugach | I77: Alaska | J77: AK | K77: =CONCATENATE(H77,", ",J77) -> Chugach, AK
A78: 77 | D78: 1 | E78: 2 | F78: 66 | G78: =CONCATENATE(TEXT($E78,"00"),TEXT($F78,"000")) -> 02066 | H78: Copper River | I78: Alaska | J78: AK | K78: =CONCATENATE(H78,", ",J78) -> Copper River, AK
A79: 78 | D79: 1 | E79: 2 | F79: 68 | G79: =CONCATENATE(TEXT($E79,"00"),TEXT($F79,"000")) -> 02068 | H79: Denali | I79: Alaska | J79: AK | K79: =CONCATENATE(H79,", ",J79) -> Denali, AK
A80: 79 | D80: 1 | E80: 2 | F80: 70 | G80: =CONCATENATE(TEXT($E80,"00"),TEXT($F80,"000")) -> 02070 | H80: Dillingham | I80: Alaska | J80: AK | K80: =CONCATENATE(H80,", ",J80) -> Dillingham, AK
A81: 80 | D81: 1 | E81: 2 | F81: 90 | G81: =CONCATENATE(TEXT($E81,"00"),TEXT($F81,"000")) -> 02090 | H81: Fairbanks North Star | I81: Alaska | J81: AK | K81: =CONCATENATE(H81,", ",J81) -> Fairbanks North Star, AK
A82: 81 | D82: 1 | E82: 2 | F82: 100 | G82: =CONCATENATE(TEXT($E82,"00"),TEXT($F82,"000")) -> 02100 | H82: Haines | I82: Alaska | J82: AK | K82: =CONCATENATE(H82,", ",J82) -> Haines, AK
A83: 82 | D83: 1 | E83: 2 | F83: 105 | G83: =CONCATENATE(TEXT($E83,"00"),TEXT($F83,"000")) -> 02105 | H83: Hoonah-Angoon | I83: Alaska | J83: AK | K83: =CONCATENATE(H83,", ",J83) -> Hoonah-Angoon, AK
A84: 83 | D84: 1 | E84: 2 | F84: 110 | G84: =CONCATENATE(TEXT($E84,"00"),TEXT($F84,"000")) -> 02110 | H84: Juneau | I84: Alaska | J84: AK | K84: =CONCATENATE(H84,", ",J84) -> Juneau, AK
A85: 84 | D85: 1 | E85: 2 | F85: 122 | G85: =CONCATENATE(TEXT($E85,"00"),TEXT($F85,"000")) -> 02122 | H85: Kenai Peninsula | I85: Alaska | J85: AK | K85: =CONCATENATE(H85,", ",J85) -> Kenai Peninsula, AK
A86: 85 | D86: 1 | E86: 2 | F86: 130 | G86: =CONCATENATE(TEXT($E86,"00"),TEXT($F86,"000")) -> 02130 | H86: Ketchikan Gateway | I86: Alaska | J86: AK | K86: =CONCATENATE(H86,", ",J86) -> Ketchikan Gateway, AK
A87: 86 | D87: 1 | E87: 2 | F87: 150 | G87: =CONCATENATE(TEXT($E87,"00"),TEXT($F87,"000")) -> 02150 | H87: Kodiak Island | I87: Alaska | J87: AK | K87: =CONCATENATE(H87,", ",J87) -> Kodiak Island, AK
A88: 87 | D88: 1 | E88: 2 | F88: 158 | G88: =CONCATENATE(TEXT($E88,"00"),TEXT($F88,"000")) -> 02158 | H88: Kusilvak | I88: Alaska | J88: AK | K88: =CONCATENATE(H88,", ",J88) -> Kusilvak, AK
... A101: 100 | D101: 1 | E101: 2 | F101: 290 | G101: =CONCATENATE(TEXT($E101,"00"),TEXT($F101,"000")) -> 02290 | H101: Yukon-Koyukuk | I101: Alaska | J101: AK | K101: =CONCATENATE(H101,", ",J101) -> Yukon-Koyukuk, AK
A102: 101 | C102: 1 | E102: 4 | G102: =CONCATENATE(TEXT($E102,"00"),TEXT($F102,"000")) -> 04000 | I102: Arizona | J102: AZ | L102: {=Arizona!C19:Q19} -> 8839 | M102: NULL | N102: NULL | O102: NULL | P102: NULL | Q102: 2170 | R102: 1606 | S102: NULL | T102: NULL | U102: NULL | V102: NULL | W102: NULL | X102: NULL | Y102: 2507 | Z102: NULL
A103: 102 | D103: 1 | E103: 4 | F103: 1 | G103: =CONCATENATE(TEXT($E103,"00"),TEXT($F103,"000")) -> 04001 | H103: Apache | I103: Arizona | J103: AZ | K103: =CONCATENATE(H103,", ",J103) -> Apache, AZ | L103: {=Arizona!C3:Q17} -> 26 | M103: NULL | N103: NULL | O103: NULL | P103: NULL | Q103: NULL | R103: NULL | S103: NULL | T103: NULL | U103: NULL | V103: NULL | W103: NULL | X103: NULL | Y103: 48 | Z103: NULL
A104: 103 | D104: 1 | E104: 4 | F104: 3 | G104: =CONCATENATE(TEXT($E104,"00"),TEXT($F104,"000")) -> 04003 | H104: Cochise | I104: Arizona | J104: AZ | K104: =CONCATENATE(H104,", ",J104) -> Cochise, AZ | L104: 215 | M104: NULL | N104: NULL | O104: NULL | P104: NULL | Q104: NULL | R104: NULL | S104: NULL | T104: NULL | U104: NULL | V104: NULL | W104: NULL | X104: NULL | Y104: 129 | Z104: NULL
A105: 104 | D105: 1 | E105: 4 | F105: 5 | G105: =CONCATENATE(TEXT($E105,"00"),TEXT($F105,"000")) -> 04005 | H105: Coconino | I105: Arizona | J105: AZ | K105: =CONCATENATE(H105,", ",J105) -> Coconino, AZ | L105: 120 | M105: NULL | N105: NULL | O105: NULL | P105: NULL | Q105: NULL | R105: NULL | S105: NULL | T105: NULL | U105: NULL | V105: NULL | W105: NULL | X105: NULL | Y105: 76 | Z105: NULL
A106: 105 | D106: 1 | E106: 4 | F106: 7 | G106: =CONCATENATE(TEXT($E106,"00"),TEXT($F106,"000")) -> 04007 | H106: Gila | I106: Arizona | J106: AZ | K106: =CONCATENATE(H106,", ",J106) -> Gila, AZ | L106: 99 | M106: NULL | N106: NULL | O106: NULL | P106: NULL | Q106: NULL | R106: NULL | S106: NULL | T106: NULL | U106: NULL | V106: NULL | W106: NULL | X106: NULL | Y106: 62 | Z106: NULL
A107: 106 | D107: 1 | E107: 4 | F107: 9 | G107: =CONCATENATE(TEXT($E107,"00"),TEXT($F107,"000")) -> 04009 | H107: Graham | I107: Arizona | J107: AZ | K107: =CONCATENATE(H107,", ",J107) -> Graham, AZ | L107: 43 | M107: NULL | N107: NULL | O107: NULL | P107: NULL | Q107: NULL | R107: NULL | S107: NULL | T107: NULL | U107: NULL | V107: NULL | W107: NULL | X107: NULL | Y107: 24 | Z107: NULL
A108: 107 | D108: 1 | E108: 4 | F108: 11 | G108: =CONCATENATE(TEXT($E108,"00"),TEXT($F108,"000")) -> 04011 | H108: Greenlee | I108: Arizona | J108: AZ | K108: =CONCATENATE(H108,", ",J108) -> Greenlee, AZ | L108: 7 | M108: NULL | N108: NULL | O108: NULL | P108: NULL | Q108: NULL | R108: NULL | S108: NULL | T108: NULL | U108: NULL | V108: NULL | W108: NULL | X108: NULL | Y108: 7 | Z108: NULL
A109: 108 | D109: 1 | E109: 4 | F109: 12 | G109: =CONCATENATE(TEXT($E109,"00"),TEXT($F109,"000")) -> 04012 | H109: La Paz | I109: Arizona | J109: AZ | K109: =CONCATENATE(H109,", ",J109) -> La Paz, AZ | L109: 18 | M109: NULL | N109: NULL | O109: NULL | P109: NULL | Q109: NULL | R109: NULL | S109: NULL | T109: NULL | U109: NULL | V109: NULL | W109: NULL | X109: NULL | Y109: 25 | Z109: NULL
A110: 109 | D110: 1 | E110: 4 | F110: 13 | G110: =CONCATENATE(TEXT($E110,"00"),TEXT($F110,"000")) -> 04013 | H110: Maricopa | I110: Arizona | J110: AZ | K110: =CONCATENATE(H110,", ",J110) -> Maricopa, AZ | L110: 5184 | M110: NULL | N110: NULL | O110: NULL | P110: NULL | Q110: NULL | R110: NULL | S110: NULL | T110: NULL | U110: NULL | V110: NULL | W110: NULL | X110: NULL | Y110: 1166 | Z110: NULL
A111: 110 | D111: 1 | E111: 4 | F111: 15 | G111: =CONCATENATE(TEXT($E111,"00"),TEXT($F111,"000")) -> 04015 | H111: Mohave | I111: Arizona | J111: AZ | K111: =CONCATENATE(H111,", ",J111) -> Mohave, AZ | L111: 305 | M111: NULL | N111: NULL | O111: NULL | P111: NULL | Q111: NULL | R111: NULL | S111: NULL | T111: NULL | U111: NULL | V111: NULL | W111: NULL | X111: NULL | Y111: 104 | Z111: NULL
A112: 111 | D112: 1 | E112: 4 | F112: 17 | G112: =CONCATENATE(TEXT($E112,"00"),TEXT($F112,"000")) -> 04017 | H112: Navajo | I112: Arizona | J112: AZ | K112: =CONCATENATE(H112,", ",J112) -> Navajo, AZ | L112: 101 | M112: NULL | N112: NULL | O112: NULL | P112: NULL | Q112: NULL | R112: NULL | S112: NULL | T112: NULL | U112: NULL | V112: NULL | W112: NULL | X112: NULL | Y112: 81 | Z112: NULL
A113: 112 | D113: 1 | E113: 4 | F113: 19 | G113: =CONCATENATE(TEXT($E113,"00"),TEXT($F113,"000")) -> 04019 | H113: Pima | I113: Arizona | J113: AZ | K113: =CONCATENATE(H113,", ",J113) -> Pima, AZ | L113: 1744 | M113: NULL | N113: NULL | O113: NULL | P113: NULL | Q113: NULL | R113: NULL | S113: NULL | T113: NULL | U113: NULL | V113: NULL | W113: NULL | X113: NULL | Y113: 404 | Z113: NULL
A114: 113 | D114: 1 | E114: 4 | F114: 21 | G114: =CONCATENATE(TEXT($E114,"00"),TEXT($F114,"000")) -> 04021 | H114: Pinal | I114: Arizona | J114: AZ | K114: =CONCATENATE(H114,", ",J114) -> Pinal, AZ | L114: 501 | M114: NULL | N114: NULL | O114: NULL | P114: NULL | Q114: NULL | R114: NULL | S114: NULL | T114: NULL | U114: NULL | V114: NULL | W114: NULL | X114: NULL | Y114: 131 | Z114: NULL
A115: 114 | D115: 1 | E115: 4 | F115: 23 | G115: =CONCATENATE(TEXT($E115,"00"),TEXT($F115,"000")) -> 04023 | H115: Santa Cruz | I115: Arizona | J115: AZ | K115: =CONCATENATE(H115,", ",J115) -> Santa Cruz, AZ | L115: 73 | M115: NULL | N115: NULL | O115: NULL | P115: NULL | Q115: NULL | R115: NULL | S115: NULL | T115: NULL | U115: NULL | V115: NULL | W115: NULL | X115: NULL | Y115: 19 | Z115: NULL
... A117: 116 | D117: 1 | E117: 4 | F117: 27 | G117: =CONCATENATE(TEXT($E117,"00"),TEXT($F117,"000")) -> 04027 | H117: Yuma | I117: Arizona | J117: AZ | K117: =CONCATENATE(H117,", ",J117) -> Yuma, AZ | L117: 169 | M117: NULL | N117: NULL | O117: NULL | P117: NULL | Q117: NULL | R117: NULL | S117: NULL | T117: NULL | U117: NULL | V117: NULL | W117: NULL | X117: NULL | Y117: 70 | Z117: NULL
A118: 117 | C118: 1 | E118: 5 | F118: 0 | G118: =CONCATENATE(TEXT($E118,"00"),TEXT($F118,"000")) -> 05000 | I118: Arkansas | J118: AR | L118: {=Arkansas!C79:Q79} -> 3604 | M118: 1.9804631 | N118: NULL | O118: NULL | P118: NULL | Q118: 1835 | R118: 299 | S118: NULL | T118: NULL | U118: 1436 | V118: NULL | W118: NULL | X118: NULL | Y118: 3846
A119: 118 | D119: 1 | E119: 5 | F119: 1 | G119: =CONCATENATE(TEXT($E119,"00"),TEXT($F119,"000")) -> 05001 | H119: Arkansas | I119: Arkansas | J119: AR | K119: =CONCATENATE(H119,", ",J119) -> Arkansas, AR | L119: {=Arkansas!C3:Q77} -> 15 | M119: 1.8 | N119: NULL | O119: 6 | P119: NULL | Q119: 5 | R119: 3 | S119: NULL | T119: NULL | U119: 9 | V119: NULL | W119: NULL | X119: NULL | Y119: 33 | Z119: NULL
A120: 119 | D120: 1 | E120: 5 | F120: 3 | G120: =CONCATENATE(TEXT($E120,"00"),TEXT($F120,"000")) -> 05003 | H120: Ashley | I120: Arkansas | J120: AR | K120: =CONCATENATE(H120,", ",J120) -> Ashley, AR | L120: 10 | M120: 1.7777778 | N120: NULL | O120: 7 | P120: NULL | Q120: 15 | R120: 0 | S120: NULL | T120: NULL | U120: 4 | V120: NULL | W120: NULL | X120: NULL | Y120: 52
A121: 120 | D121: 1 | E121: 5 | F121: 5 | G121: =CONCATENATE(TEXT($E121,"00"),TEXT($F121,"000")) -> 05005 | H121: Baxter | I121: Arkansas | J121: AR | K121: =CONCATENATE(H121,", ",J121) -> Baxter, AR | L121: 29 | M121: 1.6190476 | N121: NULL | O121: 5 | P121: NULL | Q121: 27 | R121: 4 | S121: NULL | T121: NULL | U121: 13 | V121: NULL | W121: NULL | X121: NULL | Y121: 52 | Z121: NULL
A122: 121 | D122: 1 | E122: 5 | F122: 7 | G122: =CONCATENATE(TEXT($E122,"00"),TEXT($F122,"000")) -> 05007 | H122: Benton | I122: Arkansas | J122: AR | K122: =CONCATENATE(H122,", ",J122) -> Benton, AR | L122: 129 | M122: 1.9659091 | N122: NULL | O122: 33 | P122: NULL | Q122: 113 | R122: 7 | S122: NULL | T122: NULL | U122: 65 | V122: NULL | W122: NULL | X122: NULL | Y122: 197 | Z122: NULL
A123: 122 | D123: 1 | E123: 5 | F123: 9 | G123: =CONCATENATE(TEXT($E123,"00"),TEXT($F123,"000")) -> 05009 | H123: Boone | I123: Arkansas | J123: AR | K123: =CONCATENATE(H123,", ",J123) -> Boone, AR | L123: 40 | M123: 2.2380952 | N123: NULL | O123: 18 | P123: NULL | Q123: 27 | R123: 5 | S123: NULL | T123: NULL | U123: 30 | V123: NULL | W123: NULL | X123: NULL | Y123: 67 | Z123: NULL
A124: 123 | D124: 1 | E124: 5 | F124: 11 | G124: =CONCATENATE(TEXT($E124,"00"),TEXT($F124,"000")) -> 05011 | H124: Bradley | I124: Arkansas | J124: AR | K124: =CONCATENATE(H124,", ",J124) -> Bradley, AR | L124: 7 | M124: 2.25 | N124: NULL | O124: 5 | P124: NULL | Q124: 7 | R124: 0 | S124: NULL | T124: NULL | U124: 5 | V124: NULL | W124: NULL | X124: NULL | Y124: 18 | Z124: NULL
A125: 124 | D125: 1 | E125: 5 | F125: 13 | G125: =CONCATENATE(TEXT($E125,"00"),TEXT($F125,"000")) -> 05013 | H125: Calhoun | I125: Arkansas | J125: AR | K125: =CONCATENATE(H125,", ",J125) -> Calhoun, AR | L125: 1 | M125: 1.3333333 | N125: NULL | O125: 1 | P125: NULL | Q125: 5 | R125: 0 | S125: NULL | T125: NULL | U125: 1 | V125: NULL | W125: NULL | X125: NULL | Y125: 16 | Z125: NULL
A126: 125 | D126: 1 | E126: 5 | F126: 15 | G126: =CONCATENATE(TEXT($E126,"00"),TEXT($F126,"000")) -> 05015 | H126: Carroll | I126: Arkansas | J126: AR | K126: =CONCATENATE(H126,", ",J126) -> Carroll, AR | L126: 30 | M126: 2 | N126: NULL | O126: 10 | P126: NULL | Q126: 9 | R126: 1 | S126: NULL | T126: NULL | U126: 16 | V126: NULL | W126: NULL | X126: NULL | Y126: 35 | Z126: NULL
A127: 126 | D127: 1 | E127: 5 | F127: 17 | G127: =CONCATENATE(TEXT($E127,"00"),TEXT($F127,"000")) -> 05017 | H127: Chicot | I127: Arkansas | J127: AR | K127: =CONCATENATE(H127,", ",J127) -> Chicot, AR | L127: 7 | M127: 2 | N127: NULL | O127: 2 | P127: NULL | Q127: 5 | R127: 0 | S127: NULL | T127: NULL | U127: 5 | V127: NULL | W127: NULL | X127: NULL | Y127: 24 | Z127: NULL
A128: 127 | D128: 1 | E128: 5 | F128: 19 | G128: =CONCATENATE(TEXT($E128,"00"),TEXT($F128,"000")) -> 05019 | H128: Clark | I128: Arkansas | J128: AR | K128: =CONCATENATE(H128,", ",J128) -> Clark, AR | L128: 12 | M128: 1.9411765 | N128: NULL | O128: 4 | P128: NULL | Q128: 19 | R128: 1 | S128: NULL | T128: NULL | U128: 9 | V128: NULL | W128: NULL | X128: NULL | Y128: 48 | Z128: NULL
A129: 128 | D129: 1 | E129: 5 | F129: 21 | G129: =CONCATENATE(TEXT($E129,"00"),TEXT($F129,"000")) -> 05021 | H129: Clay | I129: Arkansas | J129: AR | K129: =CONCATENATE(H129,", ",J129) -> Clay, AR | L129: 14 | M129: 2.25 | N129: NULL | O129: 5 | P129: NULL | Q129: 10 | R129: 3 | S129: NULL | T129: NULL | U129: 12 | V129: NULL | W129: NULL | X129: NULL | Y129: 21 | Z129: NULL
A130: 129 | D130: 1 | E130: 5 | F130: 23 | G130: =CONCATENATE(TEXT($E130,"00"),TEXT($F130,"000")) -> 05023 | H130: Cleburne | I130: Arkansas | J130: AR | K130: =CONCATENATE(H130,", ",J130) -> Cleburne, AR | L130: 38 | M130: 1.9166667 | N130: NULL | O130: 14 | P130: NULL | Q130: 15 | R130: 1 | S130: NULL | T130: NULL | U130: 16 | V130: NULL | W130: NULL | X130: NULL | Y130: 47 | Z130: NULL
A131: 130 | D131: 1 | E131: 5 | F131: 25 | G131: =CONCATENATE(TEXT($E131,"00"),TEXT($F131,"000")) -> 05025 | H131: Cleveland | I131: Arkansas | J131: AR | K131: =CONCATENATE(H131,", ",J131) -> Cleveland, AR | L131: 2 | M131: 2.6666667 | N131: NULL | O131: 2 | P131: NULL | Q131: 3 | R131: 0 | S131: NULL | T131: NULL | U131: 2 | V131: NULL | W131: NULL | X131: NULL | Y131: 18 | Z131: NULL
A132: 131 | D132: 1 | E132: 5 | F132: 27 | G132: =CONCATENATE(TEXT($E132,"00"),TEXT($F132,"000")) -> 05027 | H132: Columbia | I132: Arkansas | J132: AR | K132: =CONCATENATE(H132,", ",J132) -> Columbia, AR | L132: 14 | M132: 1.8461538 | N132: NULL | O132: 7 | P132: NULL | Q132: 17 | R132: 0 | S132: NULL | T132: NULL | U132: 13 | V132: NULL | W132: NULL | X132: NULL | Y132: 36 | Z132: NULL
... A193: 192 | D193: 1 | E193: 5 | F193: 149 | G193: =CONCATENATE(TEXT($E193,"00"),TEXT($F193,"000")) -> 05149 | H193: Yell | I193: Arkansas | J193: AR | K193: =CONCATENATE(H193,", ",J193) -> Yell, AR | L193: 28 | M193: 1.4545455 | N193: NULL | O193: 13 | P193: NULL | Q193: 19 | R193: 2 | S193: NULL | T193: NULL | U193: 19 | V193: NULL | W193: NULL | X193: NULL | Y193: 32 | Z193: NULL
A194: 193 | C194: 1 | E194: 6 | F194: 0 | G194: =CONCATENATE(TEXT($E194,"00"),TEXT($F194,"000")) -> 06000 | I194: California | J194: CA | L194: {=California!C62:Q62} -> 43633 | M194: NULL | N194: 18246 | O194: 15332 | P194: NULL | Q194: 34924 | R194: 8180 | S194: NULL | T194: NULL | U194: NULL | V194: NULL | W194: NULL | X194: NULL | Y194: NULL | Z194: NULL
A195: 194 | D195: 1 | E195: 6 | F195: 1 | G195: =CONCATENATE(TEXT($E195,"00"),TEXT($F195,"000")) -> 06001 | H195: Alameda | I195: California | J195: CA | K195: =CONCATENATE(H195,", ",J195) -> Alameda, CA | L195: {=California!C3:Q60} -> 916 | M195: NULL | N195: 294 | O195: 336 | P195: NULL | Q195: NULL | R195: 86 | S195: NULL | T195: 0.40648379 | U195: 295 | V195: NULL | W195: NULL | X195: NULL | Y195: 647 | Z195: NULL
A196: 195 | D196: 1 | E196: 6 | F196: 3 | G196: =CONCATENATE(TEXT($E196,"00"),TEXT($F196,"000")) -> 06003 | H196: Alpine | I196: California | J196: CA | K196: =CONCATENATE(H196,", ",J196) -> Alpine, CA | L196: 0 | M196: NULL | N196: 0 | O196: 0 | P196: NULL | Q196: NULL | R196: 0 | S196: NULL | T196: N/A | U196: 0 | V196: NULL | W196: NULL | X196: NULL | Y196: NULL | Z196: NULL
A197: 196 | D197: 1 | E197: 6 | F197: 5 | G197: =CONCATENATE(TEXT($E197,"00"),TEXT($F197,"000")) -> 06005 | H197: Amador | I197: California | J197: CA | K197: =CONCATENATE(H197,", ",J197) -> Amador, CA | L197: 54 | M197: NULL | N197: 22 | O197: 18 | P197: NULL | Q197: NULL | R197: * | S197: NULL | T197: N/A | U197: 0 | V197: NULL | W197: NULL | X197: NULL | Y197: 25 | Z197: NULL
A198: 197 | D198: 1 | E198: 6 | F198: 7 | G198: =CONCATENATE(TEXT($E198,"00"),TEXT($F198,"000")) -> 06007 | H198: Butte | I198: California | J198: CA | K198: =CONCATENATE(H198,", ",J198) -> Butte, CA | L198: 347 | M198: NULL | N198: 147 | O198: 92 | P198: NULL | Q198: NULL | R198: 104 | S198: NULL | T198: 0.48148148 | U198: 43 | V198: NULL | W198: NULL | X198: NULL | Y198: 118 | Z198: NULL
A199: 198 | D199: 1 | E199: 6 | F199: 9 | G199: =CONCATENATE(TEXT($E199,"00"),TEXT($F199,"000")) -> 06009 | H199: Calaveras | I199: California | J199: CA | K199: =CONCATENATE(H199,", ",J199) -> Calaveras, CA | L199: 53 | M199: NULL | N199: 26 | O199: 15 | P199: NULL | Q199: NULL | R199: * | S199: NULL | T199: 0.57692308 | U199: 25 | V199: NULL | W199: NULL | X199: NULL | Y199: 40 | Z199: NULL
A200: 199 | D200: 1 | E200: 6 | F200: 11 | G200: =CONCATENATE(TEXT($E200,"00"),TEXT($F200,"000")) -> 06011 | H200: Colusa | I200: California | J200: CA | K200: =CONCATENATE(H200,", ",J200) -> Colusa, CA | L200: 35 | M200: NULL | N200: 22 | O200: NULL | P200: NULL | Q200: NULL | R200: * | S200: NULL | T200: N/A | U200: 0 | V200: NULL | W200: NULL | X200: NULL | Y200: 20 | Z200: NULL
A201: 200 | D201: 1 | E201: 6 | F201: 13 | G201: =CONCATENATE(TEXT($E201,"00"),TEXT($F201,"000")) -> 06013 | H201: Contra Costa | I201: California | J201: CA | K201: =CONCATENATE(H201,", ",J201) -> Contra Costa, CA | L201: 513 | M201: NULL | N201: 219 | O201: 122 | P201: NULL | Q201: NULL | R201: 28 | S201: NULL | T201: 0.4535316 | U201: 188 | V201: NULL | W201: NULL | X201: NULL | Y201: 405 | Z201: NULL
A202: 201 | D202: 1 | E202: 6 | F202: 15 | G202: =CONCATENATE(TEXT($E202,"00"),TEXT($F202,"000")) -> 06015 | H202: Del Norte | I202: California | J202: CA | K202: =CONCATENATE(H202,", ",J202) -> Del Norte, CA | L202: 86 | M202: NULL | N202: 38 | O202: 17 | P202: NULL | Q202: NULL | R202: 11 | S202: NULL | T202: 0.64705882 | U202: 0 | V202: NULL | W202: NULL | X202: NULL | Y202: 23 | Z202: NULL
A203: 202 | D203: 1 | E203: 6 | F203: 17 | G203: =CONCATENATE(TEXT($E203,"00"),TEXT($F203,"000")) -> 06017 | H203: El Dorado | I203: California | J203: CA | K203: =CONCATENATE(H203,", ",J203) -> El Dorado, CA | L203: 99 | M203: NULL | N203: 32 | O203: 39 | P203: NULL | Q203: NULL | R203: * | S203: NULL | T203: 0.39240506 | U203: 85 | V203: NULL | W203: NULL | X203: NULL | Y203: 69 | Z203: NULL
A204: 203 | D204: 1 | E204: 6 | F204: 19 | G204: =CONCATENATE(TEXT($E204,"00"),TEXT($F204,"000")) -> 06019 | H204: Fresno | I204: California | J204: CA | K204: =CONCATENATE(H204,", ",J204) -> Fresno, CA | L204: 2093 | M204: NULL | N204: 979 | O204: 541 | P204: NULL | Q204: NULL | R204: 258 | S204: NULL | T204: 0.50347222 | U204: 207 | V204: NULL | W204: NULL | X204: NULL | Y204: 423 | Z204: NULL
A205: 204 | D205: 1 | E205: 6 | F205: 21 | G205: =CONCATENATE(TEXT($E205,"00"),TEXT($F205,"000")) -> 06021 | H205: Glenn | I205: California | J205: CA | K205: =CONCATENATE(H205,", ",J205) -> Glenn, CA | L205: 46 | M205: NULL | N205: NULL | O205: 14 | P205: NULL | Q205: NULL | R205: * | S205: NULL | T205: N/A | U205: 30 | V205: NULL | W205: NULL | X205: NULL | Y205: 27 | Z205: NULL
A206: 205 | D206: 1 | E206: 6 | F206: 23 | G206: =CONCATENATE(TEXT($E206,"00"),TEXT($F206,"000")) -> 06023 | H206: Humboldt | I206: California | J206: CA | K206: =CONCATENATE(H206,", ",J206) -> Humboldt, CA | L206: 281 | M206: NULL | N206: 78 | O206: 93 | P206: NULL | Q206: NULL | R206: 18 | S206: NULL | T206: 0.33333333 | U206: 135 | V206: NULL | W206: NULL | X206: NULL | Y206: 100 | Z206: NULL
A207: 206 | D207: 1 | E207: 6 | F207: 25 | G207: =CONCATENATE(TEXT($E207,"00"),TEXT($F207,"000")) -> 06025 | H207: Imperial | I207: California | J207: CA | K207: =CONCATENATE(H207,", ",J207) -> Imperial, CA | L207: 270 | M207: NULL | N207: 102 | O207: 102 | P207: NULL | Q207: NULL | R207: 56 | S207: NULL | T207: 0.53179191 | U207: 57 | V207: NULL | W207: NULL | X207: NULL | Y207: 72 | Z207: NULL
A208: 207 | D208: 1 | E208: 6 | F208: 27 | G208: =CONCATENATE(TEXT($E208,"00"),TEXT($F208,"000")) -> 06027 | H208: Inyo | I208: California | J208: CA | K208: =CONCATENATE(H208,", ",J208) -> Inyo, CA | L208: 33 | M208: NULL | N208: 12 | O208: 15 | P208: NULL | Q208: NULL | R208: 0 | S208: NULL | T208: N/A | U208: 0 | V208: NULL | W208: NULL | X208: NULL | Y208: 24 | Z208: NULL
A209: 208 | D209: 1 | E209: 6 | F209: 29 | G209: =CONCATENATE(TEXT($E209,"00"),TEXT($F209,"000")) -> 06029 | H209: Kern | I209: California | J209: CA | K209: =CONCATENATE(H209,", ",J209) -> Kern, CA | L209: 1728 | M209: NULL | N209: 881 | O209: 512 | P209: NULL | Q209: NULL | R209: 150 | S209: NULL | T209: 0.49001052 | U209: 307 | V209: NULL | W209: NULL | X209: NULL | Y209: 381 | Z209: NULL
A210: 209 | D210: 1 | E210: 6 | F210: 31 | G210: =CONCATENATE(TEXT($E210,"00"),TEXT($F210,"000")) -> 06031 | H210: Kings | I210: California | J210: CA | K210: =CONCATENATE(H210,", ",J210) -> Kings, CA | L210: 298 | M210: NULL | N210: 121 | O210: 124 | P210: NULL | Q210: NULL | R210: 12 | S210: NULL | T210: 0.41747573 | U210: 74 | V210: NULL | W210: NULL | X210: NULL | Y210: 60 | Z210: NULL
A211: 210 | D211: 1 | E211: 6 | F211: 33 | G211: =CONCATENATE(TEXT($E211,"00"),TEXT($F211,"000")) -> 06033 | H211: Lake | I211: California | J211: CA | K211: =CONCATENATE(H211,", ",J211) -> Lake, CA | L211: 69 | M211: NULL | N211: 17 | O211: 23 | P211: NULL | Q211: NULL | R211: * | S211: NULL | T211: N/A | U211: 0 | V211: NULL | W211: NULL | X211: NULL | Y211: 43 | Z211: NULL
A212: 211 | D212: 1 | E212: 6 | F212: 35 | G212: =CONCATENATE(TEXT($E212,"00"),TEXT($F212,"000")) -> 06035 | H212: Lassen | I212: California | J212: CA | K212: =CONCATENATE(H212,", ",J212) -> Lassen, CA | L212: 52 | M212: NULL | N212: 35 | O212: NULL | P212: NULL | Q212: NULL | R212: * | S212: NULL | T212: 0.62962963 | U212: 0 | V212: NULL | W212: NULL | X212: NULL | Y212: 29 | Z212: NULL
A213: 212 | D213: 1 | E213: 6 | F213: 37 | G213: =CONCATENATE(TEXT($E213,"00"),TEXT($F213,"000")) -> 06037 | H213: Los Angeles | I213: California | J213: CA | K213: =CONCATENATE(H213,", ",J213) -> Los Angeles, CA | L213: 15018 | M213: NULL | N213: 6150 | O213: 6029 | P213: NULL | Q213: NULL | R213: 3563 | S213: NULL | T213: 0.48168193 | U213: 6395 | V213: NULL | W213: NULL | X213: NULL | Y213: 3447 | Z213: NULL
A214: 213 | D214: 1 | E214: 6 | F214: 39 | G214: =CONCATENATE(TEXT($E214,"00"),TEXT($F214,"000")) -> 06039 | H214: Madera | I214: California | J214: CA | K214: =CONCATENATE(H214,", ",J214) -> Madera, CA | L214: 210 | M214: NULL | N214: 95 | O214: 57 | P214: NULL | Q214: NULL | R214: * | S214: NULL | T214: 0.50819672 | U214: 93 | V214: NULL | W214: NULL | X214: NULL | Y214: 67 | Z214: NULL
A215: 214 | D215: 1 | E215: 6 | F215: 41 | G215: =CONCATENATE(TEXT($E215,"00"),TEXT($F215,"000")) -> 06041 | H215: Marin | I215: California | J215: CA | K215: =CONCATENATE(H215,", ",J215) -> Marin, CA | L215: 69 | M215: NULL | N215: NULL | O215: 26 | P215: NULL | Q215: NULL | R215: * | S215: NULL | T215: 0.36585366 | U215: 31 | V215: NULL | W215: NULL | X215: NULL | Y215: 92 | Z215: NULL
A216: 215 | D216: 1 | E216: 6 | F216: 43 | G216: =CONCATENATE(TEXT($E216,"00"),TEXT($F216,"000")) -> 06043 | H216: Mariposa | I216: California | J216: CA | K216: =CONCATENATE(H216,", ",J216) -> Mariposa, CA | L216: 35 | M216: NULL | N216: 14 | O216: NULL | P216: NULL | Q216: NULL | R216: 0 | S216: NULL | T216: N/A | U216: 0 | V216: NULL | W216: NULL | X216: NULL | Y216: 20 | Z216: NULL
A217: 216 | D217: 1 | E217: 6 | F217: 45 | G217: =CONCATENATE(TEXT($E217,"00"),TEXT($F217,"000")) -> 06045 | H217: Mendocino | I217: California | J217: CA | K217: =CONCATENATE(H217,", ",J217) -> Mendocino, CA | L217: 205 | M217: NULL | N217: 94 | O217: 36 | P217: NULL | Q217: NULL | R217: * | S217: NULL | T217: 0.5472973 | U217: 60 | V217: NULL | W217: NULL | X217: NULL | Y217: 53 | Z217: NULL
A218: 217 | D218: 1 | E218: 6 | F218: 47 | G218: =CONCATENATE(TEXT($E218,"00"),TEXT($F218,"000")) -> 06047 | H218: Merced | I218: California | J218: CA | K218: =CONCATENATE(H218,", ",J218) -> Merced, CA | L218: 615 | M218: NULL | N218: 285 | O218: 224 | P218: NULL | Q218: NULL | R218: 81 | S218: NULL | T218: 0.58744395 | U218: 76 | V218: NULL | W218: NULL | X218: NULL | Y218: 111 | Z218: NULL
A219: 218 | D219: 1 | E219: 6 | F219: 49 | G219: =CONCATENATE(TEXT($E219,"00"),TEXT($F219,"000")) -> 06049 | H219: Modoc | I219: California | J219: CA | K219: =CONCATENATE(H219,", ",J219) -> Modoc, CA | L219: 18 | M219: NULL | N219: NULL | O219: NULL | P219: NULL | Q219: NULL | R219: * | S219: NULL | T219: 0.9 | U219: 12 | V219: NULL | W219: NULL | X219: NULL | Y219: 12 | Z219: NULL
A220: 219 | D220: 1 | E220: 6 | F220: 51 | G220: =CONCATENATE(TEXT($E220,"00"),TEXT($F220,"000")) -> 06051 | H220: Mono | I220: California | J220: CA | K220: =CONCATENATE(H220,", ",J220) -> Mono, CA | L220: M | M220: NULL | N220: NULL | O220: NULL | P220: NULL | Q220: NULL | R220: 0 | S220: NULL | T220: N/A | U220: 0 | V220: NULL | W220: NULL | X220: NULL | Y220: 12 | Z220: NULL
A221: 220 | D221: 1 | E221: 6 | F221: 53 | G221: =CONCATENATE(TEXT($E221,"00"),TEXT($F221,"000")) -> 06053 | H221: Monterey | I221: California | J221: CA | K221: =CONCATENATE(H221,", ",J221) -> Monterey, CA | L221: 161 | M221: NULL | N221: 84 | O221: 32 | P221: NULL | Q221: NULL | R221: * | S221: NULL | T221: 0.33766234 | U221: 57 | V221: NULL | W221: NULL | X221: NULL | Y221: 173 | Z221: NULL
A222: 221 | D222: 1 | E222: 6 | F222: 55 | G222: =CONCATENATE(TEXT($E222,"00"),TEXT($F222,"000")) -> 06055 | H222: Napa | I222: California | J222: CA | K222: =CONCATENATE(H222,", ",J222) -> Napa, CA | L222: 61 | M222: NULL | N222: 15 | O222: 19 | P222: NULL | Q222: NULL | R222: 16 | S222: NULL | T222: 0.48275862 | U222: 32 | V222: NULL | W222: NULL | X222: NULL | Y222: 50 | Z222: NULL
A223: 222 | D223: 1 | E223: 6 | F223: 57 | G223: =CONCATENATE(TEXT($E223,"00"),TEXT($F223,"000")) -> 06057 | H223: Nevada | I223: California | J223: CA | K223: =CONCATENATE(H223,", ",J223) -> Nevada, CA | L223: 36 | M223: NULL | N223: 11 | O223: 13 | P223: NULL | Q223: NULL | R223: * | S223: NULL | T223: N/A | U223: 0 | V223: NULL | W223: NULL | X223: NULL | Y223: 44 | Z223: NULL
A224: 223 | D224: 1 | E224: 6 | F224: 59 | G224: =CONCATENATE(TEXT($E224,"00"),TEXT($F224,"000")) -> 06059 | H224: Orange | I224: California | J224: CA | K224: =CONCATENATE(H224,", ",J224) -> Orange, CA | L224: 2205 | M224: NULL | N224: 543 | O224: 1107 | P224: NULL | Q224: NULL | R224: 344 | S224: NULL | T224: 0.52457695 | U224: 1069 | V224: NULL | W224: NULL | X224: NULL | Y224: 856 | Z224: NULL
A225: 224 | D225: 1 | E225: 6 | F225: 61 | G225: =CONCATENATE(TEXT($E225,"00"),TEXT($F225,"000")) -> 06061 | H225: Placer | I225: California | J225: CA | K225: =CONCATENATE(H225,", ",J225) -> Placer, CA | L225: 153 | M225: NULL | N225: 51 | O225: 56 | P225: NULL | Q225: NULL | R225: * | S225: NULL | T225: 0.55445545 | U225: 58 | V225: NULL | W225: NULL | X225: NULL | Y225: 142 | Z225: NULL
A226: 225 | D226: 1 | E226: 6 | F226: 63 | G226: =CONCATENATE(TEXT($E226,"00"),TEXT($F226,"000")) -> 06063 | H226: Plumas | I226: California | J226: CA | K226: =CONCATENATE(H226,", ",J226) -> Plumas, CA | L226: 22 | M226: NULL | N226: NULL | O226: NULL | P226: NULL | Q226: NULL | R226: * | S226: NULL | T226: 0.72727273 | U226: 14 | V226: NULL | W226: NULL | X226: NULL | Y226: 28 | Z226: NULL
...

Sheet Sheet75
A2: Alabama | B2: TOTAL | C2: =CONCATENATE("'",A2,"'!A:A") -> 'Alabama'!A:A | E2: =MATCH(B2,C2) -> 1
A3: Alaska | C3: =CONCATENATE("'",A3,"'!A:Q") -> 'Alaska'!A:Q | D3: =ROWS(C3) -> 1
A4: Arizona | C4: =CONCATENATE("'",A4,"'!A:Q") -> 'Arizona'!A:Q | D4: =ROWS(C4) -> 1
A5: Arkansas | C5: =CONCATENATE("'",A5,"'!A:Q") -> 'Arkansas'!A:Q | D5: =ROWS(C5) -> 1
A6: California | C6: =CONCATENATE("'",A6,"'!A:Q") -> 'California'!A:Q | D6: =ROWS(C6) -> 1
A7: Colorado | C7: =CONCATENATE("'",A7,"'!A:Q") -> 'Colorado'!A:Q | D7: =ROWS(C7) -> 1
A8: Connecticut | C8: =CONCATENATE("'",A8,"'!A:Q") -> 'Connecticut'!A:Q | D8: =ROWS(C8) -> 1
A9: District of Columbia | C9: =CONCATENATE("'",A9,"'!A:Q") -> 'District of Columbia'!A:Q | D9: =ROWS(C9) -> 1
A10: Delaware | C10: =CONCATENATE("'",A10,"'!A:Q") -> 'Delaware'!A:Q | D10: =ROWS(C10) -> 1
A11: Florida | C11: =CONCATENATE("'",A11,"'!A:Q") -> 'Florida'!A:Q | D11: =ROWS(C11) -> 1
A12: Georgia | C12: =CONCATENATE("'",A12,"'!A:Q") -> 'Georgia'!A:Q | D12: =ROWS(C12) -> 1
A13: Hawaii | C13: =CONCATENATE("'",A13,"'!A:Q") -> 'Hawaii'!A:Q | D13: =ROWS(C13) -> 1
A14: Idaho | C14: =CONCATENATE("'",A14,"'!A:Q") -> 'Idaho'!A:Q | D14: =ROWS(C14) -> 1
... A52: Wyoming | C52: =CONCATENATE("'",A52,"'!A:Q") -> 'Wyoming'!A:Q | D52: =ROWS(C52) -> 1

Sheet Metrics Check
A1: id | B1: is_national | C1: is_state | D1: is_county | E1: state_code | F1: county_code | G1: county_state_code | H1: county_name | I1: state_name_full | J1: state_name_abv | K1: county_state | L1: Number of Foster & Kinship Families Needed | M1: MTE Index
A2: 1 | B2: 1
A3: 2 | C3: 1 | E3: 1 | I3: Alabama | J3: AL
A4: 3 | D4: 1 | E4: 1 | F4: 1 | G4: =CONCATENATE(TEXT($E4,"00"),TEXT($F4,"000")) -> 01001 | H4: Autauga | I4: Alabama | J4: AL | K4: =CONCATENATE(H4,", ",J4) -> Autauga, AL
A5: 4 | D5: 1 | E5: 1 | F5: 3 | G5: =CONCATENATE(TEXT($E5,"00"),TEXT($F5,"000")) -> 01003 | H5: Baldwin | I5: Alabama | J5: AL | K5: =CONCATENATE(H5,", ",J5) -> Baldwin, AL
A6: 5 | D6: 1 | E6: 1 | F6: 5 | G6: =CONCATENATE(TEXT($E6,"00"),TEXT($F6,"000")) -> 01005 | H6: Barbour | I6: Alabama | J6: AL | K6: =CONCATENATE(H6,", ",J6) -> Barbour, AL
A7: 6 | D7: 1 | E7: 1 | F7: 7 | G7: =CONCATENATE(TEXT($E7,"00"),TEXT($F7,"000")) -> 01007 | H7: Bibb | I7: Alabama | J7: AL | K7: =CONCATENATE(H7,", ",J7) -> Bibb, AL
A8: 7 | D8: 1 | E8: 1 | F8: 9 | G8: =CONCATENATE(TEXT($E8,"00"),TEXT($F8,"000")) -> 01009 | H8: Blount | I8: Alabama | J8: AL | K8: =CONCATENATE(H8,", ",J8) -> Blount, AL
A9: 8 | D9: 1 | E9: 1 | F9: 11 | G9: =CONCATENATE(TEXT($E9,"00"),TEXT($F9,"000")) -> 01011 | H9: Bullock | I9: Alabama | J9: AL | K9: =CONCATENATE(H9,", ",J9) -> Bullock, AL
A10: 9 | D10: 1 | E10: 1 | F10: 13 | G10: =CONCATENATE(TEXT($E10,"00"),TEXT($F10,"000")) -> 01013 | H10: Butler | I10: Alabama | J10: AL | K10: =CONCATENATE(H10,", ",J10) -> Butler, AL
A11: 10 | D11: 1 | E11: 1 | F11: 15 | G11: =CONCATENATE(TEXT($E11,"00"),TEXT($F11,"000")) -> 01015 | H11: Calhoun | I11: Alabama | J11: AL | K11: =CONCATENATE(H11,", ",J11) -> Calhoun, AL
A12: 11 | D12: 1 | E12: 1 | F12: 17 | G12: =CONCATENATE(TEXT($E12,"00"),TEXT($F12,"000")) -> 01017 | H12: Chambers | I12: Alabama | J12: AL | K12: =CONCATENATE(H12,", ",J12) -> Chambers, AL
A13: 12 | D13: 1 | E13: 1 | F13: 19 | G13: =CONCATENATE(TEXT($E13,"00"),TEXT($F13,"000")) -> 01019 | H13: Cherokee | I13: Alabama | J13: AL | K13: =CONCATENATE(H13,", ",J13) -> Cherokee, AL
A14: 13 | D14: 1 | E14: 1 | F14: 21 | G14: =CONCATENATE(TEXT($E14,"00"),TEXT($F14,"000")) -> 01021 | H14: Chilton | I14: Alabama | J14: AL | K14: =CONCATENATE(H14,", ",J14) -> Chilton, AL
A15: 14 | D15: 1 | E15: 1 | F15: 23 | G15: =CONCATENATE(TEXT($E15,"00"),TEXT($F15,"000")) -> 01023 | H15: Choctaw | I15: Alabama | J15: AL | K15: =CONCATENATE(H15,", ",J15) -> Choctaw, AL
... A70: 69 | D70: 1 | E70: 1 | F70: 133 | G70: =CONCATENATE(TEXT($E70,"00"),TEXT($F70,"000")) -> 01133 | H70: Winston | I70: Alabama | J70: AL | K70: =CONCATENATE(H70,", ",J70) -> Winston, AL
A71: 70 | C71: 1 | E71: 2 | G71: =CONCATENATE(TEXT($E71,"00"),TEXT($F71,"000")) -> 02000 | I71: Alaska | J71: AK
A72: 71 | D72: 1 | E72: 2 | F72: 13 | G72: =CONCATENATE(TEXT($E72,"00"),TEXT($F72,"000")) -> 02013 | H72: Aleutians East | I72: Alaska | J72: AK | K72: =CONCATENATE(H72,", ",J72) -> Aleutians East, AK
A73: 72 | D73: 1 | E73: 2 | F73: 16 | G73: =CONCATENATE(TEXT($E73,"00"),TEXT($F73,"000")) -> 02016 | H73: Aleutians West | I73: Alaska | J73: AK | K73: =CONCATENATE(H73,", ",J73) -> Aleutians West, AK
A74: 73 | D74: 1 | E74: 2 | F74: 20 | G74: =CONCATENATE(TEXT($E74,"00"),TEXT($F74,"000")) -> 02020 | H74: Anchorage | I74: Alaska | J74: AK | K74: =CONCATENATE(H74,", ",J74) -> Anchorage, AK
A75: 74 | D75: 1 | E75: 2 | F75: 50 | G75: =CONCATENATE(TEXT($E75,"00"),TEXT($F75,"000")) -> 02050 | H75: Bethel | I75: Alaska | J75: AK | K75: =CONCATENATE(H75,", ",J75) -> Bethel, AK
A76: 75 | D76: 1 | E76: 2 | F76: 60 | G76: =CONCATENATE(TEXT($E76,"00"),TEXT($F76,"000")) -> 02060 | H76: Bristol Bay | I76: Alaska | J76: AK | K76: =CONCATENATE(H76,", ",J76) -> Bristol Bay, AK
A77: 76 | D77: 1 | E77: 2 | F77: 63 | G77: =CONCATENATE(TEXT($E77,"00"),TEXT($F77,"000")) -> 02063 | H77: Chugach | I77: Alaska | J77: AK | K77: =CONCATENATE(H77,", ",J77) -> Chugach, AK
A78: 77 | D78: 1 | E78: 2 | F78: 66 | G78: =CONCATENATE(TEXT($E78,"00"),TEXT($F78,"000")) -> 02066 | H78: Copper River | I78: Alaska | J78: AK | K78: =CONCATENATE(H78,", ",J78) -> Copper River, AK
A79: 78 | D79: 1 | E79: 2 | F79: 68 | G79: =CONCATENATE(TEXT($E79,"00"),TEXT($F79,"000")) -> 02068 | H79: Denali | I79: Alaska | J79: AK | K79: =CONCATENATE(H79,", ",J79) -> Denali, AK
A80: 79 | D80: 1 | E80: 2 | F80: 70 | G80: =CONCATENATE(TEXT($E80,"00"),TEXT($F80,"000")) -> 02070 | H80: Dillingham | I80: Alaska | J80: AK | K80: =CONCATENATE(H80,", ",J80) -> Dillingham, AK
A81: 80 | D81: 1 | E81: 2 | F81: 90 | G81: =CONCATENATE(TEXT($E81,"00"),TEXT($F81,"000")) -> 02090 | H81: Fairbanks North Star | I81: Alaska | J81: AK | K81: =CONCATENATE(H81,", ",J81) -> Fairbanks North Star, AK
A82: 81 | D82: 1 | E82: 2 | F82: 100 | G82: =CONCATENATE(TEXT($E82,"00"),TEXT($F82,"000")) -> 02100 | H82: Haines | I82: Alaska | J82: AK | K82: =CONCATENATE(H82,", ",J82) -> Haines, AK
A83: 82 | D83: 1 | E83: 2 | F83: 105 | G83: =CONCATENATE(TEXT($E83,"00"),TEXT($F83,"000")) -> 02105 | H83: Hoonah-Angoon | I83: Alaska | J83: AK | K83: =CONCATENATE(H83,", ",J83) -> Hoonah-Angoon, AK
... A101: 100 | D101: 1 | E101: 2 | F101: 290 | G101: =CONCATENATE(TEXT($E101,"00"),TEXT($F101,"000")) -> 02290 | H101: Yukon-Koyukuk | I101: Alaska | J101: AK | K101: =CONCATENATE(H101,", ",J101) -> Yukon-Koyukuk, AK
A102: 101 | C102: 1 | E102: 4 | G102: =CONCATENATE(TEXT($E102,"00"),TEXT($F102,"000")) -> 04000 | I102: Arizona | J102: AZ
A103: 102 | D103: 1 | E103: 4 | F103: 1 | G103: =CONCATENATE(TEXT($E103,"00"),TEXT($F103,"000")) -> 04001 | H103: Apache | I103: Arizona | J103: AZ | K103: =CONCATENATE(H103,", ",J103) -> Apache, AZ
A104: 103 | D104: 1 | E104: 4 | F104: 3 | G104: =CONCATENATE(TEXT($E104,"00"),TEXT($F104,"000")) -> 04003 | H104: Cochise | I104: Arizona | J104: AZ | K104: =CONCATENATE(H104,", ",J104) -> Cochise, AZ
A105: 104 | D105: 1 | E105: 4 | F105: 5 | G105: =CONCATENATE(TEXT($E105,"00"),TEXT($F105,"000")) -> 04005 | H105: Coconino | I105: Arizona | J105: AZ | K105: =CONCATENATE(H105,", ",J105) -> Coconino, AZ
A106: 105 | D106: 1 | E106: 4 | F106: 7 | G106: =CONCATENATE(TEXT($E106,"00"),TEXT($F106,"000")) -> 04007 | H106: Gila | I106: Arizona | J106: AZ | K106: =CONCATENATE(H106,", ",J106) -> Gila, AZ
A107: 106 | D107: 1 | E107: 4 | F107: 9 | G107: =CONCATENATE(TEXT($E107,"00"),TEXT($F107,"000")) -> 04009 | H107: Graham | I107: Arizona | J107: AZ | K107: =CONCATENATE(H107,", ",J107) -> Graham, AZ
A108: 107 | D108: 1 | E108: 4 | F108: 11 | G108: =CONCATENATE(TEXT($E108,"00"),TEXT($F108,"000")) -> 04011 | H108: Greenlee | I108: Arizona | J108: AZ | K108: =CONCATENATE(H108,", ",J108) -> Greenlee, AZ
A109: 108 | D109: 1 | E109: 4 | F109: 12 | G109: =CONCATENATE(TEXT($E109,"00"),TEXT($F109,"000")) -> 04012 | H109: La Paz | I109: Arizona | J109: AZ | K109: =CONCATENATE(H109,", ",J109) -> La Paz, AZ
A110: 109 | D110: 1 | E110: 4 | F110: 13 | G110: =CONCATENATE(TEXT($E110,"00"),TEXT($F110,"000")) -> 04013 | H110: Maricopa | I110: Arizona | J110: AZ | K110: =CONCATENATE(H110,", ",J110) -> Maricopa, AZ
A111: 110 | D111: 1 | E111: 4 | F111: 15 | G111: =CONCATENATE(TEXT($E111,"00"),TEXT($F111,"000")) -> 04015 | H111: Mohave | I111: Arizona | J111: AZ | K111: =CONCATENATE(H111,", ",J111) -> Mohave, AZ
A112: 111 | D112: 1 | E112: 4 | F112: 17 | G112: =CONCATENATE(TEXT($E112,"00"),TEXT($F112,"000")) -> 04017 | H112: Navajo | I112: Arizona | J112: AZ | K112: =CONCATENATE(H112,", ",J112) -> Navajo, AZ
A113: 112 | D113: 1 | E113: 4 | F113: 19 | G113: =CONCATENATE(TEXT($E113,"00"),TEXT($F113,"000")) -> 04019 | H113: Pima | I113: Arizona | J113: AZ | K113: =CONCATENATE(H113,", ",J113) -> Pima, AZ
A114: 113 | D114: 1 | E114: 4 | F114: 21 | G114: =CONCATENATE(TEXT($E114,"00"),TEXT($F114,"000")) -> 04021 | H114: Pinal | I114: Arizona | J114: AZ | K114: =CONCATENATE(H114,", ",J114) -> Pinal, AZ
A115: 114 | D115: 1 | E115: 4 | F115: 23 | G115: =CONCATENATE(TEXT($E115,"00"),TEXT($F115,"000")) -> 04023 | H115: Santa Cruz | I115: Arizona | J115: AZ | K115: =CONCATENATE(H115,", ",J115) -> Santa Cruz, AZ | N115: [(Number of Children in Kinship Care + (Number of Children in Care - Number of Children Placed Out-of-County)) / Average Beds per Family] + (Number of Children Placed Out of County)
A116: 115 | D116: 1 | E116: 4 | F116: 25 | G116: =CONCATENATE(TEXT($E116,"00"),TEXT($F116,"000")) -> 04025 | H116: Yavapai | I116: Arizona | J116: AZ | K116: =CONCATENATE(H116,", ",J116) -> Yavapai, AZ | N116: [(Number of Children in Care - Number of Children Out-of-County) / Average Beds] + Number of Children Placed out-of-county
A117: 116 | D117: 1 | E117: 4 | F117: 27 | G117: =CONCATENATE(TEXT($E117,"00"),TEXT($F117,"000")) -> 04027 | H117: Yuma | I117: Arizona | J117: AZ | K117: =CONCATENATE(H117,", ",J117) -> Yuma, AZ
A118: 117 | C118: 1 | E118: 5 | F118: 0 | G118: =CONCATENATE(TEXT($E118,"00"),TEXT($F118,"000")) -> 05000 | I118: Arkansas | J118: AR | N118: *Tested with 2.00 multiplier
A119: 118 | D119: 1 | E119: 5 | F119: 1 | G119: =CONCATENATE(TEXT($E119,"00"),TEXT($F119,"000")) -> 05001 | H119: Arkansas | I119: Arkansas | J119: AR | K119: =CONCATENATE(H119,", ",J119) -> Arkansas, AR | L119: =(vlookup(H119,'AR Data'!$A$3:$P$84,16,FALSE)/Arkansas!D3)+(vlookup(H119,'AR Data'!$A$3:$R$84,18,FALSE)) -> 11.888889 | M119: ='All Data Connect'!Q119/L119 -> 0.42056075 | N119: =(vlookup(H119,'AR Data'!$A$3:$P$84,16,FALSE)/Arkansas!D3)+((vlookup(H119,'AR Data'!$A$3:$R$84,18,FALSE)*2)) -> 19.888889 | O119: ='All Data Connect'!Q119/N119 -> 0.25139665
A120: 119 | D120: 1 | E120: 5 | F120: 3 | G120: =CONCATENATE(TEXT($E120,"00"),TEXT($F120,"000")) -> 05003 | H120: Ashley | I120: Arkansas | J120: AR | K120: =CONCATENATE(H120,", ",J120) -> Ashley, AR | L120: =(vlookup(H120,'AR Data'!$A$3:$P$84,16,FALSE)/Arkansas!D4)+(vlookup(H120,'AR Data'!$A$3:$R$84,18,FALSE)) -> 6.9375 | M120: ='All Data Connect'!Q120/L120 -> 2.1621622 | N120: =(vlookup(H120,'AR Data'!$A$3:$P$84,16,FALSE)/Arkansas!D4)+((vlookup(H120,'AR Data'!$A$3:$R$84,18,FALSE)*2)) -> 9.9375 | O120: ='All Data Connect'!Q120/N120 -> 1.509434
A121: 120 | D121: 1 | E121: 5 | F121: 5 | G121: =CONCATENATE(TEXT($E121,"00"),TEXT($F121,"000")) -> 05005 | H121: Baxter | I121: Arkansas | J121: AR | K121: =CONCATENATE(H121,", ",J121) -> Baxter, AR | L121: =(vlookup(H121,'AR Data'!$A$3:$P$84,16,FALSE)/Arkansas!D5)+(vlookup(H121,'AR Data'!$A$3:$R$84,18,FALSE)) -> 22.5 | M121: ='All Data Connect'!Q121/L121 -> 1.2 | N121: =(vlookup(H121,'AR Data'!$A$3:$P$84,16,FALSE)/Arkansas!D5)+((vlookup(H121,'AR Data'!$A$3:$R$84,18,FALSE)*2)) -> 34.5 | O121: ='All Data Connect'!Q121/N121 -> 0.7826087
A122: 121 | D122: 1 | E122: 5 | F122: 7 | G122: =CONCATENATE(TEXT($E122,"00"),TEXT($F122,"000")) -> 05007 | H122: Benton | I122: Arkansas | J122: AR | K122: =CONCATENATE(H122,", ",J122) -> Benton, AR | L122: =(vlookup(H122,'AR Data'!$A$3:$P$84,16,FALSE)/Arkansas!D6)+(vlookup(H122,'AR Data'!$A$3:$R$84,18,FALSE)) -> 94.115607 | M122: ='All Data Connect'!Q122/L122 -> 1.200651 | N122: =(vlookup(H122,'AR Data'!$A$3:$P$84,16,FALSE)/Arkansas!D6)+((vlookup(H122,'AR Data'!$A$3:$R$84,18,FALSE)*2)) -> 152.11561 | O122: ='All Data Connect'!Q122/N122 -> 0.74285606
A123: 122 | D123: 1 | E123: 5 | F123: 9 | G123: =CONCATENATE(TEXT($E123,"00"),TEXT($F123,"000")) -> 05009 | H123: Boone | I123: Arkansas | J123: AR | K123: =CONCATENATE(H123,", ",J123) -> Boone, AR | L123: =(vlookup(H123,'AR Data'!$A$3:$P$84,16,FALSE)/Arkansas!D7)+(vlookup(H123,'AR Data'!$A$3:$R$84,18,FALSE)) -> 26.170213 | M123: ='All Data Connect'!Q123/L123 -> 1.0317073 | N123: =(vlookup(H123,'AR Data'!$A$3:$P$84,16,FALSE)/Arkansas!D7)+((vlookup(H123,'AR Data'!$A$3:$R$84,18,FALSE)*2)) -> 41.170213 | O123: ='All Data Connect'!Q123/N123 -> 0.65581395
A124: 123 | D124: 1 | E124: 5 | F124: 11 | G124: =CONCATENATE(TEXT($E124,"00"),TEXT($F124,"000")) -> 05011 | H124: Bradley | I124: Arkansas | J124: AR | K124: =CONCATENATE(H124,", ",J124) -> Bradley, AR | L124: =(vlookup(H124,'AR Data'!$A$3:$P$84,16,FALSE)/Arkansas!D8)+(vlookup(H124,'AR Data'!$A$3:$R$84,18,FALSE)) -> 4.2222222 | M124: ='All Data Connect'!Q124/L124 -> 1.6578947 | N124: =(vlookup(H124,'AR Data'!$A$3:$P$84,16,FALSE)/Arkansas!D8)+((vlookup(H124,'AR Data'!$A$3:$R$84,18,FALSE)*2)) -> 6.2222222 | O124: ='All Data Connect'!Q124/N124 -> 1.125
A125: 124 | D125: 1 | E125: 5 | F125: 13 | G125: =CONCATENATE(TEXT($E125,"00"),TEXT($F125,"000")) -> 05013 | H125: Calhoun | I125: Arkansas | J125: AR | K125: =CONCATENATE(H125,", ",J125) -> Calhoun, AR | L125: =(vlookup(H125,'AR Data'!$A$3:$P$84,16,FALSE)/Arkansas!D9)+(vlookup(H125,'AR Data'!$A$3:$R$84,18,FALSE)) -> 0.75 | M125: ='All Data Connect'!Q125/L125 -> 6.6666667 | N125: =(vlookup(H125,'AR Data'!$A$3:$P$84,16,FALSE)/Arkansas!D9)+((vlookup(H125,'AR Data'!$A$3:$R$84,18,FALSE)*2)) -> 0.75 | O125: ='All Data Connect'!Q125/N125 -> 6.6666667
A126: 125 | D126: 1 | E126: 5 | F126: 15 | G126: =CONCATENATE(TEXT($E126,"00"),TEXT($F126,"000")) -> 05015 | H126: Carroll | I126: Arkansas | J126: AR | K126: =CONCATENATE(H126,", ",J126) -> Carroll, AR | L126: =(vlookup(H126,'AR Data'!$A$3:$P$84,16,FALSE)/Arkansas!D10)+(vlookup(H126,'AR Data'!$A$3:$R$84,18,FALSE)) -> 25 | M126: ='All Data Connect'!Q126/L126 -> 0.36 | N126: =(vlookup(H126,'AR Data'!$A$3:$P$84,16,FALSE)/Arkansas!D10)+((vlookup(H126,'AR Data'!$A$3:$R$84,18,FALSE)*2)) -> 45 | O126: ='All Data Connect'!Q126/N126 -> 0.2
A127: 126 | D127: 1 | E127: 5 | F127: 17 | G127: =CONCATENATE(TEXT($E127,"00"),TEXT($F127,"000")) -> 05017 | H127: Chicot | I127: Arkansas | J127: AR | K127: =CONCATENATE(H127,", ",J127) -> Chicot, AR | L127: =(vlookup(H127,'AR Data'!$A$3:$P$84,16,FALSE)/Arkansas!D11)+(vlookup(H127,'AR Data'!$A$3:$R$84,18,FALSE)) -> 6 | M127: ='All Data Connect'!Q127/L127 -> 0.83333333 | N127: =(vlookup(H127,'AR Data'!$A$3:$P$84,16,FALSE)/Arkansas!D11)+((vlookup(H127,'AR Data'!$A$3:$R$84,18,FALSE)*2)) -> 11 | O127: ='All Data Connect'!Q127/N127 -> 0.45454545
A128: 127 | D128: 1 | E128: 5 | F128: 19 | G128: =CONCATENATE(TEXT($E128,"00"),TEXT($F128,"000")) -> 05019 | H128: Clark | I128: Arkansas | J128: AR | K128: =CONCATENATE(H128,", ",J128) -> Clark, AR | L128: =(vlookup(H128,'AR Data'!$A$3:$P$84,16,FALSE)/Arkansas!D12)+(vlookup(H128,'AR Data'!$A$3:$R$84,18,FALSE)) -> 9.0909091 | M128: ='All Data Connect'!Q128/L128 -> 2.09 | N128: =(vlookup(H128,'AR Data'!$A$3:$P$84,16,FALSE)/Arkansas!D12)+((vlookup(H128,'AR Data'!$A$3:$R$84,18,FALSE)*2)) -> 15.090909 | O128: ='All Data Connect'!Q128/N128 -> 1.2590361
A129: 128 | D129: 1 | E129: 5 | F129: 21 | G129: =CONCATENATE(TEXT($E129,"00"),TEXT($F129,"000")) -> 05021 | H129: Clay | I129: Arkansas | J129: AR | K129: =CONCATENATE(H129,", ",J129) -> Clay, AR | L129: =(vlookup(H129,'AR Data'!$A$3:$P$84,16,FALSE)/Arkansas!D13)+(vlookup(H129,'AR Data'!$A$3:$R$84,18,FALSE)) -> 6.7777778 | M129: ='All Data Connect'!Q129/L129 -> 1.4754098 | N129: =(vlookup(H129,'AR Data'!$A$3:$P$84,16,FALSE)/Arkansas!D13)+((vlookup(H129,'AR Data'!$A$3:$R$84,18,FALSE)*2)) -> 7.7777778 | O129: ='All Data Connect'!Q129/N129 -> 1.2857143
A130: 129 | D130: 1 | E130: 5 | F130: 23 | G130: =CONCATENATE(TEXT($E130,"00"),TEXT($F130,"000")) -> 05023 | H130: Cleburne | I130: Arkansas | J130: AR | K130: =CONCATENATE(H130,", ",J130) -> Cleburne, AR | L130: =(vlookup(H130,'AR Data'!$A$3:$P$84,16,FALSE)/Arkansas!D14)+(vlookup(H130,'AR Data'!$A$3:$R$84,18,FALSE)) -> 30.347826 | M130: ='All Data Connect'!Q130/L130 -> 0.49426934 | N130: =(vlookup(H130,'AR Data'!$A$3:$P$84,16,FALSE)/Arkansas!D14)+((vlookup(H130,'AR Data'!$A$3:$R$84,18,FALSE)*2)) -> 52.347826 | O130: ='All Data Connect'!Q130/N130 -> 0.28654485
... A193: 192 | D193: 1 | E193: 5 | F193: 149 | G193: =CONCATENATE(TEXT($E193,"00"),TEXT($F193,"000")) -> 05149 | H193: Yell | I193: Arkansas | J193: AR | K193: =CONCATENATE(H193,", ",J193) -> Yell, AR | L193: =(vlookup(H193,'AR Data'!$A$3:$P$84,16,FALSE)/Arkansas!D77)+(vlookup(H193,'AR Data'!$A$3:$R$84,18,FALSE)) -> 23.625 | M193: ='All Data Connect'!Q193/L193 -> 0.8042328 | N193: =(vlookup(H193,'AR Data'!$A$3:$P$84,16,FALSE)/Arkansas!D77)+((vlookup(H193,'AR Data'!$A$3:$R$84,18,FALSE)*2)) -> 37.625 | O193: ='All Data Connect'!Q193/N193 -> 0.50498339
A194: 193 | C194: 1 | E194: 6 | F194: 0 | G194: =CONCATENATE(TEXT($E194,"00"),TEXT($F194,"000")) -> 06000 | I194: California | J194: CA
A195: 194 | D195: 1 | E195: 6 | F195: 1 | G195: =CONCATENATE(TEXT($E195,"00"),TEXT($F195,"000")) -> 06001 | H195: Alameda | I195: California | J195: CA | K195: =CONCATENATE(H195,", ",J195) -> Alameda, CA
A196: 195 | D196: 1 | E196: 6 | F196: 3 | G196: =CONCATENATE(TEXT($E196,"00"),TEXT($F196,"000")) -> 06003 | H196: Alpine | I196: California | J196: CA | K196: =CONCATENATE(H196,", ",J196) -> Alpine, CA
A197: 196 | D197: 1 | E197: 6 | F197: 5 | G197: =CONCATENATE(TEXT($E197,"00"),TEXT($F197,"000")) -> 06005 | H197: Amador | I197: California | J197: CA | K197: =CONCATENATE(H197,", ",J197) -> Amador, CA
A198: 197 | D198: 1 | E198: 6 | F198: 7 | G198: =CONCATENATE(TEXT($E198,"00"),TEXT($F198,"000")) -> 06007 | H198: Butte | I198: California | J198: CA | K198: =CONCATENATE(H198,", ",J198) -> Butte, CA
A199: 198 | D199: 1 | E199: 6 | F199: 9 | G199: =CONCATENATE(TEXT($E199,"00"),TEXT($F199,"000")) -> 06009 | H199: Calaveras | I199: California | J199: CA | K199: =CONCATENATE(H199,", ",J199) -> Calaveras, CA
A200: 199 | D200: 1 | E200: 6 | F200: 11 | G200: =CONCATENATE(TEXT($E200,"00"),TEXT($F200,"000")) -> 06011 | H200: Colusa | I200: California | J200: CA | K200: =CONCATENATE(H200,", ",J200) -> Colusa, CA
A201: 200 | D201: 1 | E201: 6 | F201: 13 | G201: =CONCATENATE(TEXT($E201,"00"),TEXT($F201,"000")) -> 06013 | H201: Contra Costa | I201: California | J201: CA | K201: =CONCATENATE(H201,", ",J201) -> Contra Costa, CA
A202: 201 | D202: 1 | E202: 6 | F202: 15 | G202: =CONCATENATE(TEXT($E202,"00"),TEXT($F202,"000")) -> 06015 | H202: Del Norte | I202: California | J202: CA | K202: =CONCATENATE(H202,", ",J202) -> Del Norte, CA
A203: 202 | D203: 1 | E203: 6 | F203: 17 | G203: =CONCATENATE(TEXT($E203,"00"),TEXT($F203,"000")) -> 06017 | H203: El Dorado | I203: California | J203: CA | K203: =CONCATENATE(H203,", ",J203) -> El Dorado, CA
A204: 203 | D204: 1 | E204: 6 | F204: 19 | G204: =CONCATENATE(TEXT($E204,"00"),TEXT($F204,"000")) -> 06019 | H204: Fresno | I204: California | J204: CA | K204: =CONCATENATE(H204,", ",J204) -> Fresno, CA
A205: 204 | D205: 1 | E205: 6 | F205: 21 | G205: =CONCATENATE(TEXT($E205,"00"),TEXT($F205,"000")) -> 06021 | H205: Glenn | I205: California | J205: CA | K205: =CONCATENATE(H205,", ",J205) -> Glenn, CA
A206: 205 | D206: 1 | E206: 6 | F206: 23 | G206: =CONCATENATE(TEXT($E206,"00"),TEXT($F206,"000")) -> 06023 | H206: Humboldt | I206: California | J206: CA | K206: =CONCATENATE(H206,", ",J206) -> Humboldt, CA
... A252: 251 | D252: 1 | E252: 6 | F252: 115 | G252: =CONCATENATE(TEXT($E252,"00"),TEXT($F252,"000")) -> 06115 | H252: Yuba | I252: California | J252: CA | K252: =CONCATENATE(H252,", ",J252) -> Yuba, CA
A253: 252 | C253: 1 | E253: 8 | F253: 0 | G253: =CONCATENATE(TEXT($E253,"00"),TEXT($F253,"000")) -> 08000 | I253: Colorado | J253: CO
A254: 253 | D254: 1 | E254: 8 | F254: 1 | G254: =CONCATENATE(TEXT($E254,"00"),TEXT($F254,"000")) -> 08001 | H254: Adams | I254: Colorado | J254: CO | K254: =CONCATENATE(H254,", ",J254) -> Adams, CO | L254: =(((Colorado!C3-(vlookup(H254,'CO Data'!$A$207:$B$251,2,FALSE)))/Colorado!D3)+(vlookup(H254,'CO Data'!$A$207:$B$251,2,FALSE))) -> 132.33333 | M254: =Colorado!H3/L254 -> 2.5465995
A255: 254 | D255: 1 | E255: 8 | F255: 3 | G255: =CONCATENATE(TEXT($E255,"00"),TEXT($F255,"000")) -> 08003 | H255: Alamosa | I255: Colorado | J255: CO | K255: =CONCATENATE(H255,", ",J255) -> Alamosa, CO | L255: =(((Colorado!C4-(vlookup(H255,'CO Data'!$A$207:$B$251,2,FALSE)))/Colorado!D4)+(vlookup(H255,'CO Data'!$A$207:$B$251,2,FALSE))) -> #VALUE! | M255: =Colorado!H4/L255 -> #VALUE!
A256: 255 | D256: 1 | E256: 8 | F256: 5 | G256: =CONCATENATE(TEXT($E256,"00"),TEXT($F256,"000")) -> 08005 | H256: Arapahoe | I256: Colorado | J256: CO | K256: =CONCATENATE(H256,", ",J256) -> Arapahoe, CO | L256: =(((Colorado!C5-(vlookup(H256,'CO Data'!$A$207:$B$251,2,FALSE)))/Colorado!D5)+(vlookup(H256,'CO Data'!$A$207:$B$251,2,FALSE))) -> 216.33333 | M256: =Colorado!H5/L256 -> 2.2280431
A257: 256 | D257: 1 | E257: 8 | F257: 7 | G257: =CONCATENATE(TEXT($E257,"00"),TEXT($F257,"000")) -> 08007 | H257: Archuleta | I257: Colorado | J257: CO | K257: =CONCATENATE(H257,", ",J257) -> Archuleta, CO | L257: =(((Colorado!C6-(vlookup(H257,'CO Data'!$A$207:$B$251,2,FALSE)))/Colorado!D6)+(vlookup(H257,'CO Data'!$A$207:$B$251,2,FALSE))) -> #N/A | M257: =Colorado!H6/L257 -> #N/A
A258: 257 | D258: 1 | E258: 8 | F258: 9 | G258: =CONCATENATE(TEXT($E258,"00"),TEXT($F258,"000")) -> 08009 | H258: Baca | I258: Colorado | J258: CO | K258: =CONCATENATE(H258,", ",J258) -> Baca, CO | L258: =(((Colorado!C7-(vlookup(H258,'CO Data'!$A$207:$B$251,2,FALSE)))/Colorado!D7)+(vlookup(H258,'CO Data'!$A$207:$B$251,2,FALSE))) -> #VALUE! | M258: =Colorado!H7/L258 -> #VALUE!
A259: 258 | D259: 1 | E259: 8 | F259: 11 | G259: =CONCATENATE(TEXT($E259,"00"),TEXT($F259,"000")) -> 08011 | H259: Bent | I259: Colorado | J259: CO | K259: =CONCATENATE(H259,", ",J259) -> Bent, CO | L259: =(((Colorado!C8-(vlookup(H259,'CO Data'!$A$207:$B$251,2,FALSE)))/Colorado!D8)+(vlookup(H259,'CO Data'!$A$207:$B$251,2,FALSE))) -> #VALUE! | M259: =Colorado!H8/L259 -> #VALUE!
A260: 259 | D260: 1 | E260: 8 | F260: 13 | G260: =CONCATENATE(TEXT($E260,"00"),TEXT($F260,"000")) -> 08013 | H260: Boulder | I260: Colorado | J260: CO | K260: =CONCATENATE(H260,", ",J260) -> Boulder, CO | L260: =(((Colorado!C9-(vlookup(H260,'CO Data'!$A$207:$B$251,2,FALSE)))/Colorado!D9)+(vlookup(H260,'CO Data'!$A$207:$B$251,2,FALSE))) -> 60.5 | M260: =Colorado!H9/L260 -> 1.4380165
A261: 260 | D261: 1 | E261: 8 | F261: 14 | G261: =CONCATENATE(TEXT($E261,"00"),TEXT($F261,"000")) -> 08014 | H261: Broomfield | I261: Colorado | J261: CO | K261: =CONCATENATE(H261,", ",J261) -> Broomfield, CO | L261: =(((Colorado!C10-(vlookup(H261,'CO Data'!$A$207:$B$251,2,FALSE)))/Colorado!D10)+(vlookup(H261,'CO Data'!$A$207:$B$251,2,FALSE))) -> #VALUE! | M261: =Colorado!H10/L261 -> #VALUE!
A262: 261 | D262: 1 | E262: 8 | F262: 15 | G262: =CONCATENATE(TEXT($E262,"00"),TEXT($F262,"000")) -> 08015 | H262: Chaffee | I262: Colorado | J262: CO | K262: =CONCATENATE(H262,", ",J262) -> Chaffee, CO | L262: =(((Colorado!C11-(vlookup(H262,'CO Data'!$A$207:$B$251,2,FALSE)))/Colorado!D11)+(vlookup(H262,'CO Data'!$A$207:$B$251,2,FALSE))) -> #VALUE! | M262: =Colorado!H11/L262 -> #VALUE!
A263: 262 | D263: 1 | E263: 8 | F263: 17 | G263: =CONCATENATE(TEXT($E263,"00"),TEXT($F263,"000")) -> 08017 | H263: Cheyenne | I263: Colorado | J263: CO | K263: =CONCATENATE(H263,", ",J263) -> Cheyenne, CO | L263: =(((Colorado!C12-(vlookup(H263,'CO Data'!$A$207:$B$251,2,FALSE)))/Colorado!D12)+(vlookup(H263,'CO Data'!$A$207:$B$251,2,FALSE))) -> #N/A | M263: =Colorado!H12/L263 -> #N/A
A264: 263 | D264: 1 | E264: 8 | F264: 19 | G264: =CONCATENATE(TEXT($E264,"00"),TEXT($F264,"000")) -> 08019 | H264: Clear Creek | I264: Colorado | J264: CO | K264: =CONCATENATE(H264,", ",J264) -> Clear Creek, CO | L264: =(((Colorado!C13-(vlookup(H264,'CO Data'!$A$207:$B$251,2,FALSE)))/Colorado!D13)+(vlookup(H264,'CO Data'!$A$207:$B$251,2,FALSE))) -> #VALUE! | M264: =Colorado!H13/L264 -> #VALUE!
A265: 264 | D265: 1 | E265: 8 | F265: 21 | G265: =CONCATENATE(TEXT($E265,"00"),TEXT($F265,"000")) -> 08021 | H265: Conejos | I265: Colorado | J265: CO | K265: =CONCATENATE(H265,", ",J265) -> Conejos, CO | L265: =(((Colorado!C14-(vlookup(H265,'CO Data'!$A$207:$B$251,2,FALSE)))/Colorado!D14)+(vlookup(H265,'CO Data'!$A$207:$B$251,2,FALSE))) -> #VALUE! | M265: =Colorado!H14/L265 -> #VALUE!
... A317: 316 | D317: 1 | E317: 8 | F317: 125 | G317: =CONCATENATE(TEXT($E317,"00"),TEXT($F317,"000")) -> 08125 | H317: Yuma | I317: Colorado | J317: CO | K317: =CONCATENATE(H317,", ",J317) -> Yuma, CO | L317: =(((Colorado!C66-(vlookup(H317,'CO Data'!$A$207:$B$251,2,FALSE)))/Colorado!D66)+(vlookup(H317,'CO Data'!$A$207:$B$251,2,FALSE))) -> #N/A | M317: =Colorado!H66/L317 -> #N/A
A318: 317 | C318: 1 | E318: 9 | F318: 0 | G318: =CONCATENATE(TEXT($E318,"00"),TEXT($F318,"000")) -> 09000 | I318: Connecticut | J318: CT
A319: 318 | D319: 1 | E319: 9 | F319: 1 | G319: =CONCATENATE(TEXT($E319,"00"),TEXT($F319,"000")) -> 09001 | H319: Fairfield | I319: Connecticut | J319: CT | K319: =CONCATENATE(H319,", ",J319) -> Fairfield, CT
A320: 319 | D320: 1 | E320: 9 | F320: 3 | G320: =CONCATENATE(TEXT($E320,"00"),TEXT($F320,"000")) -> 09003 | H320: Hartford | I320: Connecticut | J320: CT | K320: =CONCATENATE(H320,", ",J320) -> Hartford, CT
A321: 320 | D321: 1 | E321: 9 | F321: 5 | G321: =CONCATENATE(TEXT($E321,"00"),TEXT($F321,"000")) -> 09005 | H321: Litchfield | I321: Connecticut | J321: CT | K321: =CONCATENATE(H321,", ",J321) -> Litchfield, CT
A322: 321 | D322: 1 | E322: 9 | F322: 7 | G322: =CONCATENATE(TEXT($E322,"00"),TEXT($F322,"000")) -> 09007 | H322: Middlesex | I322: Connecticut | J322: CT | K322: =CONCATENATE(H322,", ",J322) -> Middlesex, CT
A323: 322 | D323: 1 | E323: 9 | F323: 9 | G323: =CONCATENATE(TEXT($E323,"00"),TEXT($F323,"000")) -> 09009 | H323: New Haven | I323: Connecticut | J323: CT | K323: =CONCATENATE(H323,", ",J323) -> New Haven, CT
A324: 323 | D324: 1 | E324: 9 | F324: 11 | G324: =CONCATENATE(TEXT($E324,"00"),TEXT($F324,"000")) -> 09011 | H324: New London | I324: Connecticut | J324: CT | K324: =CONCATENATE(H324,", ",J324) -> New London, CT
A325: 324 | D325: 1 | E325: 9 | F325: 13 | G325: =CONCATENATE(TEXT($E325,"00"),TEXT($F325,"000")) -> 09013 | H325: Tolland | I325: Connecticut | J325: CT | K325: =CONCATENATE(H325,", ",J325) -> Tolland, CT
A326: 325 | D326: 1 | E326: 9 | F326: 15 | G326: =CONCATENATE(TEXT($E326,"00"),TEXT($F326,"000")) -> 09015 | H326: Windham | I326: Connecticut | J326: CT | K326: =CONCATENATE(H326,", ",J326) -> Windham, CT
A327: 326 | C327: 1 | E327: 10 | F327: 0 | G327: =CONCATENATE(TEXT($E327,"00"),TEXT($F327,"000")) -> 10000 | I327: Delaware | J327: DE
A328: 327 | D328: 1 | E328: 10 | F328: 1 | G328: =CONCATENATE(TEXT($E328,"00"),TEXT($F328,"000")) -> 10001 | H328: Kent | I328: Delaware | J328: DE | K328: =CONCATENATE(H328,", ",J328) -> Kent, DE
A329: 328 | D329: 1 | E329: 10 | F329: 3 | G329: =CONCATENATE(TEXT($E329,"00"),TEXT($F329,"000")) -> 10003 | H329: New Castle | I329: Delaware | J329: DE | K329: =CONCATENATE(H329,", ",J329) -> New Castle, DE
...

Sheet State Overview
B1: State Overview
B2: State Demographics | L2: State-level Foster Care Data | P2: Church Data
C3: Population by Race
A4: State | B4: Population | C4: White | D4: Black or African American | E4: American Indian and Alaska Native | F4: Asian | G4: Native Hawaiian and Other Pacific Islander | H4: Other race | I4: Two or more races | J4: Median Household Income | K4: Child Poverty Rate (%) | L4: Number of Children in Out-of-Home Placement | M4: Number of Children Waiting for Adoption | N4: Number of Licensed Foster Homes | O4: Number of Family Preservation Cases | P4: Number of Churches | Q4: Number of Actively Engaged Churches Needed | R4: Number of Church Assessments Taken | S4: Churches per 1,000 People
A5: Alabama | B5: {=VLOOKUP($A5,AL_DEMO,{2,5,6,7,8,9,10,11,12,4},FALSE)} -> 5024279 | C5: 3220452 | D5: 1296162 | E5: 33625 | F5: 76660 | G5: 2984 | H5: 137443 | I5: 256953 | J5: 49881 | K5: 23.9 | L5: =Alabama!C71 -> 5844 | M5: =Alabama!H71 -> 1989 | N5: =Alabama!I71 -> 399 | O5: =Alabama!J71 -> NULL | P5: =Alabama!K71 -> NULL | Q5: =Alabama!L71 -> 4558 | R5: =Alabama!M71 -> NULL | S5: =(P5/B5)*1000 -> #VALUE!
A6: Alaska | B6: {=VLOOKUP($A6,AK_DEMO,{2,5,6,7,8,9,10,11,12,4},FALSE)} -> 733391 | C6: 435392 | D6: 21898 | E6: 111575 | F6: 44032 | G6: 12698 | H6: 18272 | I6: 89524 | J6: 74912 | K6: 14.5 | L6: =#REF! -> #REF! | M6: =VLOOKUP($A6,AFCARSCSC!$A$4:$D$56,3,FALSE) -> 328 | N6: =#REF! -> #REF! | O6: NULL | P6: =#REF! -> #REF! | Q6: =#REF! -> #REF! | R6: =#REF! -> #REF! | S6: =(P6/B6)*1000 -> #REF!
A7: Arizona | B7: {=VLOOKUP($A7,AZ_DEMO,{2,5,6,7,8,9,10,11,12,4},FALSE)} -> 7151502 | C7: 4322337 | D7: 339150 | E7: 319512 | F7: 257430 | G7: 16397 | H7: 899870 | I7: 996806 | J7: 59079 | K7: 20.4 | L7: =#REF! -> #REF! | M7: =#REF! -> #REF! | N7: =#REF! -> #REF! | O7: NULL | P7: =#REF! -> #REF! | Q7: =#REF! -> #REF! | R7: =#REF! -> #REF! | S7: =(P7/B7)*1000 -> #REF!
A8: Arkansas | B8: ='County PopulationPovertyRacial '!B122 -> 3011524 | C8: ='County PopulationPovertyRacial '!E122 -> 2114512 | D8: ='County PopulationPovertyRacial '!F122 -> 453783 | E8: ='County PopulationPovertyRacial '!G122 -> 27177 | F8: ='County PopulationPovertyRacial '!H122 -> 51839 | G8: ='County PopulationPovertyRacial '!I122 -> 14533 | H8: ='County PopulationPovertyRacial '!J122 -> 136105 | I8: ='County PopulationPovertyRacial '!K122 -> 213575 | J8: ='County PopulationPovertyRacial '!$L$122 -> 47094 | K8: ='County PopulationPovertyRacial '!D122 -> 23.8 | L8: =#REF! -> #REF! | M8: =#REF! -> #REF! | N8: =#REF! -> #REF! | O8: =#REF! -> #REF! | P8: =#REF! -> #REF! | Q8: =P8*0.1 -> #REF! | R8: =#REF! -> #REF! | S8: =(P8/B8)*1000 -> #REF!
A9: California | B9: {=VLOOKUP($A9,CA_DEMO,{2,5,6,7,8,9,10,11,12,4},FALSE)} -> 39538223 | C9: 16296122 | D9: 2237044 | E9: 631016 | F9: 6085947 | G9: 157263 | H9: 8370596 | I9: 5760235 | J9: 75250 | K9: 17.4 | L9: =#REF! -> #REF! | M9: {=VLOOKUP($A9,AFCARSCSC!$A$4:$D$56,{3,4},FALSE)} -> 8180 | N9: 34924 | O9: NULL | P9: =#REF! -> #REF! | Q9: =#REF! -> #REF! | R9: =#REF! -> #REF! | S9: =(P9/B9)*1000 -> #REF!
A10: Colorado | B10: {=VLOOKUP($A10,CO_DEMO,{2,5,6,7,8,9,10,11,12,4},FALSE)} -> 5773714 | C10: 4082927 | D10: 234828 | E10: 74129 | F10: 199827 | G10: 10287 | H10: 464046 | I10: 707670 | J10: 71949 | K10: 12.1 | L10: =#REF! -> #REF! | M10: {=VLOOKUP($A10,AFCARSCSC!$A$4:$D$56,{3,4},FALSE)} -> 560 | N10: 2078 | O10: NULL | P10: =#REF! -> #REF! | Q10: =#REF! -> #REF! | R10: =#REF! -> #REF! | S10: =(P10/B10)*1000 -> #REF!
A11: Connecticut | B11: {=VLOOKUP($A11,CT_DEMO,{2,5,6,7,8,9,10,11,12,4},FALSE)} -> 3605944 | C11: 2395128 | D11: 388675 | E11: 16051 | F11: 172455 | G11: 1598 | H11: 299133 | I11: 332904 | J11: 76366 | K11: 13.8 | L11: =#REF! -> #REF! | M11: {=VLOOKUP($A11,AFCARSCSC!$A$4:$D$56,{3,4},FALSE)} -> 438 | N11: 2363 | O11: NULL | P11: =#REF! -> #REF! | Q11: =#REF! -> #REF! | R11: =#REF! -> #REF! | S11: =(P11/B11)*1000 -> #REF!
A12: District of Columbia | B12: {=VLOOKUP($A12,DC_DEMO,{2,5,6,7,8,9,10,11,12,4},FALSE)} -> 689545 | C12: 273194 | D12: 285810 | E12: 3193 | F12: 33545 | G12: 432 | H12: 37294 | I12: 56077 | J12: 82533 | K12: 24.5 | L12: ='District of Columbia'!L3 -> 346 | M12: {=VLOOKUP($A12,AFCARSCSC!$A$4:$D$56,{3,4},FALSE)} -> 0 | N12: 386 | O12: =#REF! -> #REF! | P12: ='Population & Church Numbers'!D322 -> 480 | Q12: =P12*0.1 -> 48 | R12: =#REF! -> #REF! | S12: =(P12/B12)*1000 -> 0.6961112
A13: Delaware | B13: {=VLOOKUP($A13,DE_DEMO,{2,5,6,7,8,9,10,11,12,4},FALSE)} -> 989948 | C13: 597763 | D13: 218899 | E13: 5148 | F13: 42699 | G13: 412 | H13: 48509 | I13: 76518 | J13: 65467 | K13: 17.6 | L13: =#REF! -> #REF! | M13: =#REF! -> #REF! | N13: =#REF! -> #REF! | O13: NULL | P13: =#REF! -> #REF! | Q13: =#REF! -> #REF! | R13: =#REF! -> #REF! | S13: =(P13/B13)*1000 -> #REF!
A14: Florida | B14: {=VLOOKUP($A14,FL_DEMO,{2,5,6,7,8,9,10,11,12,4},FALSE)} -> 21538187 | C14: 12422961 | D14: 3246381 | E14: 94795 | F14: 643682 | G14: 14014 | H14: 1564282 | I14: 3552072 | J14: 55433 | K14: 20 | L14: =Florida!L71 -> NULL | M14: =VLOOKUP($A14,AFCARSCSC!$A$4:$D$56,3,FALSE) -> 5576 | N14: =VLOOKUP($A14,AFCARSCSC!$A$4:$D$56,4,FALSE) -> 8712 | O14: NULL | P14: =#REF! -> #REF! | Q14: =#REF! -> #REF! | R14: =#REF! -> #REF! | S14: =(P14/B14)*1000 -> #REF!
A15: Georgia | B15: {=VLOOKUP($A15,GA_DEMO,{2,5,6,7,8,9,10,11,12,4},FALSE)} -> 10711908 | C15: 5555483 | D15: 3320513 | E15: 50618 | F15: 479028 | G15: 7299 | H15: 555059 | I15: 743908 | J15: 58634 | K15: 21 | L15: =#REF! -> #REF! | M15: =#REF! -> #REF! | N15: =VLOOKUP($A15,AFCARSCSC!$A$4:$D$56,4,FALSE) -> 4559 | O15: NULL | P15: =#REF! -> #REF! | Q15: =#REF! -> #REF! | R15: =#REF! -> #REF! | S15: =(P15/B15)*1000 -> #REF!
A16: Hawaii | B16: ='County PopulationPovertyRacial '!B564 -> 1455271 | C16: ='County PopulationPovertyRacial '!E564 -> 333261 | D16: ='County PopulationPovertyRacial '!F564 -> 23417 | E16: ='County PopulationPovertyRacial '!G564 -> 4370 | F16: ='County PopulationPovertyRacial '!H564 -> 541902 | G16: ='County PopulationPovertyRacial '!I564 -> 157445 | H16: ='County PopulationPovertyRacial '!J564 -> 26747 | I16: ='County PopulationPovertyRacial '!K564 -> 368129 | J16: ='County PopulationPovertyRacial '!$L$564 -> 80527 | K16: ='County PopulationPovertyRacial '!D564 -> 11.8 | L16: {=VLOOKUP($A16,AFCARSCSC!$A$4:$D$56,{2,3,4},FALSE)} -> 1340 | M16: 228 | N16: 781 | O16: NULL | P16: =#REF! -> #REF! | Q16: =#REF! -> #REF! | R16: =#REF! -> #REF! | S16: =(P16/B16)*1000 -> #REF!
A17: Idaho | B17: ='County PopulationPovertyRacial '!$B$570 -> 1839106 | C17: ='County PopulationPovertyRacial '!$E$570 -> 1510360 | D17: ='County PopulationPovertyRacial '!$F$570 -> 15726 | E17: ='County PopulationPovertyRacial '!$G$570 -> 25621 | F17: ='County PopulationPovertyRacial '!$H$570 -> 26836 | G17: ='County PopulationPovertyRacial '!$I$570 -> 3726 | H17: ='County PopulationPovertyRacial '!$J$570 -> 103632 | I17: ='County PopulationPovertyRacial '!$K$570 -> 153205 | J17: ='County PopulationPovertyRacial '!$L$570 -> 55524 | K17: ='County PopulationPovertyRacial '!D570 -> 14.2 | L17: {=VLOOKUP($A17,AFCARSCSC!$A$4:$D$56,{2,3,4},FALSE)} -> 1548 | M17: 170 | N17: 1187 | O17: NULL | P17: =#REF! -> #REF! | Q17: =#REF! -> #REF! | R17: =#REF! -> #REF! | S17: =(P17/B17)*1000 -> #REF!
A18: Illinois | B18: {=VLOOKUP($A18,IL_DEMO,{2,5,6,7,8,9,10,11,12,4},FALSE)} -> 12812508 | C18: 7868227 | D18: 1808271 | E18: 96498 | F18: 754878 | G18: 4501 | H18: 1135149 | I18: 1144984 | J18: 65063 | K18: 16.2 | L18: =#REF! -> #REF! | M18: =VLOOKUP($A18,AFCARSCSC!$A$4:$D$56,3,FALSE) -> 2660 | N18: =#REF! -> #REF! | O18: NULL | P18: =#REF! -> #REF! | Q18: =#REF! -> #REF! | R18: =#REF! -> #REF! | S18: =(P18/B18)*1000 -> #REF!
A19: Indiana | B19: {=VLOOKUP($A19,IN_DEMO,{2,5,6,7,8,9,10,11,12,4},FALSE)} -> 6785528 | C19: 5241795 | D19: 648513 | E19: 26086 | F19: 167959 | G19: 3137 | H19: 261312 | I19: 436726 | J19: 55725 | K19: 17.5 | L19: =#REF! -> #REF! | M19: {=VLOOKUP($A19,AFCARSCSC!$A$4:$D$56,{3,4},FALSE)} -> 1389 | N19: 4531 | O19: =#REF! -> #REF! | P19: =#REF! -> #REF! | Q19: =#REF! -> #REF! | R19: =#REF! -> #REF! | S19: =(P19/B19)*1000 -> #REF!
A20: Iowa | B20: ='County PopulationPovertyRacial '!$B$811 -> 3190369 | C20: ='County PopulationPovertyRacial '!$E$811 -> 2694521 | D20: ='County PopulationPovertyRacial '!$F$811 -> 131972 | E20: ='County PopulationPovertyRacial '!$G$811 -> 14486 | F20: ='County PopulationPovertyRacial '!$H$811 -> 75629 | G20: ='County PopulationPovertyRacial '!$I$811 -> 5758 | H20: ='County PopulationPovertyRacial '!$J$811 -> 88720 | I20: ='County PopulationPovertyRacial '!$K$811 -> 179283 | J20: ='County PopulationPovertyRacial '!$L$811 -> 60071 | K20: ='County PopulationPovertyRacial '!$D$811 -> 13.5 | L20: =#REF! -> #REF! | M20: {=VLOOKUP($A20,AFCARSCSC!$A$4:$D$56,{3,4},FALSE)} -> 765 | N20: 2244 | O20: NULL | P20: =#REF! -> #REF! | Q20: =#REF! -> #REF! | R20: =#REF! -> #REF! | S20: =(P20/B20)*1000 -> #REF!
A21: Kansas | B21: {=VLOOKUP($A21,KS_DEMO,{2,5,6,7,8,9,10,11,12,4},FALSE)} -> 2937880 | C21: 2222462 | D21: 168809 | E21: 30995 | F21: 86273 | G21: 3412 | H21: 145422 | I21: 280507 | J21: 58150 | K21: 14.8 | L21: =#REF! -> #REF! | M21: =#REF! -> #REF! | N21: =#REF! -> #REF! | O21: NULL | P21: =#REF! -> #REF! | Q21: =#REF! -> #REF! | R21: =#REF! -> #REF! | S21: =(P21/B21)*1000 -> #REF!
A22: Kentucky | B22: {=VLOOKUP($A22,KY_DEMO,{2,5,6,7,8,9,10,11,12,4},FALSE)} -> 4505836 | C22: 3711254 | D22: 362417 | E22: 12801 | F22: 74426 | G22: 3681 | H22: 96417 | I22: 244840 | J22: 50189 | K22: 22.3 | L22: =#REF! -> #REF! | M22: =#REF! -> #REF! | N22: =VLOOKUP($A22,AFCARSCSC!$A$4:$D$56,4,FALSE) -> 5185 | O22: NULL | P22: =#REF! -> #REF! | Q22: =#REF! -> #REF! | R22: =#REF! -> #REF! | S22: =(P22/B22)*1000 -> #REF!
A23: Louisiana | B23: {=VLOOKUP($A23,LA_DEMO,{2,5,6,7,8,9,10,11,12,4},FALSE)} -> 4657757 | C23: 2657652 | D23: 1464023 | E23: 31657 | F23: 86438 | G23: 1911 | H23: 142699 | I23: 273377 | J23: 48021 | K23: 26.5 | L23: {=VLOOKUP($A23,AFCARSCSC!$A$4:$D$56,{2,3,4},FALSE)} -> 3682 | M23: 501 | N23: 1659 | O23: NULL | P23: =#REF! -> #REF! | Q23: =#REF! -> #REF! | R23: =#REF! -> #REF! | S23: =(P23/B23)*1000 -> #REF!
A24: Maine | B24: {=VLOOKUP($A24,ME_DEMO,{2,5,6,7,8,9,10,11,12,4},FALSE)} -> 1338404 | C24: 1237041 | D24: 25752 | E24: 7885 | F24: 16798 | G24: 443 | H24: 9730 | I24: 64710 | J24: 55579 | K24: 14.8 | L24: =#REF! -> #REF! | M24: {=VLOOKUP($A24,AFCARSCSC!$A$4:$D$56,{3,4},FALSE)} -> 107 | N24: 1767 | O24: NULL | P24: =#REF! -> #REF! | Q24: =#REF! -> #REF! | R24: =#REF! -> #REF! | S24: =(P24/B24)*1000 -> #REF!
A25: Maryland | B25: {=VLOOKUP($A25,MD_DEMO,{2,5,6,7,8,9,10,11,12,4},FALSE)} -> 6177224 | C25: 3007874 | D25: 1820472 | E25: 31845 | F25: 420944 | G25: 3247 | H25: 410941 | I25: 481901 | J25: 83076 | K25: 12.1 | L25: =#REF! -> #REF! | M25: =#REF! -> #REF! | N25: =#REF! -> #REF! | O25: =#REF! -> #REF! | P25: =#REF! -> #REF! | Q25: =#REF! -> #REF! | R25: =#REF! -> #REF! | S25: =(P25/B25)*1000 -> #REF!
A26: Massachusetts | B26: {=VLOOKUP($A26,MA_DEMO,{2,5,6,7,8,9,10,11,12,4},FALSE)} -> 7029917 | C26: 4896037 | D26: 494029 | E26: 24018 | F26: 507934 | G26: 2301 | H26: 496731 | I26: 608867 | J26: 79817 | K26: 12.4 | L26: {=VLOOKUP($A26,AFCARSCSC!$A$4:$D$56,{2,3,4},FALSE)} -> 8824 | M26: 1316 | N26: 5159 | O26: NULL | P26: =#REF! -> #REF! | Q26: =#REF! -> #REF! | R26: =#REF! -> #REF! | S26: =(P26/B26)*1000 -> #REF!
A27: Michigan | B27: {=VLOOKUP($A27,MI_DEMO,{2,5,6,7,8,9,10,11,12,4},FALSE)} -> 10077331 | C27: 7444974 | D27: 1376579 | E27: 61261 | F27: 334300 | G27: 3051 | H27: 221851 | I27: 635315 | J27: 56640 | K27: 19.3 | L27: =#REF! -> #REF! | M27: =#REF! -> #REF! | N27: =VLOOKUP($A27,AFCARSCSC!$A$4:$D$56,4,FALSE) -> 4169 | O27: NULL | P27: =#REF! -> #REF! | Q27: =#REF! -> #REF! | R27: =#REF! -> #REF! | S27: =(P27/B27)*1000 -> #REF!
A28: Minnesota | B28: {=VLOOKUP($A28,MN_DEMO,{2,5,6,7,8,9,10,11,12,4},FALSE)} -> 5706494 | C28: 4423146 | D28: 398434 | E28: 68641 | F28: 299190 | G28: 2918 | H28: 168444 | I28: 345721 | J28: 70295 | K28: 11.5 | L28: =#REF! -> #REF! | M28: {=VLOOKUP($A28,AFCARSCSC!$A$4:$D$56,{3,4},FALSE)} -> 1423 | N28: 3766 | O28: NULL | P28: =#REF! -> #REF! | Q28: =#REF! -> #REF! | R28: =#REF! -> #REF! | S28: =(P28/B28)*1000 -> #REF!
A29: Mississippi | B29: {=VLOOKUP($A29,MS_DEMO,{2,5,6,7,8,9,10,11,12,4},FALSE)} -> 2961279 | C29: 1658893 | D29: 1084481 | E29: 16450 | F29: 32709 | G29: 1154 | H29: 56860 | I29: 110732 | J29: 44740 | K29: 28.2 | L29: {=VLOOKUP($A29,AFCARSCSC!$A$4:$D$56,{2,3,4},FALSE)} -> 3825 | M29: 530 | N29: 1691 | O29: NULL | P29: =#REF! -> #REF! | Q29: =#REF! -> #REF! | R29: =#REF! -> #REF! | S29: =(P29/B29)*1000 -> #REF!
A30: Missouri | B30: {=VLOOKUP($A30,MO_DEMO,{2,5,6,7,8,9,10,11,12,4},FALSE)} -> 6154913 | C30: 4740335 | D30: 699840 | E30: 30518 | F30: 133377 | G30: 9730 | H30: 127942 | I30: 413171 | J30: 54412 | K30: 18.3 | L30: =#REF! -> #REF! | M30: =#REF! -> #REF! | N30: =VLOOKUP($A30,AFCARSCSC!$A$4:$D$56,4,FALSE) -> 4567 | O30: =#REF! -> #REF! | P30: =#REF! -> #REF! | Q30: =#REF! -> #REF! | R30: =#REF! -> #REF! | S30: =(P30/B30)*1000 -> #REF!
A31: Montana | B31: {=VLOOKUP($A31,MT_DEMO,{2,5,6,7,8,9,10,11,12,4},FALSE)} -> 1084225 | C31: 916524 | D31: 5484 | E31: 67612 | F31: 8300 | G31: 941 | H31: 14089 | I31: 71275 | J31: 55248 | K31: 16.4 | L31: =#REF! -> #REF! | M31: {=VLOOKUP($A31,AFCARSCSC!$A$4:$D$56,{3,4},FALSE)} -> 345 | N31: 1200 | O31: NULL | P31: =#REF! -> #REF! | Q31: =#REF! -> #REF! | R31: =#REF! -> #REF! | S31: =(P31/B31)*1000 -> #REF!
A32: Nebraska | B32: {=VLOOKUP($A32,NE_DEMO,{2,5,6,7,8,9,10,11,12,4},FALSE)} -> 1961504 | C32: 1538052 | D32: 96535 | E32: 23102 | F32: 52951 | G32: 1534 | H32: 105167 | I32: 144163 | J32: 59724 | K32: 12.9 | L32: =#REF! -> #REF! | M32: {=VLOOKUP($A32,AFCARSCSC!$A$4:$D$56,{3,4},FALSE)} -> 433 | N32: 1502 | O32: NULL | P32: =#REF! -> #REF! | Q32: =#REF! -> #REF! | R32: =#REF! -> #REF! | S32: =(P32/B32)*1000 -> #REF!
A33: Nevada | B33: {=VLOOKUP($A33,NV_DEMO,{2,5,6,7,8,9,10,11,12,4},FALSE)} -> 3104614 | C33: 1588463 | D33: 304739 | E33: 43932 | F33: 272703 | G33: 25011 | H33: 435757 | I33: 434009 | J33: 58740 | K33: 18.4 | L33: =#REF! -> #REF! | M33: {=VLOOKUP($A33,AFCARSCSC!$A$4:$D$56,{3,4},FALSE)} -> 718 | N33: 1099 | O33: NULL | P33: =#REF! -> #REF! | Q33: =#REF! -> #REF! | R33: =#REF! -> #REF! | S33: =(P33/B33)*1000 -> #REF!
A34: New Hampshire | B34: {=VLOOKUP($A34,NH_DEMO,{2,5,6,7,8,9,10,11,12,4},FALSE)} -> 1377529 | C34: 1216203 | D34: 20127 | E34: 3031 | F34: 35871 | G34: 453 | H34: 24102 | I34: 77742 | J34: 75322 | K34: 10.1 | L34: {=VLOOKUP($A34,AFCARSCSC!$A$4:$D$56,{2,3,4},FALSE)} -> 1181 | M34: 60 | N34: 599 | O34: NULL | P34: =#REF! -> #REF! | Q34: =#REF! -> #REF! | R34: =#REF! -> #REF! | S34: =(P34/B34)*1000 -> #REF!
A35: New Jersey | B35: {=VLOOKUP($A35,NJ_DEMO,{2,5,6,7,8,9,10,11,12,4},FALSE)} -> 9288994 | C35: 5112280 | D35: 1219770 | E35: 51186 | F35: 950090 | G35: 3533 | H35: 1048641 | I35: 903494 | J35: 81777 | K35: 13.5 | L35: =#REF! -> #REF! | M35: {=VLOOKUP($A35,AFCARSCSC!$A$4:$D$56,{3,4},FALSE)} -> 444 | N35: 2449 | O35: NULL | P35: =#REF! -> #REF! | Q35: =#REF! -> #REF! | R35: =#REF! -> #REF! | S35: =(P35/B35)*1000 -> #REF!
A36: New Mexico | B36: {=VLOOKUP($A36,NM_DEMO,{2,5,6,7,8,9,10,11,12,4},FALSE)} -> 2117522 | C36: 1078937 | D36: 45904 | E36: 212241 | F36: 37469 | G36: 2093 | H36: 318632 | I36: 422246 | J36: 47405 | K36: 25.3 | L36: ='NM Data'!B77 -> 1942 | M36: =#REF! -> #REF! | N36: =VLOOKUP($A36,AFCARSCSC!$A$4:$D$56,4,FALSE) -> 1007 | O36: NULL | P36: =#REF! -> #REF! | Q36: =#REF! -> #REF! | R36: =#REF! -> #REF! | S36: =(P36/B36)*1000 -> #REF!
A37: New York | B37: ='County PopulationPovertyRacial '!B1867 -> 20201249 | C37: ='County PopulationPovertyRacial '!E1867 -> 11143349 | D37: ='County PopulationPovertyRacial '!F1867 -> 2986172 | E37: ='County PopulationPovertyRacial '!G1867 -> 149690 | F37: ='County PopulationPovertyRacial '!H1867 -> 1933127 | G37: ='County PopulationPovertyRacial '!I1867 -> 10815 | H37: ='County PopulationPovertyRacial '!J1867 -> 2210633 | I37: ='County PopulationPovertyRacial '!K1867 -> 1767463 | J37: ='County PopulationPovertyRacial '!$L$1867 -> 67648 | K37: ='County PopulationPovertyRacial '!D1867 -> 18.8 | L37: =#REF! -> #REF! | M37: =#REF! -> #REF! | N37: =#REF! -> #REF! | O37: NULL | P37: =#REF! -> #REF! | Q37: =#REF! -> #REF! | R37: =#REF! -> #REF! | S37: =(P37/B37)*1000 -> #REF!
A38: North Carolina | B38: {=VLOOKUP($A38,NC_DEMO,{2,5,6,7,8,9,10,11,12,4},FALSE)} -> 10439388 | C38: 6488459 | D38: 2140217 | E38: 130032 | F38: 343051 | G38: 8518 | H38: 617390 | I38: 711721 | J38: 53922 | K38: 20.2 | L38: =#REF! -> #REF! | M38: {=VLOOKUP($A38,AFCARSCSC!$A$4:$D$56,{3,4},FALSE)} -> 1154 | N38: 5616 | O38: NULL | P38: =#REF! -> #REF! | Q38: =#REF! -> #REF! | R38: =#REF! -> #REF! | S38: =(P38/B38)*1000 -> #REF!
A39: North Dakota | B39: {=VLOOKUP($A39,ND_DEMO,{2,5,6,7,8,9,10,11,12,4},FALSE)} -> 779094 | C39: 645938 | D39: 26783 | E39: 38914 | F39: 13213 | G39: 924 | H39: 11382 | I39: 41940 | J39: 65250 | K39: 11 | L39: =#REF! -> #REF! | M39: {=VLOOKUP($A39,AFCARSCSC!$A$4:$D$56,{3,4},FALSE)} -> 343 | N39: 974 | O39: NULL | P39: =#REF! -> #REF! | Q39: =#REF! -> #REF! | R39: =#REF! -> #REF! | S39: =(P39/B39)*1000 -> #REF!
A40: Ohio | B40: {=VLOOKUP($A40,OH_DEMO,{2,5,6,7,8,9,10,11,12,4},FALSE)} -> 11799448 | C40: 9080688 | D40: 1478781 | E40: 30720 | F40: 298509 | G40: 5034 | H40: 224344 | I40: 681372 | J40: 56155 | K40: 19.2 | L40: =#REF! -> #REF! | M40: =#REF! -> #REF! | N40: {=VLOOKUP($A40,AFCARSCSC!$A$4:$D$56,4,FALSE)} -> 7349 | O40: NULL | P40: =#REF! -> #REF! | Q40: =#REF! -> #REF! | R40: =#REF! -> #REF! | S40: =(P40/B40)*1000 -> #REF!
A41: Oklahoma | B41: ='County PopulationPovertyRacial '!B2174 -> 3959353 | C41: ='County PopulationPovertyRacial '!E2174 -> 2514885 | D41: ='County PopulationPovertyRacial '!F2174 -> 289961 | E41: ='County PopulationPovertyRacial '!G2174 -> 332791 | F41: ='County PopulationPovertyRacial '!H2174 -> 90949 | G41: ='County PopulationPovertyRacial '!I2174 -> 8608 | H41: ='County PopulationPovertyRacial '!J2174 -> 214001 | I41: ='County PopulationPovertyRacial '!K2174 -> 508158 | J41: ='County PopulationPovertyRacial '!$L$2174 -> 51914 | K41: ='County PopulationPovertyRacial '!D2174 -> 21.4 | L41: =#REF! -> #REF! | M41: =#REF! -> #REF! | N41: =#REF! -> #REF! | O41: =#REF! -> #REF! | P41: =#REF! -> #REF! | Q41: =#REF! -> #REF! | R41: =#REF! -> #REF! | S41: =(P41/B41)*1000 -> #REF!
A42: Oregon | B42: {=VLOOKUP($A42,OR_DEMO,{2,5,6,7,8,9,10,11,12,4},FALSE)} -> 4237256 | C42: 3169096 | D42: 82655 | E42: 62993 | F42: 194538 | G42: 19204 | H42: 265431 | I42: 443339 | J42: 63168 | K42: 15.7 | L42: =#REF! -> #REF! | M42: =VLOOKUP($A42,AFCARSCSC!$A$4:$D$56,3,FALSE) -> 700 | N42: =#REF! -> #REF! | O42: NULL | P42: =#REF! -> #REF! | Q42: =#REF! -> #REF! | R42: =#REF! -> #REF! | S42: =(P42/B42)*1000 -> #REF!
A43: Pennsylvania | B43: {=VLOOKUP($A43,PA_DEMO,{2,5,6,7,8,9,10,11,12,4},FALSE)} -> 13002700 | C43: 9750687 | D43: 1423169 | E43: 31052 | F43: 510501 | G43: 4276 | H43: 508531 | I43: 774484 | J43: 60891 | K43: 16.7 | L43: {=VLOOKUP($A43,AFCARSCSC!$A$4:$D$56,{2,3,4},FALSE)} -> 12465 | M43: 1794 | N43: 12616 | O43: NULL | P43: =#REF! -> #REF! | Q43: =#REF! -> #REF! | R43: =#REF! -> #REF! | S43: =(P43/B43)*1000 -> #REF!
A44: Rhode Island | B44: {=VLOOKUP($A44,RI_DEMO,{2,5,6,7,8,9,10,11,12,4},FALSE)} -> 1097379 | C44: 782920 | D44: 62168 | E44: 7385 | F44: 38961 | G44: 536 | H44: 103615 | I44: 101794 | J44: 63787 | K44: 18 | L44: {=VLOOKUP($A44,AFCARSCSC!$A$4:$D$56,{2,3,4},FALSE)} -> 1723 | M44: 94 | N44: 828 | O44: NULL | P44: =#REF! -> #REF! | Q44: =#REF! -> #REF! | R44: =#REF! -> #REF! | S44: =(P44/B44)*1000 -> #REF!
A45: South Carolina | B45: {=VLOOKUP($A45,SC_DEMO,{2,5,6,7,8,9,10,11,12,4},FALSE)} -> 5118425 | C45: 3243442 | D45: 1280531 | E45: 24303 | F45: 90466 | G45: 3431 | H45: 177876 | I45: 298376 | J45: 52449 | K45: 22.1 | L45: =#REF! -> #REF! | M45: =#REF! -> #REF! | N45: =#REF! -> #REF! | O45: =#REF! -> #REF! | P45: =#REF! -> #REF! | Q45: =#REF! -> #REF! | R45: =#REF! -> #REF! | S45: =(P45/B45)*1000 -> #REF!
A46: South Dakota | B46: {=VLOOKUP($A46,SD_DEMO,{2,5,6,7,8,9,10,11,12,4},FALSE)} -> 886667 | C46: 715336 | D46: 17842 | E46: 77748 | F46: 13476 | G46: 543 | H46: 15057 | I46: 46665 | J46: 57041 | K46: 16.1 | L46: {=VLOOKUP($A46,AFCARSCSC!$A$4:$D$56,{2,3,4},FALSE)} -> 1615 | M46: 440 | N46: 835 | O46: NULL | P46: =#REF! -> #REF! | Q46: =#REF! -> #REF! | R46: =#REF! -> #REF! | S46: =(P46/B46)*1000 -> #REF!
A47: Tennessee | B47: {=VLOOKUP($A47,TN_DEMO,{2,5,6,7,8,9,10,11,12,4},FALSE)} -> 6910840 | C47: 4990938 | D47: 1092948 | E47: 28044 | F47: 135615 | G47: 4115 | H47: 246282 | I47: 412898 | J47: 52366 | K47: 21.8 | L47: {=VLOOKUP($A47,AFCARSCSC!$A$4:$D$56,{2,3,4},FALSE)} -> 9053 | M47: 1155 | N47: 4509 | O47: NULL | P47: =#REF! -> #REF! | Q47: =#REF! -> #REF! | R47: =#REF! -> #REF! | S47: =(P47/B47)*1000 -> #REF!
A48: Texas | B48: {=VLOOKUP($A48,TX_DEMO,{2,5,6,7,8,9,10,11,12,4},FALSE)} -> 29145505 | C48: 14609365 | D48: 3552997 | E48: 278948 | F48: 1585480 | G48: 33611 | H48: 3951366 | I48: 5133738 | J48: 60632 | K48: 21.1 | L48: =#REF! -> #REF! | M48: =#REF! -> #REF! | N48: =VLOOKUP($A48,AFCARSCSC!$A$4:$D$56,4,FALSE) -> NULL | O48: =#REF! -> #REF! | P48: =#REF! -> #REF! | Q48: =#REF! -> #REF! | R48: =#REF! -> #REF! | S48: =(P48/B48)*1000 -> #REF!
A49: Utah | B49: ='County PopulationPovertyRacial '!B2828 -> 3271616 | C49: ='County PopulationPovertyRacial '!E2828 -> 2573413 | D49: ='County PopulationPovertyRacial '!F2828 -> 40058 | E49: ='County PopulationPovertyRacial '!G2828 -> 41644 | F49: ='County PopulationPovertyRacial '!H2828 -> 80438 | G49: ='County PopulationPovertyRacial '!I2828 -> 36930 | H49: ='County PopulationPovertyRacial '!J2828 -> 220120 | I49: ='County PopulationPovertyRacial '!K2828 -> 279013 | J49: ='County PopulationPovertyRacial '!$L$2828 -> 71381 | K49: ='County PopulationPovertyRacial '!D2828 -> 9.7 | L49: =#REF! -> #REF! | M49: {=VLOOKUP($A49,AFCARSCSC!$A$4:$D$56,{3,4},FALSE)} -> 257 | N49: 1120 | O49: =#REF! -> #REF! | P49: =#REF! -> #REF! | Q49: =#REF! -> #REF! | R49: =#REF! -> #REF! | S49: =(P49/B49)*1000 -> #REF!
A50: Vermont | B50: {=VLOOKUP($A50,VT_DEMO,{2,5,6,7,8,9,10,11,12,4},FALSE)} -> 643077 | C50: 577751 | D50: 9034 | E50: 2289 | F50: 11549 | G50: 181 | H50: 5247 | I50: 37026 | J50: 60917 | K50: 12.2 | L50: {=VLOOKUP($A50,AFCARSCSC!$A$4:$D$56,{2,3,4},FALSE)} -> 1096 | M50: 159 | N50: 810 | O50: NULL | P50: =#REF! -> #REF! | Q50: =#REF! -> #REF! | R50: =#REF! -> #REF! | S50: =(P50/B50)*1000 -> #REF!
A51: Virginia | B51: {=VLOOKUP($A51,VA_DEMO,{2,5,6,7,8,9,10,11,12,4},FALSE)} -> 8631393 | C51: 5208856 | D51: 1607581 | E51: 40007 | F51: 615436 | G51: 7156 | H51: 446650 | I51: 705707 | J51: 72600 | K51: 13.8 | L51: =#REF! -> #REF! | M51: =#REF! -> #REF! | N51: =VLOOKUP($A51,AFCARSCSC!$A$4:$D$56,4,FALSE) -> 4735 | O51: NULL | P51: =#REF! -> #REF! | Q51: =#REF! -> #REF! | R51: =#REF! -> #REF! | S51: =(P51/B51)*1000 -> #REF!
A52: Washington | B52: {=VLOOKUP($A52,WA_DEMO,{2,5,6,7,8,9,10,11,12,4},FALSE)} -> 7705281 | C52: 5130920 | D52: 307565 | E52: 121468 | F52: 730596 | G52: 64933 | H52: 513140 | I52: 836659 | J52: 74023 | K52: 12.6 | L52: =#REF! -> #REF! | M52: {=VLOOKUP($A52,AFCARSCSC!$A$4:$D$56,{3,4},FALSE)} -> 997 | N52: 4341 | O52: NULL | P52: =#REF! -> #REF! | Q52: =#REF! -> #REF! | R52: =#REF! -> #REF! | S52: =(P52/B52)*1000 -> #REF!
A53: West Virginia | B53: {=VLOOKUP($A53,WV_DEMO,{2,5,6,7,8,9,10,11,12,4},FALSE)} -> 1793716 | C53: 1610749 | D53: 65813 | E53: 3706 | F53: 15109 | G53: 476 | H53: 12919 | I53: 84944 | J53: 44038 | K53: 23.2 | L53: =#REF! -> #REF! | M53: {=VLOOKUP($A53,AFCARSCSC!$A$4:$D$56,{3,4},FALSE)} -> 1748 | N53: 3148 | O53: NULL | P53: =#REF! -> #REF! | Q53: =#REF! -> #REF! | R53: =#REF! -> #REF! | S53: =(P53/B53)*1000 -> #REF!
A54: Wisconsin | B54: {=VLOOKUP($A54,WI_DEMO,{2,5,6,7,8,9,10,11,12,4},FALSE)} -> 5893718 | C54: 4737545 | D54: 376256 | E54: 60428 | F54: 175702 | G54: 2199 | H54: 182054 | I54: 359534 | J54: 60779 | K54: 14.1 | L54: =#REF! -> #REF! | M54: {=VLOOKUP($A54,AFCARSCSC!$A$4:$D$56,{3,4},FALSE)} -> 667 | N54: 2968 | O54: NULL | P54: =#REF! -> #REF! | Q54: =#REF! -> #REF! | R54: =#REF! -> #REF! | S54: =(P54/B54)*1000 -> #REF!
A55: Wyoming | B55: {=VLOOKUP($A55,WY_DEMO,{2,5,6,7,8,9,10,11,12,4},FALSE)} -> 576851 | C55: 488374 | D55: 5232 | E55: 13898 | F55: 5212 | G55: 579 | H55: 20083 | I55: 43473 | J55: 62259 | K55: 13.1 | L55: {=VLOOKUP($A55,AFCARSCSC!$A$4:$D$56,{2,3,4},FALSE)} -> 756 | M55: 10 | N55: 468 | O55: NULL | P55: =#REF! -> #REF! | Q55: =#REF! -> #REF! | R55: =#REF! -> #REF! | S55: =(P55/B55)*1000 -> #REF!
A57: United States | B57: {=VLOOKUP($A57,US_DEMO,{2,5,6,7,8,9,10,11,12,4},FALSE)} -> 331449281 | C57: 204277273 | D57: 41104200 | E57: 3727135 | F57: 19886049 | G57: 689966 | H57: 27915715 | I57: 33848943 | J57: 61937 | K57: 18 | L57: {=VLOOKUP($A57,AFCARSCSC!$A$4:$D$56,{2,3,4},FALSE)} -> 368530 | M57: 64561 | N57: 208823 | O57: NULL | P57: 234667 | Q57: =SUM(Q5:Q55) -> #REF! | R57: =SUM(R5:R55) -> #REF! | S57: =(P57/B57)*1000 -> 0.70800274

Sheet Top 50%
D2: Top 130 Counties- 50% of Children in Care
D3: County Demographics | N3: Foster Care Data | S3: Church Data
E4: Population by Race
B5: County | C5: State | D5: County Population | E5: White | F5: Black or African American | G5: American Indian and Alaska Native | H5: Asian | I5: Native Hawaiian and Other Pacific Islander | J5: Other race | K5: Two or more races | L5: Median Household Income | M5: Poverty Rate | N5: Number of Children in Out-of-Home Placement | O5: Number of Children in Kinship Care | P5: Number of Children Waiting for Adoption | Q5: Number of Licensed Foster Homes | R5: Number of Family Preservation Cases | S5: Number of Churches | T5: Number of Actively Engaged Churches Needed | U5: Churches per 1,000 People | V5: Children in Care per Church | W5: Churches per Children in Care
A6: 1 | B6: Los Angeles | C6: CA | D6: =California!B$21 -> 10014009 | E6: =California!C$21 -> 15018 | F6: =California!D$21 -> NULL | G6: =California!E$21 -> 6150 | H6: =California!F$21 -> 6029 | I6: =California!G$21 -> NULL | J6: =California!H$21 -> NULL | K6: =California!I$21 -> 3563 | ... M6: =California!K$21 -> 0.48168193 | N6: {=VLOOKUP($B6,'CarePortal - Audrey'!$A$2:$T$166,{8,17,18,20},FALSE)} -> #REF! | O6: #REF! | P6: #REF! | Q6: #REF! | R6: =#REF! -> #REF! | S6: =#REF! -> #REF! | T6: =#REF! -> #REF! | U6: =#REF! -> #REF! | V6: =#REF! -> #REF! | W6: =#REF! -> #REF!
A7: 2 | B7: Cook | C7: IL | D7: =Illinois!B$18 -> 5275541 | E7: =Illinois!C$18 -> 2458 | F7: =Illinois!D$18 -> NULL | G7: =Illinois!E$18 -> 1044 | H7: =Illinois!F$18 -> 1191 | I7: =Illinois!G$18 -> NULL | J7: =Illinois!H$18 -> 1282 | K7: =Illinois!I$18 -> 169 | ... M7: =Illinois!K$18 -> NULL | N7: {=VLOOKUP($B7,'CarePortal - Audrey'!$A$2:$T$166,{8,17,18,20},FALSE)} -> #REF! | O7: #REF! | P7: #REF! | Q7: #REF! | R7: =#REF! -> #REF! | S7: =#REF! -> #REF! | T7: =#REF! -> #REF! | U7: =#REF! -> #REF! | V7: =#REF! -> #REF! | W7: =#REF! -> #REF!
A8: 3 | B8: Harris | C8: TX | D8: =#REF! -> #REF! | E8: =#REF! -> #REF! | F8: =#REF! -> #REF! | G8: =#REF! -> #REF! | H8: =#REF! -> #REF! | I8: =#REF! -> #REF! | J8: =#REF! -> #REF! | K8: =#REF! -> #REF! | ... M8: =#REF! -> #REF! | N8: {=VLOOKUP($B8,'CarePortal - Audrey'!$A$2:$T$166,{8,17,18,20},FALSE)} -> #REF! | O8: #REF! | P8: #REF! | Q8: #REF! | R8: =#REF! -> #REF! | S8: =#REF! -> #REF! | T8: =#REF! -> #REF! | U8: =#REF! -> #REF! | V8: =#REF! -> #REF! | W8: =#REF! -> #REF!
A9: 4 | B9: Maricopa | C9: AZ | D9: =Arizona!B$10 -> 4420568 | E9: =Arizona!C$10 -> 5184 | F9: =Arizona!D$10 -> NULL | G9: =Arizona!E$10 -> NULL | H9: =Arizona!F$10 -> NULL | I9: =Arizona!G$10 -> NULL | J9: =Arizona!H$10 -> NULL | K9: =Arizona!I$10 -> NULL | ... M9: =Arizona!K$10 -> NULL | N9: {=VLOOKUP($B9,'CarePortal - Audrey'!$A$2:$T$166,{8,17,18,20},FALSE)} -> #REF! | O9: #REF! | P9: #REF! | Q9: #REF! | R9: =#REF! -> #REF! | S9: =#REF! -> #REF! | T9: =#REF! -> #REF! | U9: =#REF! -> #REF! | V9: =#REF! -> #REF! | W9: =#REF! -> #REF!
A10: 5 | B10: San Diego | C10: CA | D10: =California!B$39 -> 3298634 | E10: =California!C$39 -> 1655 | F10: =California!D$39 -> NULL | G10: =California!E$39 -> 636 | H10: =California!F$39 -> 587 | I10: =California!G$39 -> NULL | J10: =California!H$39 -> NULL | K10: =California!I$39 -> 192 | ... M10: =California!K$39 -> 0.45605469 | N10: {=VLOOKUP($B10,'CarePortal - Audrey'!$A$2:$T$166,{8,17,18,20},FALSE)} -> #REF! | O10: #REF! | P10: #REF! | Q10: #REF! | R10: =#REF! -> #REF! | S10: =#REF! -> #REF! | T10: =#REF! -> #REF! | U10: =#REF! -> #REF! | V10: =#REF! -> #REF! | W10: =#REF! -> #REF!
A11: 6 | B11: Orange | C11: CA | D11: =California!B$32 -> 3186989 | E11: =California!C$32 -> 2205 | F11: =California!D$32 -> NULL | G11: =California!E$32 -> 543 | H11: =California!F$32 -> 1107 | I11: =California!G$32 -> NULL | J11: =California!H$32 -> NULL | K11: =California!I$32 -> 344 | ... M11: =California!K$32 -> 0.52457695 | N11: {=VLOOKUP($B11,'CarePortal - Audrey'!$A$2:$T$166,{8,17,18,20},FALSE)} -> #REF! | O11: #REF! | P11: #REF! | Q11: #REF! | R11: =#REF! -> #REF! | S11: =#REF! -> #REF! | T11: =#REF! -> #REF! | U11: =#REF! -> #REF! | V11: =#REF! -> #REF! | W11: =#REF! -> #REF!
A12: 7 | B12: Miami-Dade | C12: FL | D12: =Florida!B$45 -> 2701767 | E12: =Florida!C$45 -> 1338 | F12: =Florida!D$45 -> NULL | G12: =Florida!E$45 -> 709 | H12: =Florida!F$45 -> 348 | I12: =Florida!G$45 -> NULL | J12: =Florida!H$45 -> NULL | K12: =Florida!I$45 -> NULL | ... M12: =Florida!K$45 -> 0.65799257 | N12: {=VLOOKUP($B12,'CarePortal - Audrey'!$A$2:$T$166,{8,17,18,20},FALSE)} -> #REF! | O12: #REF! | P12: #REF! | Q12: #REF! | R12: =#REF! -> #REF! | S12: =#REF! -> #REF! | T12: =#REF! -> #REF! | U12: =#REF! -> #REF! | V12: =#REF! -> #REF! | W12: =#REF! -> #REF!
A13: 8 | B13: Dallas | C13: TX | D13: =Texas!B$254 -> 17867 | E13: =Texas!C$254 -> 50 | F13: =Texas!D$254 -> NULL | G13: =Texas!E$254 -> 29 | H13: =Texas!F$254 -> 16 | I13: =Texas!G$254 -> NULL | J13: =Texas!H$254 -> 21 | K13: =Texas!I$254 -> 1 | ... M13: =Texas!K$254 -> NULL | N13: {=VLOOKUP($B13,'CarePortal - Audrey'!$A$2:$T$166,{8,17,18,20},FALSE)} -> #REF! | O13: #REF! | P13: #REF! | Q13: #REF! | R13: =#REF! -> #REF! | S13: =#REF! -> #REF! | T13: =#REF! -> #REF! | U13: =#REF! -> #REF! | V13: =#REF! -> #REF! | W13: =#REF! -> #REF!
A14: 9 | B14: Kings | C14: NY | D14: ='New York'!B$26 -> 2736074 | E14: ='New York'!C$26 -> NULL | F14: ='New York'!D$26 -> NULL | G14: ='New York'!E$26 -> NULL | H14: ='New York'!F$26 -> NULL | I14: ='New York'!G$26 -> NULL | J14: ='New York'!H$26 -> NULL | K14: ='New York'!I$26 -> NULL | ... M14: ='New York'!K$26 -> NULL | N14: {=VLOOKUP($B14,'CarePortal - Audrey'!$A$2:$T$166,{8,17,18,20},FALSE)} -> #REF! | O14: #REF! | P14: #REF! | Q14: #REF! | R14: =#REF! -> #REF! | S14: =#REF! -> #REF! | T14: =#REF! -> #REF! | U14: =#REF! -> #REF! | V14: =#REF! -> #REF! | W14: =#REF! -> #REF!
A15: 10 | B15: Riverside | C15: CA | D15: =California!B$35 -> 2418185 | E15: =California!C$35 -> 3119 | F15: =California!D$35 -> NULL | G15: =California!E$35 -> 1320 | H15: =California!F$35 -> 1177 | I15: =California!G$35 -> NULL | J15: =California!H$35 -> NULL | K15: =California!I$35 -> 357 | ... M15: =California!K$35 -> 0.52603471 | N15: {=VLOOKUP($B15,'CarePortal - Audrey'!$A$2:$T$166,{8,17,18,20},FALSE)} -> #REF! | O15: #REF! | P15: #REF! | Q15: #REF! | R15: =#REF! -> #REF! | S15: =#REF! -> #REF! | T15: =#REF! -> #REF! | U15: =#REF! -> #REF! | V15: =#REF! -> #REF! | W15: =#REF! -> #REF!
A16: 11 | B16: Queens | C16: NY | D16: ='New York'!B$43 -> 2405464 | E16: ='New York'!C$43 -> NULL | F16: ='New York'!D$43 -> NULL | G16: ='New York'!E$43 -> NULL | H16: ='New York'!F$43 -> NULL | I16: ='New York'!G$43 -> NULL | J16: ='New York'!H$43 -> NULL | K16: ='New York'!I$43 -> NULL | ... M16: ='New York'!K$43 -> NULL | N16: {=VLOOKUP($B16,'CarePortal - Audrey'!$A$2:$T$166,{8,17,18,20},FALSE)} -> #REF! | O16: #REF! | P16: #REF! | Q16: #REF! | R16: =#REF! -> #REF! | S16: =#REF! -> #REF! | T16: =#REF! -> #REF! | U16: =#REF! -> #REF! | V16: =#REF! -> #REF! | W16: =#REF! -> #REF!
A17: 12 | B17: King | C17: WA | D17: =Washington!B$19 -> 2269675 | E17: =Washington!C$19 -> NULL | F17: =Washington!D$19 -> NULL | G17: =Washington!E$19 -> NULL | H17: =Washington!F$19 -> NULL | I17: =Washington!G$19 -> NULL | J17: =Washington!H$19 -> NULL | K17: =Washington!I$19 -> NULL | ... M17: =Washington!K$19 -> NULL | N17: {=VLOOKUP($B17,'CarePortal - Audrey'!$A$2:$T$166,{8,17,18,20},FALSE)} -> #REF! | O17: #REF! | P17: #REF! | Q17: #REF! | R17: =#REF! -> #REF! | S17: =#REF! -> #REF! | T17: =#REF! -> #REF! | U17: =#REF! -> #REF! | V17: =#REF! -> #REF! | W17: =#REF! -> #REF!
A18: 13 | B18: Clark | C18: NV | D18: =Nevada!B$5 -> 49488 | E18: =Nevada!C$5 -> NULL | F18: =Nevada!D$5 -> NULL | G18: =Nevada!E$5 -> NULL | H18: =Nevada!F$5 -> NULL | I18: =Nevada!G$5 -> NULL | J18: =Nevada!H$5 -> NULL | K18: =Nevada!I$5 -> NULL | ... M18: =Nevada!K$5 -> NULL | N18: {=VLOOKUP($B18,'CarePortal - Audrey'!$A$2:$T$166,{8,17,18,20},FALSE)} -> #REF! | O18: #REF! | P18: #REF! | Q18: #REF! | R18: =#REF! -> #REF! | S18: =#REF! -> #REF! | T18: =#REF! -> #REF! | U18: =#REF! -> #REF! | V18: =#REF! -> #REF! | W18: =#REF! -> #REF!
A19: 14 | B19: San Bernardino | C19: CA | D19: =California!B$38 -> 2181654 | E19: =California!C$38 -> 4996 | F19: =California!D$38 -> NULL | G19: =California!E$38 -> 2220 | H19: =California!F$38 -> 1544 | I19: =California!G$38 -> NULL | J19: =California!H$38 -> NULL | K19: =California!I$38 -> 643 | ... M19: =California!K$38 -> 0.45051635 | N19: {=VLOOKUP($B19,'CarePortal - Audrey'!$A$2:$T$166,{8,17,18,20},FALSE)} -> #REF! | O19: #REF! | P19: #REF! | Q19: #REF! | R19: =#REF! -> #REF! | S19: =#REF! -> #REF! | T19: =#REF! -> #REF! | U19: =#REF! -> #REF! | V19: =#REF! -> #REF! | W19: =#REF! -> #REF!
A20: 15 | B20: Tarrant | C20: TX | D20: =#REF! -> #REF! | E20: =#REF! -> #REF! | F20: =#REF! -> #REF! | G20: =#REF! -> #REF! | H20: =#REF! -> #REF! | I20: =#REF! -> #REF! | J20: =#REF! -> #REF! | K20: =#REF! -> #REF! | ... M20: =#REF! -> #REF! | N20: {=VLOOKUP($B20,'CarePortal - Audrey'!$A$2:$T$166,{8,17,18,20},FALSE)} -> #REF! | O20: #REF! | P20: #REF! | Q20: #REF! | R20: =#REF! -> #REF! | S20: =#REF! -> #REF! | T20: =#REF! -> #REF! | U20: =#REF! -> #REF! | V20: =#REF! -> #REF! | W20: =#REF! -> #REF!
A21: 16 | B21: Bexar | C21: TX | D21: =Texas!B$212 -> 24022 | E21: =Texas!C$212 -> 28 | F21: =Texas!D$212 -> NULL | G21: =Texas!E$212 -> 13 | H21: =Texas!F$212 -> 13 | I21: =Texas!G$212 -> NULL | J21: =Texas!H$212 -> 18 | K21: =Texas!I$212 -> 4 | ... M21: =Texas!K$212 -> NULL | N21: {=VLOOKUP($B21,'CarePortal - Audrey'!$A$2:$T$166,{8,17,18,20},FALSE)} -> #REF! | O21: #REF! | P21: #REF! | Q21: #REF! | R21: =#REF! -> #REF! | S21: =#REF! -> #REF! | T21: =#REF! -> #REF! | U21: =#REF! -> #REF! | V21: =#REF! -> #REF! | W21: =#REF! -> #REF!
A22: 17 | B22: Broward | C22: FL | D22: =Florida!B$8 -> 1944375 | E22: =Florida!C$8 -> 1067 | F22: =Florida!D$8 -> NULL | G22: =Florida!E$8 -> 456 | H22: =Florida!F$8 -> 365 | I22: =Florida!G$8 -> NULL | J22: =Florida!H$8 -> NULL | K22: =Florida!I$8 -> NULL | ... M22: =Florida!K$8 -> 0.6872093 | N22: {=VLOOKUP($B22,'CarePortal - Audrey'!$A$2:$T$166,{8,17,18,20},FALSE)} -> #REF! | O22: #REF! | P22: #REF! | Q22: #REF! | R22: =#REF! -> #REF! | S22: =#REF! -> #REF! | T22: =#REF! -> #REF! | U22: =#REF! -> #REF! | V22: =#REF! -> #REF! | W22: =#REF! -> #REF!
A23: 18 | B23: Santa Clara | C23: CA | D23: =California!B$45 -> 1936259 | E23: =California!C$45 -> 494 | F23: =California!D$45 -> NULL | G23: =California!E$45 -> 234 | H23: =California!F$45 -> 111 | I23: =California!G$45 -> NULL | J23: =California!H$45 -> NULL | K23: =California!I$45 -> 85 | ... M23: =California!K$45 -> 0.22772277 | N23: {=VLOOKUP($B23,'CarePortal - Audrey'!$A$2:$T$166,{8,17,18,20},FALSE)} -> #REF! | O23: #REF! | P23: #REF! | Q23: #REF! | R23: =#REF! -> #REF! | S23: =#REF! -> #REF! | T23: =#REF! -> #REF! | U23: =#REF! -> #REF! | V23: =#REF! -> #REF! | W23: =#REF! -> #REF!
A24: 19 | B24: Wayne | C24: MI | D24: =#REF! -> #REF! | E24: =#REF! -> #REF! | F24: =#REF! -> #REF! | G24: =#REF! -> #REF! | H24: =#REF! -> #REF! | I24: =#REF! -> #REF! | J24: =#REF! -> #REF! | K24: =#REF! -> #REF! | ... M24: =#REF! -> #REF! | N24: {=VLOOKUP($B24,'CarePortal - Audrey'!$A$2:$T$166,{8,17,18,20},FALSE)} -> #REF! | O24: #REF! | P24: #REF! | Q24: #REF! | R24: =#REF! -> #REF! | S24: =#REF! -> #REF! | T24: =#REF! -> #REF! | U24: =#REF! -> #REF! | V24: =#REF! -> #REF! | W24: =#REF! -> #REF!
A25: 20 | B25: Alameda | C25: CA | D25: =California!B$3 -> 1682353 | E25: =California!C$3 -> 916 | F25: =California!D$3 -> NULL | G25: =California!E$3 -> 294 | H25: =California!F$3 -> 336 | I25: =California!G$3 -> NULL | J25: =California!H$3 -> NULL | K25: =California!I$3 -> 86 | ... M25: =California!K$3 -> 0.40648379 | N25: {=VLOOKUP($B25,'CarePortal - Audrey'!$A$2:$T$166,{8,17,18,20},FALSE)} -> #REF! | O25: #REF! | P25: #REF! | Q25: #REF! | R25: =#REF! -> #REF! | S25: =#REF! -> #REF! | T25: =#REF! -> #REF! | U25: =#REF! -> #REF! | V25: =#REF! -> #REF! | W25: =#REF! -> #REF!
A26: 21 | B26: New York | C26: NY | D26: ='New York'!B$33 -> 1694251 | E26: ='New York'!C$33 -> NULL | F26: ='New York'!D$33 -> NULL | G26: ='New York'!E$33 -> NULL | H26: ='New York'!F$33 -> NULL | I26: ='New York'!G$33 -> NULL | J26: ='New York'!H$33 -> NULL | K26: ='New York'!I$33 -> NULL | ... M26: ='New York'!K$33 -> NULL | N26: {=VLOOKUP($B26,'CarePortal - Audrey'!$A$2:$T$166,{8,17,18,20},FALSE)} -> #REF! | O26: #REF! | P26: #REF! | Q26: #REF! | R26: =#REF! -> #REF! | S26: =#REF! -> #REF! | T26: =#REF! -> #REF! | U26: =#REF! -> #REF! | V26: =#REF! -> #REF! | W26: =#REF! -> #REF!
A27: 22 | B27: Middlesex | C27: MA | D27: =#REF! -> #REF! | E27: =#REF! -> #REF! | F27: =#REF! -> #REF! | G27: =#REF! -> #REF! | H27: =#REF! -> #REF! | I27: =#REF! -> #REF! | J27: =#REF! -> #REF! | K27: =#REF! -> #REF! | ... M27: =#REF! -> #REF! | N27: {=VLOOKUP($B27,'CarePortal - Audrey'!$A$2:$T$166,{8,17,18,20},FALSE)} -> #REF! | O27: #REF! | P27: #REF! | Q27: #REF! | R27: =#REF! -> #REF! | S27: =#REF! -> #REF! | T27: =#REF! -> #REF! | U27: =#REF! -> #REF! | V27: =#REF! -> #REF! | W27: =#REF! -> #REF!
A28: 23 | B28: Philadelphia | C28: PA | D28: =Pennsylvania!B$53 -> 1603797 | E28: =Pennsylvania!C$53 -> 3753 | F28: =Pennsylvania!D$53 -> NULL | G28: =Pennsylvania!E$53 -> 1452 | H28: =Pennsylvania!F$53 -> 1850 | I28: =Pennsylvania!G$53 -> NULL | J28: =Pennsylvania!H$53 -> NULL | K28: =Pennsylvania!I$53 -> NULL | ... M28: =Pennsylvania!K$53 -> NULL | N28: {=VLOOKUP($B28,'CarePortal - Audrey'!$A$2:$T$166,{8,17,18,20},FALSE)} -> #REF! | O28: #REF! | P28: #REF! | Q28: #REF! | R28: =#REF! -> #REF! | S28: =#REF! -> #REF! | T28: =#REF! -> #REF! | U28: =#REF! -> #REF! | V28: =#REF! -> #REF! | W28: =#REF! -> #REF!
A29: 24 | B29: Sacramento | C29: CA | D29: =California!B$36 -> 1585055 | E29: =California!C$36 -> 1176 | F29: =California!D$36 -> NULL | G29: =California!E$36 -> 457 | H29: =California!F$36 -> 277 | I29: =California!G$36 -> NULL | J29: =California!H$36 -> NULL | K29: =California!I$36 -> 166 | ... M29: =California!K$36 -> 0.4616307 | N29: {=VLOOKUP($B29,'CarePortal - Audrey'!$A$2:$T$166,{8,17,18,20},FALSE)} -> #REF! | O29: #REF! | P29: #REF! | Q29: #REF! | R29: =#REF! -> #REF! | S29: =#REF! -> #REF! | T29: =#REF! -> #REF! | U29: =#REF! -> #REF! | V29: =#REF! -> #REF! | W29: =#REF! -> #REF!
A30: 25 | B30: Palm Beach | C30: FL | D30: =Florida!B$52 -> 1492191 | E30: =Florida!C$52 -> 854 | F30: =Florida!D$52 -> NULL | G30: =Florida!E$52 -> 347 | H30: =Florida!F$52 -> 289 | I30: =Florida!G$52 -> NULL | J30: =Florida!H$52 -> NULL | K30: =Florida!I$52 -> NULL | ... M30: =Florida!K$52 -> 0.7578534 | N30: {=VLOOKUP($B30,'CarePortal - Audrey'!$A$2:$T$166,{8,17,18,20},FALSE)} -> #REF! | O30: #REF! | P30: #REF! | Q30: #REF! | R30: =#REF! -> #REF! | S30: =#REF! -> #REF! | T30: =#REF! -> #REF! | U30: =#REF! -> #REF! | V30: =#REF! -> #REF! | W30: =#REF! -> #REF!
A31: 26 | B31: Suffolk | C31: NY | D31: ='New York'!B$54 -> 1525920 | E31: ='New York'!C$54 -> 518 | F31: ='New York'!D$54 -> 1.9534368 | G31: ='New York'!E$54 -> 241 | H31: ='New York'!F$54 -> 163 | I31: ='New York'!G$54 -> NULL | J31: ='New York'!H$54 -> 451 | K31: ='New York'!I$54 -> 170 | ... M31: ='New York'!K$54 -> 0.597 | N31: {=VLOOKUP($B31,'CarePortal - Audrey'!$A$2:$T$166,{8,17,18,20},FALSE)} -> #REF! | O31: #REF! | P31: #REF! | Q31: #REF! | R31: =#REF! -> #REF! | S31: =#REF! -> #REF! | T31: =#REF! -> #REF! | U31: =#REF! -> #REF! | V31: =#REF! -> #REF! | W31: =#REF! -> #REF!
A32: 27 | B32: Hillsborough | C32: FL | D32: =Florida!B$30 -> 1459762 | E32: =Florida!C$30 -> 1716 | F32: =Florida!D$30 -> NULL | G32: =Florida!E$30 -> 831 | H32: =Florida!F$30 -> 510 | I32: =Florida!G$30 -> NULL | J32: =Florida!H$30 -> NULL | K32: =Florida!I$30 -> NULL | ... M32: =Florida!K$30 -> 0.93942218 | N32: {=VLOOKUP($B32,'CarePortal - Audrey'!$A$2:$T$166,{8,17,18,20},FALSE)} -> #REF! | O32: #REF! | P32: #REF! | Q32: #REF! | R32: =#REF! -> #REF! | S32: =#REF! -> #REF! | T32: =#REF! -> #REF! | U32: =#REF! -> #REF! | V32: =#REF! -> #REF! | W32: =#REF! -> #REF!
A33: 28 | B33: Bronx | C33: NY | D33: ='New York'!B$5 -> 1472654 | E33: ='New York'!C$5 -> NULL | F33: ='New York'!D$5 -> NULL | G33: ='New York'!E$5 -> NULL | H33: ='New York'!F$5 -> NULL | I33: ='New York'!G$5 -> NULL | J33: ='New York'!H$5 -> NULL | K33: ='New York'!I$5 -> NULL | ... M33: ='New York'!K$5 -> NULL | N33: {=VLOOKUP($B33,'CarePortal - Audrey'!$A$2:$T$166,{8,17,18,20},FALSE)} -> #REF! | O33: #REF! | P33: #REF! | Q33: #REF! | R33: =#REF! -> #REF! | S33: =#REF! -> #REF! | T33: =#REF! -> #REF! | U33: =#REF! -> #REF! | V33: =#REF! -> #REF! | W33: =#REF! -> #REF!
A34: 29 | B34: Orange | C34: FL | D34: =Florida!B$50 -> 1429908 | E34: =Florida!C$50 -> 943 | F34: =Florida!D$50 -> NULL | G34: =Florida!E$50 -> 434 | H34: =Florida!F$50 -> 305 | I34: =Florida!G$50 -> NULL | J34: =Florida!H$50 -> NULL | K34: =Florida!I$50 -> NULL | ... M34: =Florida!K$50 -> 0.83755274 | N34: {=VLOOKUP($B34,'CarePortal - Audrey'!$A$2:$T$166,{8,17,18,20},FALSE)} -> #REF! | O34: #REF! | P34: #REF! | Q34: #REF! | R34: =#REF! -> #REF! | S34: =#REF! -> #REF! | T34: =#REF! -> #REF! | U34: =#REF! -> #REF! | V34: =#REF! -> #REF! | W34: =#REF! -> #REF!
A35: 30 | B35: Nassau | C35: NY | D35: ='New York'!B$32 -> 1395774 | E35: ='New York'!C$32 -> 159 | F35: ='New York'!D$32 -> 2.7647059 | G35: ='New York'!E$32 -> 87 | H35: ='New York'!F$32 -> 24 | I35: ='New York'!G$32 -> NULL | J35: ='New York'!H$32 -> 213 | K35: ='New York'!I$32 -> 37 | ... M35: ='New York'!K$32 -> 0.707 | N35: {=VLOOKUP($B35,'CarePortal - Audrey'!$A$2:$T$166,{8,17,18,20},FALSE)} -> #REF! | O35: #REF! | P35: #REF! | Q35: #REF! | R35: =#REF! -> #REF! | S35: =#REF! -> #REF! | T35: =#REF! -> #REF! | U35: =#REF! -> #REF! | V35: =#REF! -> #REF! | W35: =#REF! -> #REF!
A36: 31 | B36: Franklin | C36: OH | D36: =Ohio!B$88 -> 37102 | E36: =Ohio!C$88 -> 30 | F36: =Ohio!D$88 -> NULL | G36: =Ohio!E$88 -> 23 | H36: =Ohio!F$88 -> NULL | I36: =Ohio!G$88 -> NULL | J36: =Ohio!H$88 -> NULL | K36: =Ohio!I$88 -> NULL | ... M36: =Ohio!K$88 -> 0.69565217 | N36: {=VLOOKUP($B36,'CarePortal - Audrey'!$A$2:$T$166,{8,17,18,20},FALSE)} -> #REF! | O36: #REF! | P36: #REF! | Q36: #REF! | R36: =#REF! -> #REF! | S36: =#REF! -> #REF! | T36: =#REF! -> #REF! | U36: =#REF! -> #REF! | V36: =#REF! -> #REF! | W36: =#REF! -> #REF!
A37: 32 | B37: Hennepin | C37: MN | N37: {=VLOOKUP($B37,'CarePortal - Audrey'!$A$2:$T$166,{8,17,18,20},FALSE)} -> #REF! | O37: #REF! | P37: #REF! | Q37: #REF!
A38: 33 | B38: Oakland | C38: MI | N38: {=VLOOKUP($B38,'CarePortal - Audrey'!$A$2:$T$166,{8,17,18,20},FALSE)} -> #REF! | O38: #REF! | P38: #REF! | Q38: #REF!
A39: 34 | B39: Travis | C39: TX | N39: {=VLOOKUP($B39,'CarePortal - Audrey'!$A$2:$T$166,{8,17,18,20},FALSE)} -> #REF! | O39: #REF! | P39: #REF! | Q39: #REF!
A40: 35 | B40: Cuyahoga | C40: OH | N40: {=VLOOKUP($B40,'CarePortal - Audrey'!$A$2:$T$166,{8,17,18,20},FALSE)} -> #REF! | O40: #REF! | P40: #REF! | Q40: #REF!
A41: 36 | B41: Allegheny | C41: PA | N41: {=VLOOKUP($B41,'CarePortal - Audrey'!$A$2:$T$166,{8,17,18,20},FALSE)} -> #REF! | O41: #REF! | P41: #REF! | Q41: #REF!
A42: 37 | B42: Salt Lake | C42: UT | N42: {=VLOOKUP($B42,'CarePortal - Audrey'!$A$2:$T$166,{8,17,18,20},FALSE)} -> #REF! | O42: #REF! | P42: #REF! | Q42: #REF!
A43: 38 | B43: Fairfax County | C43: VA
A44: 39 | B44: Contra Costa | C44: CA | N44: {=VLOOKUP($B44,'CarePortal - Audrey'!$A$2:$T$166,{8,17,18,20},FALSE)} -> #REF! | O44: #REF! | P44: #REF! | Q44: #REF!
A45: 40 | B45: Mecklenburg | C45: NC | N45: {=VLOOKUP($B45,'CarePortal - Audrey'!$A$2:$T$166,{8,17,18,20},FALSE)} -> #REF! | O45: #REF! | P45: #REF! | Q45: #REF!
A46: 41 | B46: Wake | C46: NC | N46: {=VLOOKUP($B46,'CarePortal - Audrey'!$A$2:$T$166,{8,17,18,20},FALSE)} -> #REF! | O46: #REF! | P46: #REF! | Q46: #REF!
A47: 42 | B47: Montgomery | C47: MD | N47: {=VLOOKUP($B47,'CarePortal - Audrey'!$A$2:$T$166,{8,17,18,20},FALSE)} -> #REF! | O47: #REF! | P47: #REF! | Q47: #REF!
A48: 43 | B48: Fulton | C48: GA | N48: {=VLOOKUP($B48,'CarePortal - Audrey'!$A$2:$T$166,{8,17,18,20},FALSE)} -> #REF! | O48: #REF! | P48: #REF! | Q48: #REF!
A49: 44 | B49: Pima | C49: AZ | N49: {=VLOOKUP($B49,'CarePortal - Audrey'!$A$2:$T$166,{8,17,18,20},FALSE)} -> #REF! | O49: #REF! | P49: #REF! | Q49: #REF!
A50: 45 | B50: Collin | C50: TX | N50: {=VLOOKUP($B50,'CarePortal - Audrey'!$A$2:$T$166,{8,17,18,20},FALSE)} -> #REF! | O50: #REF! | P50: #REF! | Q50: #REF!
A51: 46 | B51: St. Louis | C51: MO | N51: {=VLOOKUP($B51,'CarePortal - Audrey'!$A$2:$T$166,{8,17,18,20},FALSE)} -> #REF! | O51: #REF! | P51: #REF! | Q51: #REF!
A52: 47 | B52: Fresno | C52: CA | N52: {=VLOOKUP($B52,'CarePortal - Audrey'!$A$2:$T$166,{8,17,18,20},FALSE)} -> #REF! | O52: #REF! | P52: #REF! | Q52: #REF!
A53: 48 | B53: Honolulu | C53: HI | N53: {=VLOOKUP($B53,'CarePortal - Audrey'!$A$2:$T$166,{8,17,18,20},FALSE)} -> #REF! | O53: #REF! | P53: #REF! | Q53: #REF!
A54: 49 | B54: Pinellas | C54: FL | N54: {=VLOOKUP($B54,'CarePortal - Audrey'!$A$2:$T$166,{8,17,18,20},FALSE)} -> #REF! | O54: #REF! | P54: #REF! | Q54: #REF!
A55: 50 | B55: Westchester | C55: NY | N55: {=VLOOKUP($B55,'CarePortal - Audrey'!$A$2:$T$166,{8,17,18,20},FALSE)} -> #REF! | O55: #REF! | P55: #REF! | Q55: #REF!
... A135: 130 | B135: Kane | C135: IL | N135: {=VLOOKUP($B135,'CarePortal - Audrey'!$A$2:$T$166,{8,17,18,20},FALSE)} -> #REF! | O135: #REF! | P135: #REF! | Q135: #REF!

Sheet Alabama
B1: Alabama
A2: County | B2: County Population | C2: Number of Children in Care | D2: Average Beds per Family | E2: Number of Children in Foster Care | F2: Number of Children in Kinship Care | G2: Number of Children Placed Out-of-County | H2: Number of Foster and Kinship Homes | I2: Number of Children Waiting for Adoption | J2: Number of Children with 80+ Connections Made | K2: Biological Family Reunification Rate | L2: Number of Family Preservation Cases | M2: Number of Adoptive Families | N2: Number of Biological Families | O2: Number of Wraparound Supporters | P2: Number of Churches | Q2: Foster Family Retention Rate
A3: Autauga | B3: {=VLOOKUP($A3,AL_DEMO,2,FALSE)} -> 58805 | C3: NULL | D3: NULL | E3: NULL | F3: NULL | G3: NULL | H3: NULL | I3: NULL | J3: NULL | K3: NULL | L3: NULL | M3: NULL | N3: NULL | O3: NULL | P3: NULL | Q3: NULL
A4: Baldwin | B4: {=VLOOKUP($A4,AL_DEMO,2,FALSE)} -> 231767 | C4: NULL | D4: NULL | E4: NULL | F4: NULL | G4: NULL | H4: NULL | I4: NULL | J4: NULL | K4: NULL | L4: NULL | M4: NULL | N4: NULL | O4: NULL | P4: NULL | Q4: NULL
A5: Barbour | B5: {=VLOOKUP($A5,AL_DEMO,2,FALSE)} -> 25223 | C5: NULL | D5: NULL | E5: NULL | F5: NULL | G5: NULL | H5: NULL | I5: NULL | J5: NULL | K5: NULL | L5: NULL | M5: NULL | N5: NULL | O5: NULL | P5: NULL | Q5: NULL
A6: Bibb | B6: {=VLOOKUP($A6,AL_DEMO,2,FALSE)} -> 22293 | C6: NULL | D6: NULL | E6: NULL | F6: NULL | G6: NULL | H6: NULL | I6: NULL | J6: NULL | K6: NULL | L6: NULL | M6: NULL | N6: NULL | O6: NULL | P6: NULL | Q6: NULL
A7: Blount | B7: {=VLOOKUP($A7,AL_DEMO,2,FALSE)} -> 59134 | C7: NULL | D7: NULL | E7: NULL | F7: NULL | G7: NULL | H7: NULL | I7: NULL | J7: NULL | K7: NULL | L7: NULL | M7: NULL | N7: NULL | O7: NULL | P7: NULL | Q7: NULL
A8: Bullock | B8: {=VLOOKUP($A8,AL_DEMO,2,FALSE)} -> 10357 | C8: NULL | D8: NULL | E8: NULL | F8: NULL | G8: NULL | H8: NULL | I8: NULL | J8: NULL | K8: NULL | L8: NULL | M8: NULL | N8: NULL | O8: NULL | P8: NULL | Q8: NULL
A9: Butler | B9: {=VLOOKUP($A9,AL_DEMO,2,FALSE)} -> 19051 | C9: NULL | D9: NULL | E9: NULL | F9: NULL | G9: NULL | H9: NULL | I9: NULL | J9: NULL | K9: NULL | L9: NULL | M9: NULL | N9: NULL | O9: NULL | P9: NULL | Q9: NULL
A10: Calhoun | B10: {=VLOOKUP($A10,AL_DEMO,2,FALSE)} -> 116441 | C10: NULL | D10: NULL | E10: NULL | F10: NULL | G10: NULL | H10: NULL | I10: NULL | J10: NULL | K10: NULL | L10: NULL | M10: NULL | N10: NULL | O10: NULL | P10: NULL | Q10: NULL
A11: Chambers | B11: {=VLOOKUP($A11,AL_DEMO,2,FALSE)} -> 34772 | C11: NULL | D11: NULL | E11: NULL | F11: NULL | G11: NULL | H11: NULL | I11: NULL | J11: NULL | K11: NULL | L11: NULL | M11: NULL | N11: NULL | O11: NULL | P11: NULL | Q11: NULL
A12: Cherokee | B12: {=VLOOKUP($A12,AL_DEMO,2,FALSE)} -> 24971 | C12: NULL | D12: NULL | E12: NULL | F12: NULL | G12: NULL | H12: NULL | I12: NULL | J12: NULL | K12: NULL | L12: NULL | M12: NULL | N12: NULL | O12: NULL | P12: NULL | Q12: NULL
A13: Chilton | B13: {=VLOOKUP($A13,AL_DEMO,2,FALSE)} -> 45014 | C13: NULL | D13: NULL | E13: NULL | F13: NULL | G13: NULL | H13: NULL | I13: NULL | J13: NULL | K13: NULL | L13: NULL | M13: NULL | N13: NULL | O13: NULL | P13: NULL | Q13: NULL
A14: Choctaw | B14: {=VLOOKUP($A14,AL_DEMO,2,FALSE)} -> 12665 | C14: NULL | D14: NULL | E14: NULL | F14: NULL | G14: NULL | H14: NULL | I14: NULL | J14: NULL | K14: NULL | L14: NULL | M14: NULL | N14: NULL | O14: NULL | P14: NULL | Q14: NULL
... A69: Winston | B69: {=VLOOKUP($A69,AL_DEMO,2,FALSE)} -> 23540 | C69: NULL | D69: NULL | E69: NULL | F69: NULL | G69: NULL | H69: NULL | I69: NULL | J69: NULL | K69: NULL | L69: NULL | M69: NULL | N69: NULL | O69: NULL | P69: NULL | Q69: NULL
A71: TOTAL | B71: ='County PopulationPovertyRacial '!B7 -> 5024279 | C71: ='AL Data'!B71 -> 5844 | D71: NULL | E71: NULL | F71: NULL | G71: NULL | H71: ='AL Data'!B200 -> 1989 | I71: ='AL Data'!B128 -> 399 | J71: NULL | K71: NULL | L71: ='AL Data'!B274 -> 4558 | M71: NULL | N71: NULL | O71: NULL | P71: =sum(P3:P69) -> 0 | Q71: NULL

Sheet AL Data
A1: NUMBER OF CHILDREN IN OUT-OF-HOME PLACEMENT | D1: SOURCE: | E1: Department of Human Resources | H1: DATE UPDATED: | I1: 44666 | J1: DATE COLLECTED: | K1: 44619
A3: County | B3: # In Care | E3: Placement Type | F3: # in each placement
A4: Autauga | B4: 45 | E4: Blank
A5: Baldwin | B5: 187 | E5: Foster Family Home (Non-Relative)
A6: Barbour | B6: 40 | E6: Foster Family Home (Relative)
A7: Bibb | B7: 39 | E7: Group Home
A8: Blount | B8: 52 | E8: Institution
A9: Bullock | B9: 13 | E9: Pre-Adoptive Home
A10: Butler | B10: 13 | E10: Runaway
A11: Calhoun | B11: 301 | E11: Supervised Independent Living
A12: Chambers | B12: 72 | E12: Trial Home Viisit
A13: Cherokee | B13: 18 | E13: Statewide Total
A14: Chilton | B14: 133
A15: Choctaw | B15: 23
A16: Clarke | B16: 14
A17: Clay | B17: 11
A18: Cleburne | B18: 31
A19: Coffee | B19: 52
A20: Colbert | B20: 79
A21: Conecuh | B21: 42
A22: Coosa | B22: 17
A23: Covington | B23: 48
A24: Crenshaw | B24: 7
A25: Cullman | B25: 167
... A71: Statewide Total | B71: 5844
A75: NUMBER OF CHILDREN WAITING FOR ADOPTION | D75: SOURCE: | E75: Department of Human Resources | H75: DATE UPDATED: | I75: 44490 | J75: DATE COLLECTED: | K75: 44614
A77: County | B77: # Waiting
A78: AUTAUGA | B78: 4
A79: BALDWIN | B79: 4
A80: BARBOUR | B80: 1
A81: BLOUNT | B81: 6
A82: CALHOUN | B82: 34
A83: CHAMBERS | B83: 4
A84: CHEROKEE | B84: 1
A85: CHILTON | B85: 6
A86: CLAY | B86: 2
A87: CLEBURNE | B87: 5
A88: COFFEE | B88: 5
A89: COLBERT | B89: 3
... A128: Statewide Total | B128: 399
A132: NUMBER OF LICENSED FOSTER HOMES | D132: SOURCE: | E132: Department of Human Resources | H132: DATE UPDATED: | I132: 44490 | J132: DATE COLLECTED: | K132: 44593
A134: County | B134: # Foster Homes
A135: AUTAUGA | B135: 15
A136: BALDWIN | B136: 56
A137: BARBOUR | B137: 17
A138: BIBB | B138: 21
A139: BLOUNT | B139: 23
A140: BULLOCK | B140: 5
A141: BUTLER | B141: 12
A142: CALHOUN | B142: 48
A143: CHAMBERS | B143: 42
A144: CHEROKEE | B144: 21
A145: CHILTON | B145: 64
A146: CLARKE | B146: 3
... A200: Statewide Total | B200: 1989
A204: NUMBER OF IN-HOME CASES | D204: SOURCE: | E204: Department of Human Resources | H204: DATE UPDATED: | I204: 44490 | J204: DATE COLLECTED: | K204: 44592
A206: County | B206: # In Home Cases
A207: AUTAUGA | B207: 24
A208: BALDWIN | B208: 127
A209: BARBOUR | B209: 25
A210: BIBB | B210: 61
A211: BLOUNT | B211: 104
A212: BULLOCK | B212: 4
A213: BUTLER | B213: 14
A214: CALHOUN | B214: 101
A215: CHAMBERS | B215: 33
A216: CHEROKEE | B216: 12
A217: CHILTON | B217: 14
A218: CHOCTAW | B218: 14
... A274: Statewide Total | B274: 4558

Sheet Alaska
B1: Alaska
A2: County | B2: County Population | C2: Number of Children in Care | D2: Average Beds per Family | E2: Number of Children in Foster Care | F2: Number of Children in Kinship Care | G2: Number of Children Placed Out-of-County | H2: Number of Foster and Kinship Homes | I2: Number of Children Waiting for Adoption | J2: Number of Children with 80+ Connections Made | K2: Biological Family Reunification Rate | L2: Number of Family Preservation Cases | M2: Number of Adoptive Families | N2: Number of Biological Families | O2: Number of Wraparound Supporters | P2: Number of Churches | Q2: Foster Family Retention Rate
A3: Anchorage | C3: ='AK Data'!B4 -> 858 | D3: NULL | E3: ='AK Data'!B5 -> 431 | F3: ='AK Data'!B6 -> 418 | G3: NULL | H3: NULL | I3: ='AK Data'!B10 -> 280 | J3: NULL | K3: ='AK Data'!B12 -> 0.524 | L3: NULL | M3: NULL | N3: ='AK Data'!B12 -> 0.524 | O3: NULL | P3: =ifna(vlookup(A3,'Population & Church Numbers'!$A$70:$D$98,4,FALSE),"NULL") -> 210 | Q3: NULL
A4: Northern | C4: ='AK Data'!D4 -> 440 | D4: NULL | E4: ='AK Data'!D5 -> 242 | F4: ='AK Data'!D6 -> 193 | G4: NULL | H4: NULL | I4: ='AK Data'!D10 -> 174 | J4: NULL | K4: ='AK Data'!D12 -> 0.534 | L4: NULL | M4: NULL | N4: ='AK Data'!D12 -> 0.534 | O4: NULL | P4: =ifna(vlookup(A4,'Population & Church Numbers'!$A$70:$D$98,4,FALSE),"NULL") -> NULL | Q4: NULL
A5: Southcentral | C5: ='AK Data'!C4 -> 562 | D5: NULL | E5: ='AK Data'!C5 -> 261 | F5: ='AK Data'!C6 -> 290 | G5: NULL | H5: NULL | I5: ='AK Data'!C10 -> 277 | J5: NULL | K5: NULL | L5: NULL | M5: NULL | N5: ='AK Data'!C12 -> 0.498 | O5: NULL | P5: =ifna(vlookup(A5,'Population & Church Numbers'!$A$70:$D$98,4,FALSE),"NULL") -> NULL | Q5: NULL
A6: Southeast | C6: ='AK Data'!F4 -> 146 | D6: NULL | E6: ='AK Data'!F5 -> 76 | F6: ='AK Data'!F6 -> 68 | G6: NULL | H6: NULL | I6: ='AK Data'!F10 -> 42 | J6: NULL | K6: NULL | L6: NULL | M6: NULL | N6: ='AK Data'!F12 -> 0.397 | O6: NULL | P6: =ifna(vlookup(A6,'Population & Church Numbers'!$A$70:$D$98,4,FALSE),"NULL") -> NULL | Q6: NULL
A7: Western | C7: ='AK Data'!E4 -> 255 | D7: NULL | E7: ='AK Data'!E5 -> 102 | F7: ='AK Data'!E6 -> 148 | G7: NULL | H7: NULL | I7: ='AK Data'!E10 -> 80 | J7: NULL | K7: NULL | L7: NULL | M7: NULL | N7: ='AK Data'!E12 -> 0.486 | O7: NULL | P7: =ifna(vlookup(A7,'Population & Church Numbers'!$A$70:$D$98,4,FALSE),"NULL") -> NULL | Q7: NULL
A9: TOTAL | C9: ='AK Data'!G4 -> 2261 | D9: ='AK Data'!G8 -> 2.08 | E9: ='AK Data'!G5 -> 1112 | F9: ='AK Data'!G6 -> 1117 | G9: NULL | H9: ='AK Data'!B17 -> 1486 | I9: ='AK Data'!G10 -> 853 | J9: NULL | K9: ='AK Data'!G12 -> 0.4878 | L9: NULL | M9: NULL | N9: NULL | O9: NULL | P9: =sum(P3:P7) -> 210 | Q9: NULL

Sheet AK Data
A1: ¿¿¿
A2: SHARED DATA | E2: SOURCE: | I2: DATE UPDATED: | J2: 45462 | K2: DATE COLLECTED: | L2: 44986
B3: ARO | C3: SCRO | D3: NRO | E3: WRO | F3: SERO | G3: Total | H3: *there were 32 children at the time the data was pulled that were in a status (like runaway or placed in an adult assisted living facility, etc.) These children are not accounted for here.
A4: Number of Children in Care | B4: 858 | C4: 562 | D4: 440 | E4: 255 | F4: 146 | G4: =SUM(B4:F4) -> 2261
A5: Number of Children in Foster Care | B5: 431 | C5: 261 | D5: 242 | E5: 102 | F5: 76 | G5: =SUM(B5:F5) -> 1112
A6: Number of Children in Kinship Care | B6: 418 | C6: 290 | D6: 193 | E6: 148 | F6: 68 | G6: =SUM(B6:F6) -> 1117
A7: Number of Children Placed Out-of-County | B7: We don't have a reliable way of identifying children placed outside of their home region. This is something we are working on.
A8: Average Beds per Family | B8: 2.4 | C8: 2 | D8: 1.8 | E8: 2.1 | F8: 2.1 | G8: =AVERAGE(B8:F8) -> 2.08
A9: Number of Foster and Kinship Homes
A10: Number of Children Legally Free for Adoption | B10: 280 | C10: 277 | D10: 174 | E10: 80 | F10: 42 | G10: =SUM(B10:F10) -> 853
A11: Number of Family Preservation Cases | B11: We don't have a designation of "family preservation." We do in-home cases but we don't have a reliable way of identifying these due to a number of reasons stemming from how things are documented in our database. This number would be very small though.
A12: Biological Family Reunification Rate | B12: 0.524 | C12: 0.498 | D12: 0.534 | E12: 0.486 | F12: 0.397 | G12: =AVERAGE(B12:F12) -> 0.4878
A15: NUMBER OF LICENSED FOSTER HOMES | E15: SOURCE: | F15: Dept. of Heath and Social Services, Office of Children's Services | I15: DATE UPDATED: | J15: 45462 | K15: DATE COLLECTED: | L15: 45291
A17: Foster Home | B17: 1486
A18: ARO Foster Home
A19: NRO Foster Home
A20: SCRO Foster Home
A21: SERO Foster Home
A22: WRO Foster Home
A23: OOS Foster Home
A25: Anchorage | B25: Anchorage | C25: =B18 | D25: * | E25: =CONCAT(C25,D25) -> *
A26: Fairbanks North Star | B26: Northern | C26: =B19 | D26: * | E26: =CONCAT(C26,D26) -> *
A27: North Slope | B27: Northern | C27: =$C$26 | D27: * | E27: =CONCAT(C27,D27) -> *
A28: Northwest Arctic | B28: Northern | C28: =$C$26 | D28: * | E28: =CONCAT(C28,D28) -> *
A29: Nome | B29: Northern | C29: =$C$26 | D29: * | E29: =CONCAT(C29,D29) -> *
A30: Yukon-Koyukuk | B30: Northern | C30: =$C$26 | D30: * | E30: =CONCAT(C30,D30) -> *
A31: Southeast Fairbanks | B31: Northern | C31: =$C$26 | D31: * | E31: =CONCAT(C31,D31) -> *
A32: Denali | B32: Northern | C32: =$C$26 | D32: * | E32: =CONCAT(C32,D32) -> *
A33: Bethel | B33: Western | C33: =B22 | D33: * | E33: =CONCAT(C33,D33) -> *
A34: Kusilvak | B34: Western | C34: =C33 | D34: * | E34: =CONCAT(C34,D34) -> *
A35: Dillingham | B35: Southcentral | C35: =B20 | D35: * | E35: =CONCAT(C35,D35) -> *
A36: Kenai Peninsula | B36: Southcentral | C36: =$C$35 | D36: * | E36: =CONCAT(C36,D36) -> *
A37: Kodiak Island | B37: Southcentral | C37: =$C$35 | D37: * | E37: =CONCAT(C37,D37) -> *
A38: Chugach | B38: Southcentral | C38: =$C$35 | D38: * | E38: =CONCAT(C38,D38) -> *
A39: Copper River | B39: Southcentral | C39: =$C$35 | D39: * | E39: =CONCAT(C39,D39) -> *
A40: Aleutians East | B40: Southcentral | C40: =$C$35 | D40: * | E40: =CONCAT(C40,D40) -> *
A41: Aleutians West | B41: Southcentral | C41: =$C$35 | D41: * | E41: =CONCAT(C41,D41) -> *
A42: Lake And Peninsula | B42: Southcentral | C42: =$C$35 | D42: * | E42: =CONCAT(C42,D42) -> *
A43: Bristol Bay | B43: Southcentral | C43: =$C$35 | D43: * | E43: =CONCAT(C43,D43) -> *
A44: Matanuska-Susitna | B44: Southcentral | C44: =$C$35 | D44: * | E44: =CONCAT(C44,D44) -> *
A45: Juneau | B45: Southeast | C45: =B21 | D45: * | E45: =CONCAT(C45,D45) -> *
A46: Sitka | B46: Southeast | C46: =$C$45 | D46: * | E46: =CONCAT(C46,D46) -> *
A47: Ketchikan Gateway | B47: Southeast | C47: =$C$45 | D47: * | E47: =CONCAT(C47,D47) -> *
A48: Petersburg | B48: Southeast | C48: =$C$45 | D48: * | E48: =CONCAT(C48,D48) -> *
A49: Prince of Wales Hyder | B49: Southeast | C49: =$C$45 | D49: * | E49: =CONCAT(C49,D49) -> *
A50: Yakutat | B50: Southeast | C50: =$C$45 | D50: * | E50: =CONCAT(C50,D50) -> *
A51: Skagway | B51: Southeast | C51: =$C$45 | D51: * | E51: =CONCAT(C51,D51) -> *
A52: Wrangell | B52: Southeast | C52: =$C$45 | D52: * | E52: =CONCAT(C52,D52) -> *
A53: Hoonah-Angoon | B53: Southeast | C53: =$C$45 | D53: * | E53: =CONCAT(C53,D53) -> *
A54: Haines | B54: Southeast | C54: =$C$45 | D54: * | E54: =CONCAT(C54,D54) -> *
A55: Total | C55: =B17 -> 1486

Sheet Arizona
B1: Arizona
A2: County | B2: County Population | C2: Number of Children in Care | D2: Average Beds per Family | E2: Number of Children in Foster Care | F2: Number of Children in Kinship Care | G2: Number of Children Placed Out-of-County | H2: Number of Foster and Kinship Homes | I2: Number of Children Waiting for Adoption | J2: Number of Children with 80+ Connections Made | K2: Biological Family Reunification Rate | L2: Number of Family Preservation Cases | M2: Number of Adoptive Families | N2: Number of Biological Families | O2: Number of Wraparound Supporters | P2: Number of Churches | Q2: Foster Family Retention Rate
A3: Apache | B3: {=VLOOKUP($A3,AZ_DEMO,2,FALSE)} -> 66021 | C3: =VLOOKUP($A3,'AZ Data'!$A$24:$B$38,2,FALSE) -> 26 | D3: NULL | E3: NULL | F3: NULL | G3: NULL | H3: NULL | I3: NULL | J3: NULL | K3: NULL | L3: NULL | M3: NULL | N3: NULL | O3: NULL | P3: =ifna(vlookup(A3,'Population & Church Numbers'!$A$99:$D$113,4,FALSE),"NULL") -> 48 | Q3: NULL
A4: Cochise | B4: {=VLOOKUP($A4,AZ_DEMO,2,FALSE)} -> 125447 | C4: =VLOOKUP($A4,'AZ Data'!$A$24:$B$38,2,FALSE) -> 215 | D4: NULL | E4: NULL | F4: NULL | G4: NULL | H4: NULL | I4: NULL | J4: NULL | K4: NULL | L4: NULL | M4: NULL | N4: NULL | O4: NULL | P4: =ifna(vlookup(A4,'Population & Church Numbers'!$A$99:$D$113,4,FALSE),"NULL") -> 129 | Q4: NULL
A5: Coconino | B5: {=VLOOKUP($A5,AZ_DEMO,2,FALSE)} -> 145101 | C5: =VLOOKUP($A5,'AZ Data'!$A$24:$B$38,2,FALSE) -> 120 | D5: NULL | E5: NULL | F5: NULL | G5: NULL | H5: NULL | I5: NULL | J5: NULL | K5: NULL | L5: NULL | M5: NULL | N5: NULL | O5: NULL | P5: =ifna(vlookup(A5,'Population & Church Numbers'!$A$99:$D$113,4,FALSE),"NULL") -> 76 | Q5: NULL
A6: Gila | B6: {=VLOOKUP($A6,AZ_DEMO,2,FALSE)} -> 53272 | C6: =VLOOKUP($A6,'AZ Data'!$A$24:$B$38,2,FALSE) -> 99 | D6: NULL | E6: NULL | F6: NULL | G6: NULL | H6: NULL | I6: NULL | J6: NULL | K6: NULL | L6: NULL | M6: NULL | N6: NULL | O6: NULL | P6: =ifna(vlookup(A6,'Population & Church Numbers'!$A$99:$D$113,4,FALSE),"NULL") -> 62 | Q6: NULL
A7: Graham | B7: {=VLOOKUP($A7,AZ_DEMO,2,FALSE)} -> 38533 | C7: =VLOOKUP($A7,'AZ Data'!$A$24:$B$38,2,FALSE) -> 43 | D7: NULL | E7: NULL | F7: NULL | G7: NULL | H7: NULL | I7: NULL | J7: NULL | K7: NULL | L7: NULL | M7: NULL | N7: NULL | O7: NULL | P7: =ifna(vlookup(A7,'Population & Church Numbers'!$A$99:$D$113,4,FALSE),"NULL") -> 24 | Q7: NULL
A8: Greenlee | B8: {=VLOOKUP($A8,AZ_DEMO,2,FALSE)} -> 9563 | C8: =VLOOKUP($A8,'AZ Data'!$A$24:$B$38,2,FALSE) -> 7 | D8: NULL | E8: NULL | F8: NULL | G8: NULL | H8: NULL | I8: NULL | J8: NULL | K8: NULL | L8: NULL | M8: NULL | N8: NULL | O8: NULL | P8: =ifna(vlookup(A8,'Population & Church Numbers'!$A$99:$D$113,4,FALSE),"NULL") -> 7 | Q8: NULL
A9: La Paz | B9: {=VLOOKUP($A9,AZ_DEMO,2,FALSE)} -> 16557 | C9: =VLOOKUP($A9,'AZ Data'!$A$24:$B$38,2,FALSE) -> 18 | D9: NULL | E9: NULL | F9: NULL | G9: NULL | H9: NULL | I9: NULL | J9: NULL | K9: NULL | L9: NULL | M9: NULL | N9: NULL | O9: NULL | P9: =ifna(vlookup(A9,'Population & Church Numbers'!$A$99:$D$113,4,FALSE),"NULL") -> 25 | Q9: NULL
A10: Maricopa | B10: {=VLOOKUP($A10,AZ_DEMO,2,FALSE)} -> 4420568 | C10: =VLOOKUP($A10,'AZ Data'!$A$24:$B$38,2,FALSE) -> 5184 | D10: NULL | E10: NULL | F10: NULL | G10: NULL | H10: NULL | I10: NULL | J10: NULL | K10: NULL | L10: NULL | M10: NULL | N10: NULL | O10: NULL | P10: =ifna(vlookup(A10,'Population & Church Numbers'!$A$99:$D$113,4,FALSE),"NULL") -> 1166 | Q10: NULL
A11: Mohave | B11: {=VLOOKUP($A11,AZ_DEMO,2,FALSE)} -> 213267 | C11: =VLOOKUP($A11,'AZ Data'!$A$24:$B$38,2,FALSE) -> 305 | D11: NULL | E11: NULL | F11: NULL | G11: NULL | H11: NULL | I11: NULL | J11: NULL | K11: NULL | L11: NULL | M11: NULL | N11: NULL | O11: NULL | P11: =ifna(vlookup(A11,'Population & Church Numbers'!$A$99:$D$113,4,FALSE),"NULL") -> 104 | Q11: NULL
A12: Navajo | B12: {=VLOOKUP($A12,AZ_DEMO,2,FALSE)} -> 106717 | C12: =VLOOKUP($A12,'AZ Data'!$A$24:$B$38,2,FALSE) -> 101 | D12: NULL | E12: NULL | F12: NULL | G12: NULL | H12: NULL | I12: NULL | J12: NULL | K12: NULL | L12: NULL | M12: NULL | N12: NULL | O12: NULL | P12: =ifna(vlookup(A12,'Population & Church Numbers'!$A$99:$D$113,4,FALSE),"NULL") -> 81 | Q12: NULL
A13: Pima | B13: {=VLOOKUP($A13,AZ_DEMO,2,FALSE)} -> 1043433 | C13: =VLOOKUP($A13,'AZ Data'!$A$24:$B$38,2,FALSE) -> 1744 | D13: NULL | E13: NULL | F13: NULL | G13: NULL | H13: NULL | I13: NULL | J13: NULL | K13: NULL | L13: NULL | M13: NULL | N13: NULL | O13: NULL | P13: =ifna(vlookup(A13,'Population & Church Numbers'!$A$99:$D$113,4,FALSE),"NULL") -> 404 | Q13: NULL
A14: Pinal | B14: {=VLOOKUP($A14,AZ_DEMO,2,FALSE)} -> 425264 | C14: =VLOOKUP($A14,'AZ Data'!$A$24:$B$38,2,FALSE) -> 501 | D14: NULL | E14: NULL | F14: NULL | G14: NULL | H14: NULL | I14: NULL | J14: NULL | K14: NULL | L14: NULL | M14: NULL | N14: NULL | O14: NULL | P14: =ifna(vlookup(A14,'Population & Church Numbers'!$A$99:$D$113,4,FALSE),"NULL") -> 131 | Q14: NULL
... A17: Yuma | B17: {=VLOOKUP($A17,AZ_DEMO,2,FALSE)} -> 203881 | C17: =VLOOKUP($A17,'AZ Data'!$A$24:$B$38,2,FALSE) -> 169 | D17: NULL | E17: NULL | F17: NULL | G17: NULL | H17: NULL | I17: NULL | J17: NULL | K17: NULL | L17: NULL | M17: NULL | N17: NULL | O17: NULL | P17: =ifna(vlookup(A17,'Population & Church Numbers'!$A$99:$D$113,4,FALSE),"NULL") -> 70 | Q17: NULL
A19: TOTAL | C19: ='AZ Data'!B5 -> 8839 | D19: NULL | E19: NULL | F19: NULL | G19: NULL | H19: ='AZ Data'!C62 -> 2170 | I19: ='AZ Data'!E67 -> 1606 | J19: NULL | K19: NULL | L19: NULL | M19: NULL | N19: NULL | O19: NULL | P19: =SUM(P3:P17) -> 2507 | Q19: NULL

Sheet AZ Data
A1: NUMBER OF CHILDREN IN CARE | E1: SOURCE: | F1: Arizona Dept. of Child Safety | I1: DATE UPDATED: | J1: 45442 | K1: DATE COLLECTED: | L1: 45382
A4: Out-Of-Home Population (by Child) | B4: 0-17 Years Old | D4: 18+ Years Old | J4: 0-17 | K4: 18+
A5: Total in Out-of-Home Care | B5: 8839 | D5: 937 | I5: Unlicensed (Primarily Kinship) | J5: 4252 | K5: 58 | M5: Kinship Care
A6: AGE RANGE | I6: Family Foster Home | J6: 2611 | K6: 36 | M6: Foster Care
A7: 0-12 months | B7: 856 | I7: Family Foster Home | J7: 1383 | K7: 11
A8: 1 years | B8: 795 | I8: Family Foster Home - DDD | J8: 378 | K8: 1
A9: 2-3 years | B9: 1040 | I9: Family Foster Home - Out of State | J9: 89 | K9: 0
A10: 4-5 years | B10: 890 | I10: Family Foster Home - Medically Fragile | J10: 26 | K10: 11
A11: 6-8 years | B11: 1241 | I11: Family Foster Home - Specialized | J11: 645 | K11: 12
A12: 9-12 years | B12: 1454 | I12: Family Foster Home - Therapeutic Foster Care | J12: 90 | K12: 1
A13: 13-17 years | B13: 2563 | I13: Family Foster Home & Unlicensed (Non-Kinship) 4 | J13: 691 | K13: 5
A14: Unavailable | B14: 0 | I14: Family Foster Home & Unlicensed (Kinship) 4 | J14: 2173 | K14: 14
A15: ETHNICITY | I15: Congregate Care - Shelter Care | J15: 16 | K15: 0
A16: African-American | B16: 1659 | D16: 199 | I16: Congregate Care - Group Home | J16: 969 | K16: 168
A17: American Indian | B17: 993 | D17: 61 | I17: Standard GH | J17: 677 | K17: 140
A18: Asian | B18: 105 | D18: 17 | I18: Medical GH | J18: 1 | K18: 11
A19: Hispanic | B19: 2968 | D19: 339 | I19: Mother/Infant/House/Teen Parent GH | J19: 194 | K19: 10
A20: Other / Unknown | B20: 75 | D20: 1 | I20: DDD GH | J20: 97 | K20: 7
A21: Caucasian | B21: 3039 | D21: 320 | I21: Congregate Care - QRTP Group Home | J21: 329 | K21: 4
F22: SUM 0-18+ YEARS OLD | I22: Sexually Maladaptive GH | J22: 90 | K22: 1
A23: COUNTY OF ENTRY | I23: Significant Trauma GH | J23: 30 | K23: 2
A24: Apache | B24: 26 | D24: 4 | F24: =B24+D24 -> 30 | I24: Structured GH | J24: 209 | K24: 1
A25: Cochise | B25: 215 | D25: 12 | F25: =B25+D25 -> 227 | I25: Congregate Care - Residential Treatment | J25: 231
A26: Coconino | B26: 120 | D26: 15 | F26: =B26+D26 -> 135 | I26: BHRF | J26: 65 | K26: 0
A27: Gila | B27: 99 | D27: 5 | F27: =B27+D27 -> 104 | I27: BHIF | J27: 83 | K27: 0
A28: Graham | B28: 43 | D28: 2 | F28: =B28+D28 -> 45 | I28: Welcome Centers | J28: 30 | K28: 2
A29: Greenlee | B29: 7 | D29: 1 | F29: =B29+D29 -> 8 | I29: Detention | J29: 53 | K29: 1
A30: La Paz | B30: 18 | D30: 3 | F30: =B30+D30 -> 21 | I30: Hospital & Other | J30: 0 | K30: 0
A31: Maricopa | B31: 5184 | D31: 582 | F31: =B31+D31 -> 5766 | I31: Independent Living | J31: 1 | K31: 605
A32: Mohave | B32: 305 | D32: 25 | F32: =B32+D32 -> 330 | I32: Runaway | J32: 110 | K32: 1
A33: Navajo | B33: 101 | D33: 10 | F33: =B33+D33 -> 111 | I33: Missing/Abducted | J33: 17 | K33: 0
A34: Pima | B34: 1744 | D34: 155 | F34: =B34+D34 -> 1899 | I34: Service Authorization Pending | J34: 303 | K34: 84
A35: Pinal | B35: 501 | D35: 61 | F35: =B35+D35 -> 562 | I35: Other Facility / Parent Guardian (Trial Home Visit) | J35: 0 | K35: 0
A36: Santa Cruz | B36: 73 | D36: 4 | F36: =B36+D36 -> 77
A37: Yavapai | B37: 231 | D37: 34 | F37: =B37+D37 -> 265
A38: Yuma | B38: 169 | D38: 20 | F38: =B38+D38 -> 189
B39: 3 | D39: 4
A60: NUMBER OF LICENSED FOSTER HOMES | E60: SOURCE: | F60: Arizona Dept. of Child Safety | I60: DATE UPDATED: | J60: 45442 | K60: DATE COLLECTED: | L60: 45381
A62: # of Licensed Foster Homes | C62: 2170
A65: NUMBER OF CHILDREN WAITING FOR ADOPTION | E65: SOURCE: | F65: Arizona Dept. of Child Safety | I65: DATE UPDATED: | J65: 45442 | K65: DATE COLLECTED: | L65: 45381
A67: # of Children Legally Free with a case plan goal of Adoption | E67: 1606

Sheet Arkansas
B1: Arkansas
A2: County | B2: County Population | C2: Number of Children in Care | D2: Average Beds per Family | E2: Number of Children in Foster Care | F2: Number of Children in Kinship Care | G2: Number of Children Placed Out-of-County | H2: Number of Foster and Kinship Homes | I2: Number of Children Waiting for Adoption | J2: Number of Children with 80+ Connections Made | K2: Biological Family Reunification Rate | L2: Number of Family Preservation Cases | M2: Number of Adoptive Families | N2: Number of Biological Families | O2: Number of Wraparound Supporters | P2: Number of Churches | Q2: Foster Family Retention Rate
A3: Arkansas | B3: {=VLOOKUP($A3,AR_DEMO,2,FALSE)} -> 17149 | C3: =vlookup(A3,'AR Data'!$A$3:$N$84,2, FALSE) -> 15 | D3: =(vlookup(A3,'AR Data'!$A$3:$N$84,6,FALSE))/(vlookup(A3,'AR Data'!$A$3:$N$84,5,FALSE)) -> 1.8 | E3: NULL | F3: =vlookup(A3,'AR Data'!$A$3:$N$84,10,FALSE) -> 6 | G3: NULL | H3: =vlookup(A3,'AR Data'!$A$3:$N$84,5,FALSE)+vlookup(A3,'AR Data'!$A$3:$N$84,7, FALSE) -> 5 | I3: =vlookup(A3,'AR Data'!$A$3:$N$84,3, FALSE) -> 3 | J3: NULL | K3: NULL | L3: =vlookup(A3,'AR Data'!$A$3:$N$84,4, FALSE) -> 9 | M3: NULL | N3: NULL | O3: NULL | P3: =ifna(vlookup(A3,'Population & Church Numbers'!$A$114:$D$188,4,FALSE),"NULL") -> 33 | Q3: NULL
A4: Ashley | B4: {=VLOOKUP($A4,AR_DEMO,2,FALSE)} -> 19062 | C4: =vlookup(A4,'AR Data'!$A$3:$N$84,2, FALSE) -> 10 | D4: =(vlookup(A4,'AR Data'!$A$3:$N$84,6,FALSE))/(vlookup(A4,'AR Data'!$A$3:$N$84,5,FALSE)) -> 1.7777778 | E4: NULL | F4: =vlookup(A4,'AR Data'!$A$3:$N$84,10,FALSE) -> 7 | G4: NULL | H4: =vlookup(A4,'AR Data'!$A$3:$N$84,5,FALSE)+vlookup(A4,'AR Data'!$A$3:$N$84,7, FALSE) -> 15 | I4: =vlookup(A4,'AR Data'!$A$3:$N$84,3, FALSE) -> 0 | J4: NULL | K4: NULL | L4: =vlookup(A4,'AR Data'!$A$3:$N$84,4, FALSE) -> 4 | M4: NULL | N4: NULL | O4: NULL | P4: =ifna(vlookup(A4,'Population & Church Numbers'!$A$114:$D$188,4,FALSE),"NULL") -> 52 | Q4: NULL
A5: Baxter | B5: {=VLOOKUP($A5,AR_DEMO,2,FALSE)} -> 41627 | C5: =vlookup(A5,'AR Data'!$A$3:$N$84,2, FALSE) -> 29 | D5: =(vlookup(A5,'AR Data'!$A$3:$N$84,6,FALSE))/(vlookup(A5,'AR Data'!$A$3:$N$84,5,FALSE)) -> 1.6190476 | E5: NULL | F5: =vlookup(A5,'AR Data'!$A$3:$N$84,10,FALSE) -> 5 | G5: NULL | H5: =vlookup(A5,'AR Data'!$A$3:$N$84,5,FALSE)+vlookup(A5,'AR Data'!$A$3:$N$84,7, FALSE) -> 27 | I5: =vlookup(A5,'AR Data'!$A$3:$N$84,3, FALSE) -> 4 | J5: NULL | K5: NULL | L5: =vlookup(A5,'AR Data'!$A$3:$N$84,4, FALSE) -> 13 | M5: NULL | N5: NULL | O5: NULL | P5: =ifna(vlookup(A5,'Population & Church Numbers'!$A$114:$D$188,4,FALSE),"NULL") -> 52 | Q5: NULL
A6: Benton | B6: {=VLOOKUP($A6,AR_DEMO,2,FALSE)} -> 284333 | C6: =vlookup(A6,'AR Data'!$A$3:$N$84,2, FALSE) -> 129 | D6: =(vlookup(A6,'AR Data'!$A$3:$N$84,6,FALSE))/(vlookup(A6,'AR Data'!$A$3:$N$84,5,FALSE)) -> 1.9659091 | E6: NULL | F6: =vlookup(A6,'AR Data'!$A$3:$N$84,10,FALSE) -> 33 | G6: NULL | H6: =vlookup(A6,'AR Data'!$A$3:$N$84,5,FALSE)+vlookup(A6,'AR Data'!$A$3:$N$84,7, FALSE) -> 113 | I6: =vlookup(A6,'AR Data'!$A$3:$N$84,3, FALSE) -> 7 | J6: NULL | K6: NULL | L6: =vlookup(A6,'AR Data'!$A$3:$N$84,4, FALSE) -> 65 | M6: NULL | N6: NULL | O6: NULL | P6: =ifna(vlookup(A6,'Population & Church Numbers'!$A$114:$D$188,4,FALSE),"NULL") -> 197 | Q6: NULL
A7: Boone | B7: {=VLOOKUP($A7,AR_DEMO,2,FALSE)} -> 37373 | C7: =vlookup(A7,'AR Data'!$A$3:$N$84,2, FALSE) -> 40 | D7: =(vlookup(A7,'AR Data'!$A$3:$N$84,6,FALSE))/(vlookup(A7,'AR Data'!$A$3:$N$84,5,FALSE)) -> 2.2380952 | E7: NULL | F7: =vlookup(A7,'AR Data'!$A$3:$N$84,10,FALSE) -> 18 | G7: NULL | H7: =vlookup(A7,'AR Data'!$A$3:$N$84,5,FALSE)+vlookup(A7,'AR Data'!$A$3:$N$84,7, FALSE) -> 27 | I7: =vlookup(A7,'AR Data'!$A$3:$N$84,3, FALSE) -> 5 | J7: NULL | K7: NULL | L7: =vlookup(A7,'AR Data'!$A$3:$N$84,4, FALSE) -> 30 | M7: NULL | N7: NULL | O7: NULL | P7: =ifna(vlookup(A7,'Population & Church Numbers'!$A$114:$D$188,4,FALSE),"NULL") -> 67 | Q7: NULL
A8: Bradley | B8: {=VLOOKUP($A8,AR_DEMO,2,FALSE)} -> 10545 | C8: =vlookup(A8,'AR Data'!$A$3:$N$84,2, FALSE) -> 7 | D8: =(vlookup(A8,'AR Data'!$A$3:$N$84,6,FALSE))/(vlookup(A8,'AR Data'!$A$3:$N$84,5,FALSE)) -> 2.25 | E8: NULL | F8: =vlookup(A8,'AR Data'!$A$3:$N$84,10,FALSE) -> 5 | G8: NULL | H8: =vlookup(A8,'AR Data'!$A$3:$N$84,5,FALSE)+vlookup(A8,'AR Data'!$A$3:$N$84,7, FALSE) -> 7 | I8: =vlookup(A8,'AR Data'!$A$3:$N$84,3, FALSE) -> 0 | J8: NULL | K8: NULL | L8: =vlookup(A8,'AR Data'!$A$3:$N$84,4, FALSE) -> 5 | M8: NULL | N8: NULL | O8: NULL | P8: =ifna(vlookup(A8,'Population & Church Numbers'!$A$114:$D$188,4,FALSE),"NULL") -> 18 | Q8: NULL
A9: Calhoun | B9: {=VLOOKUP($A9,AR_DEMO,2,FALSE)} -> 4739 | C9: =vlookup(A9,'AR Data'!$A$3:$N$84,2, FALSE) -> 1 | D9: =(vlookup(A9,'AR Data'!$A$3:$N$84,6,FALSE))/(vlookup(A9,'AR Data'!$A$3:$N$84,5,FALSE)) -> 1.3333333 | E9: NULL | F9: =vlookup(A9,'AR Data'!$A$3:$N$84,10,FALSE) -> 1 | G9: NULL | H9: =vlookup(A9,'AR Data'!$A$3:$N$84,5,FALSE)+vlookup(A9,'AR Data'!$A$3:$N$84,7, FALSE) -> 5 | I9: =vlookup(A9,'AR Data'!$A$3:$N$84,3, FALSE) -> 0 | J9: NULL | K9: NULL | L9: =vlookup(A9,'AR Data'!$A$3:$N$84,4, FALSE) -> 1 | M9: NULL | N9: NULL | O9: NULL | P9: =ifna(vlookup(A9,'Population & Church Numbers'!$A$114:$D$188,4,FALSE),"NULL") -> 16 | Q9: NULL
A10: Carroll | B10: {=VLOOKUP($A10,AR_DEMO,2,FALSE)} -> 28260 | C10: =vlookup(A10,'AR Data'!$A$3:$N$84,2, FALSE) -> 30 | D10: =(vlookup(A10,'AR Data'!$A$3:$N$84,6,FALSE))/(vlookup(A10,'AR Data'!$A$3:$N$84,5,FALSE)) -> 2 | E10: NULL | F10: =vlookup(A10,'AR Data'!$A$3:$N$84,10,FALSE) -> 10 | G10: NULL | H10: =vlookup(A10,'AR Data'!$A$3:$N$84,5,FALSE)+vlookup(A10,'AR Data'!$A$3:$N$84,7, FALSE) -> 9 | I10: =vlookup(A10,'AR Data'!$A$3:$N$84,3, FALSE) -> 1 | J10: NULL | K10: NULL | L10: =vlookup(A10,'AR Data'!$A$3:$N$84,4, FALSE) -> 16 | M10: NULL | N10: NULL | O10: NULL | P10: =ifna(vlookup(A10,'Population & Church Numbers'!$A$114:$D$188,4,FALSE),"NULL") -> 35 | Q10: NULL
A11: Chicot | B11: {=VLOOKUP($A11,AR_DEMO,2,FALSE)} -> 10208 | C11: =vlookup(A11,'AR Data'!$A$3:$N$84,2, FALSE) -> 7 | D11: =(vlookup(A11,'AR Data'!$A$3:$N$84,6,FALSE))/(vlookup(A11,'AR Data'!$A$3:$N$84,5,FALSE)) -> 2 | E11: NULL | F11: =vlookup(A11,'AR Data'!$A$3:$N$84,10,FALSE) -> 2 | G11: NULL | H11: =vlookup(A11,'AR Data'!$A$3:$N$84,5,FALSE)+vlookup(A11,'AR Data'!$A$3:$N$84,7, FALSE) -> 5 | I11: =vlookup(A11,'AR Data'!$A$3:$N$84,3, FALSE) -> 0 | J11: NULL | K11: NULL | L11: =vlookup(A11,'AR Data'!$A$3:$N$84,4, FALSE) -> 5 | M11: NULL | N11: NULL | O11: NULL | P11: =ifna(vlookup(A11,'Population & Church Numbers'!$A$114:$D$188,4,FALSE),"NULL") -> 24 | Q11: NULL
A12: Clark | B12: {=VLOOKUP($A12,AR_DEMO,2,FALSE)} -> 21446 | C12: =vlookup(A12,'AR Data'!$A$3:$N$84,2, FALSE) -> 12 | D12: =(vlookup(A12,'AR Data'!$A$3:$N$84,6,FALSE))/(vlookup(A12,'AR Data'!$A$3:$N$84,5,FALSE)) -> 1.9411765 | E12: NULL | F12: =vlookup(A12,'AR Data'!$A$3:$N$84,10,FALSE) -> 4 | G12: NULL | H12: =vlookup(A12,'AR Data'!$A$3:$N$84,5,FALSE)+vlookup(A12,'AR Data'!$A$3:$N$84,7, FALSE) -> 19 | I12: =vlookup(A12,'AR Data'!$A$3:$N$84,3, FALSE) -> 1 | J12: NULL | K12: NULL | L12: =vlookup(A12,'AR Data'!$A$3:$N$84,4, FALSE) -> 9 | M12: NULL | N12: NULL | O12: NULL | P12: =ifna(vlookup(A12,'Population & Church Numbers'!$A$114:$D$188,4,FALSE),"NULL") -> 48 | Q12: NULL
A13: Clay | B13: {=VLOOKUP($A13,AR_DEMO,2,FALSE)} -> 14552 | C13: =vlookup(A13,'AR Data'!$A$3:$N$84,2, FALSE) -> 14 | D13: =(vlookup(A13,'AR Data'!$A$3:$N$84,6,FALSE))/(vlookup(A13,'AR Data'!$A$3:$N$84,5,FALSE)) -> 2.25 | E13: NULL | F13: =vlookup(A13,'AR Data'!$A$3:$N$84,10,FALSE) -> 5 | G13: NULL | H13: =vlookup(A13,'AR Data'!$A$3:$N$84,5,FALSE)+vlookup(A13,'AR Data'!$A$3:$N$84,7, FALSE) -> 10 | I13: =vlookup(A13,'AR Data'!$A$3:$N$84,3, FALSE) -> 3 | J13: NULL | K13: NULL | L13: =vlookup(A13,'AR Data'!$A$3:$N$84,4, FALSE) -> 12 | M13: NULL | N13: NULL | O13: NULL | P13: =ifna(vlookup(A13,'Population & Church Numbers'!$A$114:$D$188,4,FALSE),"NULL") -> 21 | Q13: NULL
A14: Cleburne | B14: {=VLOOKUP($A14,AR_DEMO,2,FALSE)} -> 24711 | C14: =vlookup(A14,'AR Data'!$A$3:$N$84,2, FALSE) -> 38 | D14: =(vlookup(A14,'AR Data'!$A$3:$N$84,6,FALSE))/(vlookup(A14,'AR Data'!$A$3:$N$84,5,FALSE)) -> 1.9166667 | E14: NULL | F14: =vlookup(A14,'AR Data'!$A$3:$N$84,10,FALSE) -> 14 | G14: NULL | H14: =vlookup(A14,'AR Data'!$A$3:$N$84,5,FALSE)+vlookup(A14,'AR Data'!$A$3:$N$84,7, FALSE) -> 15 | I14: =vlookup(A14,'AR Data'!$A$3:$N$84,3, FALSE) -> 1 | J14: NULL | K14: NULL | L14: =vlookup(A14,'AR Data'!$A$3:$N$84,4, FALSE) -> 16 | M14: NULL | N14: NULL | O14: NULL | P14: =ifna(vlookup(A14,'Population & Church Numbers'!$A$114:$D$188,4,FALSE),"NULL") -> 47 | Q14: NULL
... A77: Yell | B77: {=VLOOKUP($A77,AR_DEMO,2,FALSE)} -> 20263 | C77: =vlookup(A77,'AR Data'!$A$3:$N$84,2, FALSE) -> 28 | D77: =(vlookup(A77,'AR Data'!$A$3:$N$84,6,FALSE))/(vlookup(A77,'AR Data'!$A$3:$N$84,5,FALSE)) -> 1.4545455 | E77: NULL | F77: =vlookup(A77,'AR Data'!$A$3:$N$84,10,FALSE) -> 13 | G77: NULL | H77: =vlookup(A77,'AR Data'!$A$3:$N$84,5,FALSE)+vlookup(A77,'AR Data'!$A$3:$N$84,7, FALSE) -> 19 | I77: =vlookup(A77,'AR Data'!$A$3:$N$84,3, FALSE) -> 2 | J77: NULL | K77: NULL | L77: =vlookup(A77,'AR Data'!$A$3:$N$84,4, FALSE) -> 19 | M77: NULL | N77: NULL | O77: NULL | P77: =ifna(vlookup(A77,'Population & Church Numbers'!$A$114:$D$188,4,FALSE),"NULL") -> 32 | Q77: NULL
A79: TOTAL | C79: ='AR Data'!B82 -> 3604 | D79: ='AR Data'!F82/'AR Data'!E82 -> 1.9804631 | E79: NULL | F79: NULL | G79: NULL | H79: ='AR Data'!E82+'AR Data'!G82 -> 1835 | I79: ='AR Data'!C82 -> 299 | J79: NULL | K79: NULL | L79: ='AR Data'!D82 -> 1436 | M79: NULL | N79: NULL | O79: NULL | P79: =SUM(P3:P77) -> 3846 | Q79: NULL

Sheet AR Data
A1: ALL DATAPOINTS | C1: SOURCE: | D1: Arkansas Dept. of Human Services | G1: DATE UPDATED: | H1: 45470 | I1: DATE COLLECTED: | J1: 45412
A3: County | B3: Number of Children in Foster Care | C3: Number of Children Available for Adoption | D3: Number of In-Home Protective Services Cases | E3: Number of Foster Family Homes | F3: Total Foster Family Home Beds | G3: Relative/ Fictive Kin Foster Family Homes | H3: Relative/ Fictive Kin Foster Home Beds | I3: Number of Applicable Children (Placed with Relatives) | J3: Number of Children Placed with Relatives | K3: Percentage (%) of Applicable Children Placed with Relatives | L3: Number of Applicable Children (Home County) | M3: Number of Children Placed in Home County | N3: Percentage (%) of Applicable Children Placed in Home County | P3: "ideal placement" | R3: out of county
A4: Benton | B4: 129 | C4: 7 | D4: 65 | E4: 88 | F4: 173 | G4: 25 | H4: 37 | I4: 125 | J4: 33 | K4: 26.4 | L4: 92 | M4: 38 | N4: 41.3 | P4: =M4+J4 -> 71 | R4: =B4-(J4+M4) -> 58
A5: Carroll | B5: 30 | C5: 1 | D5: 16 | E5: 7 | F5: 14 | G5: 2 | H5: 4 | I5: 27 | J5: 10 | K5: 37 | L5: 17 | M5: 0 | N5: 0 | P5: =M5+J5 -> 10 | R5: =B5-(J5+M5) -> 20
A6: Madison | B6: 33 | C6: 1 | D6: 1 | E6: 9 | F6: 15 | G6: 5 | H6: 7 | I6: 30 | J6: 19 | K6: 63.3 | L6: 11 | M6: 1 | N6: 9.1 | P6: =M6+J6 -> 20 | R6: =B6-(J6+M6) -> 13
A7: Washington | B7: 253 | C7: 36 | D7: 64 | E7: 88 | F7: 173 | G7: 30 | H7: 49 | I7: 234 | J7: 88 | K7: 37.6 | L7: 146 | M7: 35 | N7: 24 | P7: =M7+J7 -> 123 | R7: =B7-(J7+M7) -> 130
A8: Crawford | B8: 66 | C8: 0 | D8: 53 | E8: 43 | F8: 78 | G8: 20 | H8: 31 | I8: 61 | J8: 23 | K8: 37.7 | L8: 38 | M8: 9 | N8: 23.7 | P8: =M8+J8 -> 32 | R8: =B8-(J8+M8) -> 34
A9: Franklin | B9: 42 | C9: 3 | D9: 9 | E9: 7 | F9: 12 | G9: 5 | H9: 8 | I9: 36 | J9: 19 | K9: 52.8 | L9: 17 | M9: 2 | N9: 11.8 | P9: =M9+J9 -> 21 | R9: =B9-(J9+M9) -> 21
A10: Johnson | B10: 32 | C10: 1 | D10: 17 | E10: 11 | F10: 18 | G10: 6 | H10: 8 | I10: 29 | J10: 22 | K10: 75.9 | L10: 7 | M10: 1 | N10: 14.3 | P10: =M10+J10 -> 23 | R10: =B10-(J10+M10) -> 9
A11: Logan | B11: 60 | C11: 11 | D11: 33 | E11: 10 | F11: 21 | G11: 5 | H11: 11 | I11: 51 | J11: 21 | K11: 41.2 | L11: 30 | M11: 2 | N11: 6.7 | P11: =M11+J11 -> 23 | R11: =B11-(J11+M11) -> 37
A12: Scott | B12: 21 | C12: 4 | D12: 3 | E12: 6 | F12: 15 | G12: 2 | H12: 5 | I12: 21 | J12: 6 | K12: 28.6 | L12: 15 | M12: 1 | N12: 6.7 | P12: =M12+J12 -> 7 | R12: =B12-(J12+M12) -> 14
A13: Sebastian | B13: 387 | C13: 36 | D13: 75 | E13: 86 | F13: 162 | G13: 51 | H13: 74 | I13: 354 | J13: 127 | K13: 35.9 | L13: 227 | M13: 75 | N13: 33 | P13: =M13+J13 -> 202 | R13: =B13-(J13+M13) -> 185
A14: Yell | B14: 28 | C14: 2 | D14: 19 | E14: 11 | F14: 16 | G14: 8 | H14: 10 | I14: 21 | J14: 13 | K14: 61.9 | L14: 8 | M14: 1 | N14: 12.5 | P14: =M14+J14 -> 14 | R14: =B14-(J14+M14) -> 14
A15: Clark | B15: 12 | C15: 1 | D15: 9 | E15: 17 | F15: 33 | G15: 2 | H15: 5 | I15: 11 | J15: 4 | K15: 36.4 | L15: 7 | M15: 2 | N15: 28.6 | P15: =M15+J15 -> 6 | R15: =B15-(J15+M15) -> 6
... A46: Bradley | B46: 7 | C46: 0 | D46: 5 | E46: 4 | F46: 9 | G46: 3 | H46: 6 | I46: 7 | J46: 5 | K46: 71.4 | L46: 2 | M46: 0 | N46: 0 | P46: =M46+J46 -> 5 | R46: =B46-(J46+M46) -> 2
A47: Calhoun | B47: 1 | C47: 0 | D47: 1 | E47: 3 | F47: 4 | G47: 2 | H47: 2 | I47: 1 | J47: 1 | K47: 100 | L47: 0 | M47: 0 | P47: =M47+J47 -> 1 | R47: =B47-(J47+M47) -> 0
A48: Cleveland | B48: 2 | C48: 0 | D48: 2 | E48: 3 | F48: 8 | G48: 0 | H48: 0 | I48: 2 | J48: 2 | K48: 100 | L48: 0 | M48: 0 | P48: =M48+J48 -> 2 | R48: =B48-(J48+M48) -> 0
A49: Dallas | B49: 15 | C49: 4 | D49: 2 | E49: 1 | F49: 2 | G49: 0 | H49: 0 | I49: 15 | J49: 3 | K49: 20 | L49: 12 | M49: 1 | N49: 8.3 | P49: =M49+J49 -> 4 | R49: =B49-(J49+M49) -> 11
A50: Grant | B50: 27 | C50: 0 | D50: 9 | E50: 12 | F50: 30 | G50: 3 | H50: 7 | I50: 25 | J50: 13 | K50: 52 | L50: 12 | M50: 5 | N50: 41.7 | P50: =M50+J50 -> 18 | R50: =B50-(J50+M50) -> 9
A51: Jefferson | B51: 83 | C51: 2 | D51: 52 | E51: 28 | F51: 71 | G51: 7 | H51: 11 | I51: 76 | J51: 30 | K51: 39.5 | L51: 46 | M51: 16 | N51: 34.8 | P51: =M51+J51 -> 46 | R51: =B51-(J51+M51) -> 37
A52: Lincoln | B52: 13 | C52: 0 | D52: 7 | E52: 5 | F52: 13 | G52: 2 | H52: 6 | I52: 12 | J52: 9 | K52: 75 | L52: 3 | M52: 1 | N52: 33.3 | P52: =M52+J52 -> 10 | R52: =B52-(J52+M52) -> 3
A53: Lonoke | B53: 68 | C53: 14 | D53: 25 | E53: 46 | F53: 84 | G53: 13 | H53: 22 | I53: 66 | J53: 11 | K53: 16.7 | L53: 55 | M53: 14 | N53: 25.5 | P53: =M53+J53 -> 25 | R53: =B53-(J53+M53) -> 43
A54: Prairie | B54: 2 | C54: 0 | D54: 6 | E54: 2 | F54: 8 | G54: 1 | H54: 4 | I54: 2 | J54: 2 | K54: 100 | L54: 0 | M54: 0 | P54: =M54+J54 -> 2 | R54: =B54-(J54+M54) -> 0
A55: Clay | B55: 14 | C55: 3 | D55: 12 | E55: 8 | F55: 18 | G55: 2 | H55: 2 | I55: 14 | J55: 5 | K55: 35.7 | L55: 9 | M55: 8 | N55: 88.9 | P55: =M55+J55 -> 13 | R55: =B55-(J55+M55) -> 1
A56: Craighead | B56: 95 | C56: 4 | D56: 68 | E56: 37 | F56: 72 | G56: 7 | H56: 10 | I56: 91 | J56: 29 | K56: 31.9 | L56: 62 | M56: 24 | N56: 38.7 | P56: =M56+J56 -> 53 | R56: =B56-(J56+M56) -> 42
A57: Fulton | B57: 8 | C57: 0 | D57: 10 | E57: 4 | F57: 10 | G57: 0 | H57: 0 | I57: 8 | J57: 2 | K57: 25 | L57: 6 | M57: 2 | N57: 33.3 | P57: =M57+J57 -> 4 | R57: =B57-(J57+M57) -> 4
A58: Greene | B58: 102 | C58: 10 | D58: 38 | E58: 17 | F58: 38 | G58: 6 | H58: 13 | I58: 99 | J58: 24 | K58: 24.2 | L58: 75 | M58: 10 | N58: 13.3 | P58: =M58+J58 -> 34 | R58: =B58-(J58+M58) -> 68
A59: Izard | B59: 21 | C59: 2 | D59: 3 | E59: 2 | F59: 7 | G59: 0 | H59: 0 | I59: 21 | J59: 9 | K59: 42.9 | L59: 12 | M59: 0 | N59: 0 | P59: =M59+J59 -> 9 | R59: =B59-(J59+M59) -> 12
A60: Lawrence | B60: 26 | C60: 1 | D60: 16 | E60: 8 | F60: 21 | G60: 2 | H60: 5 | I60: 24 | J60: 9 | K60: 37.5 | L60: 15 | M60: 2 | N60: 13.3 | P60: =M60+J60 -> 11 | R60: =B60-(J60+M60) -> 15
A61: Mississippi | B61: 27 | C61: 1 | D61: 7 | E61: 11 | F61: 17 | G61: 5 | H61: 6 | I61: 22 | J61: 8 | K61: 36.4 | L61: 14 | M61: 2 | N61: 14.3 | P61: =M61+J61 -> 10 | R61: =B61-(J61+M61) -> 17
A62: Randolph | B62: 42 | C62: 2 | D62: 13 | E62: 5 | F62: 16 | G62: 2 | H62: 3 | I62: 35 | J62: 16 | K62: 45.7 | L62: 19 | M62: 4 | N62: 21.1 | P62: =M62+J62 -> 20 | R62: =B62-(J62+M62) -> 22
A63: Sharp | B63: 31 | C63: 6 | D63: 17 | E63: 12 | F63: 23 | G63: 7 | H63: 9 | I63: 31 | J63: 8 | K63: 25.8 | L63: 23 | M63: 6 | N63: 26.1 | P63: =M63+J63 -> 14 | R63: =B63-(J63+M63) -> 17
A64: Cleburne | B64: 38 | C64: 1 | D64: 16 | E64: 12 | F64: 23 | G64: 3 | H64: 4 | I64: 36 | J64: 14 | K64: 38.9 | L64: 22 | M64: 2 | N64: 9.1 | P64: =M64+J64 -> 16 | R64: =B64-(J64+M64) -> 22
A65: Crittenden | B65: 67 | C65: 0 | D65: 35 | E65: 12 | F65: 21 | G65: 6 | H65: 8 | I65: 61 | J65: 17 | K65: 27.9 | L65: 44 | M65: 6 | N65: 13.6 | P65: =M65+J65 -> 23 | R65: =B65-(J65+M65) -> 44
A66: Cross | B66: 23 | C66: 1 | D66: 13 | E66: 29 | F66: 64 | G66: 4 | H66: 8 | I66: 22 | J66: 5 | K66: 22.7 | L66: 17 | M66: 0 | N66: 0 | P66: =M66+J66 -> 5 | R66: =B66-(J66+M66) -> 18
... A75: Chicot | B75: 7 | C75: 0 | D75: 5 | E75: 3 | F75: 6 | G75: 2 | H75: 4 | I75: 7 | J75: 2 | K75: 28.6 | L75: 5 | M75: 0 | N75: 0 | P75: =M75+J75 -> 2 | R75: =B75-(J75+M75) -> 5
A76: Desha | B76: 1 | C76: 0 | D76: 1 | E76: 3 | F76: 5 | G76: 2 | H76: 4 | I76: 1 | J76: 1 | K76: 100 | L76: 0 | M76: 0 | P76: =M76+J76 -> 1 | R76: =B76-(J76+M76) -> 0
A77: Drew | B77: 12 | C77: 1 | D77: 6 | E77: 16 | F77: 40 | G77: 8 | H77: 9 | I77: 12 | J77: 7 | K77: 58.3 | L77: 5 | M77: 0 | N77: 0 | P77: =M77+J77 -> 7 | R77: =B77-(J77+M77) -> 5
A78: Lee | B78: 10 | C78: 0 | D78: 5 | E78: 4 | F78: 8 | G78: 3 | H78: 6 | I78: 10 | J78: 10 | K78: 100 | L78: 0 | M78: 0 | P78: =M78+J78 -> 10 | R78: =B78-(J78+M78) -> 0
A79: Monroe | B79: 12 | C79: 1 | D79: 5 | E79: 8 | F79: 18 | G79: 1 | H79: 1 | I79: 12 | J79: 7 | K79: 58.3 | L79: 5 | M79: 2 | N79: 40 | P79: =M79+J79 -> 9 | R79: =B79-(J79+M79) -> 3
A80: Phillips | B80: 17 | C80: 1 | D80: 9 | E80: 3 | F80: 5 | G80: 2 | H80: 3 | I80: 17 | J80: 16 | K80: 94.1 | L80: 1 | M80: 0 | N80: 0 | P80: =M80+J80 -> 16 | R80: =B80-(J80+M80) -> 1
A81: St. Francis | B81: 21 | C81: 0 | D81: 26 | E81: 7 | F81: 14 | G81: 5 | H81: 8 | I81: 21 | J81: 13 | K81: 61.9 | L81: 8 | M81: 1 | N81: 12.5 | P81: =M81+J81 -> 14 | R81: =B81-(J81+M81) -> 7
A82: TOTAL | B82: 3604 | C82: 299 | D82: 1436 | E82: 1382 | F82: 2737 | G82: 453 | H82: 719 | I82: 3322 | J82: 1186 | K82: 35.7 | L82: 2136 | M82: 615 | N82: 28.8 | P82: =M82+J82 -> 1801 | R82: =B82-(J82+M82) -> 1803
A84: Pulaski | B84: =sum(B42:B45) -> 480 | C84: =sum(C42:C45) -> 32 | D84: =sum(D42:D45) -> 137 | E84: =sum(E42:E45) -> 162 | F84: =sum(F42:F45) -> 276 | G84: =sum(G42:G45) -> 33 | H84: =sum(H42:H45) -> 54 | I84: =sum(I42:I45) -> 426 | ... N84: =sum(N42:N45) -> 202.7 | P84: =M84+J84 -> 275 | R84: =B84-(J84+M84) -> 205

Sheet California
B1: California
A2: County | B2: County Population | C2: Number of Children in Care | D2: Average Beds per Family | E2: Number of Children in Foster Care | F2: Number of Children in Kinship Care | G2: Number of Children Placed Out-of-County | H2: Number of Foster and Kinship Homes | I2: Number of Children Waiting for Adoption | J2: Number of Children with 80+ Connections Made | K2: Biological Family Reunification Rate | L2: Number of Family Preservation Cases | M2: Number of Adoptive Families | N2: Number of Biological Families | O2: Number of Wraparound Supporters | P2: Number of Churches | Q2: Foster Family Retention Rate
A3: Alameda | B3: {=VLOOKUP($A3,CA_DEMO,2,FALSE)} -> 1682353 | C3: =vlookup(A3,'CA Data'!$A$3:$D$62,2,FALSE) -> 916 | D3: NULL | E3: =vlookup(A3,'CA Data'!$A$3:$D$62,3,FALSE) -> 294 | F3: =vlookup(A3,'CA Data'!$A$3:$D$62,4,FALSE) -> 336 | G3: NULL | H3: NULL | I3: =vlookup(A3,'CA Data'!$A$212:$B$271,2,FALSE) -> 86 | J3: NULL | K3: 0.40648379 | L3: =vlookup(A3,'CA Data'!$A$271:$D$338,4,FALSE) -> 295 | M3: NULL | N3: NULL | O3: NULL | P3: =ifna(vlookup(A3,'Population & Church Numbers'!$A$189:$D$246,4,FALSE),"NULL") -> 647 | Q3: NULL
A4: Alpine | B4: {=VLOOKUP($A4,CA_DEMO,2,FALSE)} -> 1204 | C4: =vlookup(A4,'CA Data'!$A$3:$B$62,2,FALSE) -> 0 | D4: NULL | E4: =vlookup(A4,'CA Data'!$A$3:$D$62,3,FALSE) -> 0 | F4: =vlookup(A4,'CA Data'!$A$3:$D$62,4,FALSE) -> 0 | G4: NULL | H4: NULL | I4: =vlookup(A4,'CA Data'!$A$212:$B$271,2,FALSE) -> 0 | J4: NULL | K4: N/A | L4: =vlookup(A4,'CA Data'!$A$271:$D$338,4,FALSE) -> 0 | M4: NULL | N4: NULL | O4: NULL | P4: =ifna(vlookup(A4,'Population & Church Numbers'!$A$189:$D$246,4,FALSE),"NULL") -> NULL | Q4: NULL
A5: Amador | B5: {=VLOOKUP($A5,CA_DEMO,2,FALSE)} -> 40474 | C5: =vlookup(A5,'CA Data'!$A$3:$B$62,2,FALSE) -> 54 | D5: NULL | E5: =vlookup(A5,'CA Data'!$A$3:$D$62,3,FALSE) -> 22 | F5: =vlookup(A5,'CA Data'!$A$3:$D$62,4,FALSE) -> 18 | G5: NULL | H5: NULL | I5: =vlookup(A5,'CA Data'!$A$212:$B$271,2,FALSE) -> * | J5: NULL | K5: N/A | L5: =vlookup(A5,'CA Data'!$A$271:$D$338,4,FALSE) -> 0 | M5: NULL | N5: NULL | O5: NULL | P5: =ifna(vlookup(A5,'Population & Church Numbers'!$A$189:$D$246,4,FALSE),"NULL") -> 25 | Q5: NULL
A6: Butte | B6: {=VLOOKUP($A6,CA_DEMO,2,FALSE)} -> 211632 | C6: =vlookup(A6,'CA Data'!$A$3:$B$62,2,FALSE) -> 347 | D6: NULL | E6: =vlookup(A6,'CA Data'!$A$3:$D$62,3,FALSE) -> 147 | F6: =vlookup(A6,'CA Data'!$A$3:$D$62,4,FALSE) -> 92 | G6: NULL | H6: NULL | I6: =vlookup(A6,'CA Data'!$A$212:$B$271,2,FALSE) -> 104 | J6: NULL | K6: 0.48148148 | L6: =vlookup(A6,'CA Data'!$A$271:$D$338,4,FALSE) -> 43 | M6: NULL | N6: NULL | O6: NULL | P6: =ifna(vlookup(A6,'Population & Church Numbers'!$A$189:$D$246,4,FALSE),"NULL") -> 118 | Q6: NULL
A7: Calaveras | B7: {=VLOOKUP($A7,CA_DEMO,2,FALSE)} -> 45292 | C7: =vlookup(A7,'CA Data'!$A$3:$B$62,2,FALSE) -> 53 | D7: NULL | E7: =vlookup(A7,'CA Data'!$A$3:$D$62,3,FALSE) -> 26 | F7: =vlookup(A7,'CA Data'!$A$3:$D$62,4,FALSE) -> 15 | G7: NULL | H7: NULL | I7: =vlookup(A7,'CA Data'!$A$212:$B$271,2,FALSE) -> * | J7: NULL | K7: 0.57692308 | L7: =vlookup(A7,'CA Data'!$A$271:$D$338,4,FALSE) -> 25 | M7: NULL | N7: NULL | O7: NULL | P7: =ifna(vlookup(A7,'Population & Church Numbers'!$A$189:$D$246,4,FALSE),"NULL") -> 40 | Q7: NULL
A8: Colusa | B8: {=VLOOKUP($A8,CA_DEMO,2,FALSE)} -> 21839 | C8: =vlookup(A8,'CA Data'!$A$3:$B$62,2,FALSE) -> 35 | D8: NULL | E8: =vlookup(A8,'CA Data'!$A$3:$D$62,3,FALSE) -> 22 | F8: =vlookup(A8,'CA Data'!$A$3:$D$62,4,FALSE) -> NULL | G8: NULL | H8: NULL | I8: =vlookup(A8,'CA Data'!$A$212:$B$271,2,FALSE) -> * | J8: NULL | K8: N/A | L8: =vlookup(A8,'CA Data'!$A$271:$D$338,4,FALSE) -> 0 | M8: NULL | N8: NULL | O8: NULL | P8: =ifna(vlookup(A8,'Population & Church Numbers'!$A$189:$D$246,4,FALSE),"NULL") -> 20 | Q8: NULL
A9: Contra Costa | B9: {=VLOOKUP($A9,CA_DEMO,2,FALSE)} -> 1165927 | C9: =vlookup(A9,'CA Data'!$A$3:$B$62,2,FALSE) -> 513 | D9: NULL | E9: =vlookup(A9,'CA Data'!$A$3:$D$62,3,FALSE) -> 219 | F9: =vlookup(A9,'CA Data'!$A$3:$D$62,4,FALSE) -> 122 | G9: NULL | H9: NULL | I9: =vlookup(A9,'CA Data'!$A$212:$B$271,2,FALSE) -> 28 | J9: NULL | K9: 0.4535316 | L9: =vlookup(A9,'CA Data'!$A$271:$D$338,4,FALSE) -> 188 | M9: NULL | N9: NULL | O9: NULL | P9: =ifna(vlookup(A9,'Population & Church Numbers'!$A$189:$D$246,4,FALSE),"NULL") -> 405 | Q9: NULL
A10: Del Norte | B10: {=VLOOKUP($A10,CA_DEMO,2,FALSE)} -> 27743 | C10: =vlookup(A10,'CA Data'!$A$3:$B$62,2,FALSE) -> 86 | D10: NULL | E10: =vlookup(A10,'CA Data'!$A$3:$D$62,3,FALSE) -> 38 | F10: =vlookup(A10,'CA Data'!$A$3:$D$62,4,FALSE) -> 17 | G10: NULL | H10: NULL | I10: =vlookup(A10,'CA Data'!$A$212:$B$271,2,FALSE) -> 11 | J10: NULL | K10: 0.64705882 | L10: =vlookup(A10,'CA Data'!$A$271:$D$338,4,FALSE) -> 0 | M10: NULL | N10: NULL | O10: NULL | P10: =ifna(vlookup(A10,'Population & Church Numbers'!$A$189:$D$246,4,FALSE),"NULL") -> 23 | Q10: NULL
A11: El Dorado | B11: {=VLOOKUP($A11,CA_DEMO,2,FALSE)} -> 191185 | C11: =vlookup(A11,'CA Data'!$A$3:$B$62,2,FALSE) -> 99 | D11: NULL | E11: =vlookup(A11,'CA Data'!$A$3:$D$62,3,FALSE) -> 32 | F11: =vlookup(A11,'CA Data'!$A$3:$D$62,4,FALSE) -> 39 | G11: NULL | H11: NULL | I11: =vlookup(A11,'CA Data'!$A$212:$B$271,2,FALSE) -> * | J11: NULL | K11: 0.39240506 | L11: =vlookup(A11,'CA Data'!$A$271:$D$338,4,FALSE) -> 85 | M11: NULL | N11: NULL | O11: NULL | P11: =ifna(vlookup(A11,'Population & Church Numbers'!$A$189:$D$246,4,FALSE),"NULL") -> 69 | Q11: NULL
A12: Fresno | B12: {=VLOOKUP($A12,CA_DEMO,2,FALSE)} -> 1008654 | C12: =vlookup(A12,'CA Data'!$A$3:$B$62,2,FALSE) -> 2093 | D12: NULL | E12: =vlookup(A12,'CA Data'!$A$3:$D$62,3,FALSE) -> 979 | F12: =vlookup(A12,'CA Data'!$A$3:$D$62,4,FALSE) -> 541 | G12: NULL | H12: NULL | I12: =vlookup(A12,'CA Data'!$A$212:$B$271,2,FALSE) -> 258 | J12: NULL | K12: 0.50347222 | L12: =vlookup(A12,'CA Data'!$A$271:$D$338,4,FALSE) -> 207 | M12: NULL | N12: NULL | O12: NULL | P12: =ifna(vlookup(A12,'Population & Church Numbers'!$A$189:$D$246,4,FALSE),"NULL") -> 423 | Q12: NULL
A13: Glenn | B13: {=VLOOKUP($A13,CA_DEMO,2,FALSE)} -> 28917 | C13: =vlookup(A13,'CA Data'!$A$3:$B$62,2,FALSE) -> 46 | D13: NULL | E13: =vlookup(A13,'CA Data'!$A$3:$D$62,3,FALSE) -> NULL | F13: =vlookup(A13,'CA Data'!$A$3:$D$62,4,FALSE) -> 14 | G13: NULL | H13: NULL | I13: =vlookup(A13,'CA Data'!$A$212:$B$271,2,FALSE) -> * | J13: NULL | K13: N/A | L13: =vlookup(A13,'CA Data'!$A$271:$D$338,4,FALSE) -> 30 | M13: NULL | N13: NULL | O13: NULL | P13: =ifna(vlookup(A13,'Population & Church Numbers'!$A$189:$D$246,4,FALSE),"NULL") -> 27 | Q13: NULL
A14: Humboldt | B14: {=VLOOKUP($A14,CA_DEMO,2,FALSE)} -> 136463 | C14: =vlookup(A14,'CA Data'!$A$3:$B$62,2,FALSE) -> 281 | D14: NULL | E14: =vlookup(A14,'CA Data'!$A$3:$D$62,3,FALSE) -> 78 | F14: =vlookup(A14,'CA Data'!$A$3:$D$62,4,FALSE) -> 93 | G14: NULL | H14: NULL | I14: =vlookup(A14,'CA Data'!$A$212:$B$271,2,FALSE) -> 18 | J14: NULL | K14: 0.33333333 | L14: =vlookup(A14,'CA Data'!$A$271:$D$338,4,FALSE) -> 135 | M14: NULL | N14: NULL | O14: NULL | P14: =ifna(vlookup(A14,'Population & Church Numbers'!$A$189:$D$246,4,FALSE),"NULL") -> 100 | Q14: NULL
A15: Imperial | B15: {=VLOOKUP($A15,CA_DEMO,2,FALSE)} -> 179702 | C15: =vlookup(A15,'CA Data'!$A$3:$B$62,2,FALSE) -> 270 | D15: NULL | E15: =vlookup(A15,'CA Data'!$A$3:$D$62,3,FALSE) -> 102 | F15: =vlookup(A15,'CA Data'!$A$3:$D$62,4,FALSE) -> 102 | G15: NULL | H15: NULL | I15: =vlookup(A15,'CA Data'!$A$212:$B$271,2,FALSE) -> 56 | J15: NULL | K15: 0.53179191 | L15: =vlookup(A15,'CA Data'!$A$271:$D$338,4,FALSE) -> 57 | M15: NULL | N15: NULL | O15: NULL | P15: =ifna(vlookup(A15,'Population & Church Numbers'!$A$189:$D$246,4,FALSE),"NULL") -> 72 | Q15: NULL
A16: Inyo | B16: {=VLOOKUP($A16,CA_DEMO,2,FALSE)} -> 19016 | C16: =vlookup(A16,'CA Data'!$A$3:$B$62,2,FALSE) -> 33 | D16: NULL | E16: =vlookup(A16,'CA Data'!$A$3:$D$62,3,FALSE) -> 12 | F16: =vlookup(A16,'CA Data'!$A$3:$D$62,4,FALSE) -> 15 | G16: NULL | H16: NULL | I16: =vlookup(A16,'CA Data'!$A$212:$B$271,2,FALSE) -> 0 | J16: NULL | K16: N/A | L16: =vlookup(A16,'CA Data'!$A$271:$D$338,4,FALSE) -> 0 | M16: NULL | N16: NULL | O16: NULL | P16: =ifna(vlookup(A16,'Population & Church Numbers'!$A$189:$D$246,4,FALSE),"NULL") -> 24 | Q16: NULL
A17: Kern | B17: {=VLOOKUP($A17,CA_DEMO,2,FALSE)} -> 909235 | C17: =vlookup(A17,'CA Data'!$A$3:$B$62,2,FALSE) -> 1728 | D17: NULL | E17: =vlookup(A17,'CA Data'!$A$3:$D$62,3,FALSE) -> 881 | F17: =vlookup(A17,'CA Data'!$A$3:$D$62,4,FALSE) -> 512 | G17: NULL | H17: NULL | I17: =vlookup(A17,'CA Data'!$A$212:$B$271,2,FALSE) -> 150 | J17: NULL | K17: 0.49001052 | L17: =vlookup(A17,'CA Data'!$A$271:$D$338,4,FALSE) -> 307 | M17: NULL | N17: NULL | O17: NULL | P17: =ifna(vlookup(A17,'Population & Church Numbers'!$A$189:$D$246,4,FALSE),"NULL") -> 381 | Q17: NULL
A18: Kings | B18: {=VLOOKUP($A18,CA_DEMO,2,FALSE)} -> 152486 | C18: =vlookup(A18,'CA Data'!$A$3:$B$62,2,FALSE) -> 298 | D18: NULL | E18: =vlookup(A18,'CA Data'!$A$3:$D$62,3,FALSE) -> 121 | F18: =vlookup(A18,'CA Data'!$A$3:$D$62,4,FALSE) -> 124 | G18: NULL | H18: NULL | I18: =vlookup(A18,'CA Data'!$A$212:$B$271,2,FALSE) -> 12 | J18: NULL | K18: 0.41747573 | L18: =vlookup(A18,'CA Data'!$A$271:$D$338,4,FALSE) -> 74 | M18: NULL | N18: NULL | O18: NULL | P18: =ifna(vlookup(A18,'Population & Church Numbers'!$A$189:$D$246,4,FALSE),"NULL") -> 60 | Q18: NULL
A19: Lake | B19: {=VLOOKUP($A19,CA_DEMO,2,FALSE)} -> 68163 | C19: =vlookup(A19,'CA Data'!$A$3:$B$62,2,FALSE) -> 69 | D19: NULL | E19: =vlookup(A19,'CA Data'!$A$3:$D$62,3,FALSE) -> 17 | F19: =vlookup(A19,'CA Data'!$A$3:$D$62,4,FALSE) -> 23 | G19: NULL | H19: NULL | I19: =vlookup(A19,'CA Data'!$A$212:$B$271,2,FALSE) -> * | J19: NULL | K19: N/A | L19: =vlookup(A19,'CA Data'!$A$271:$D$338,4,FALSE) -> 0 | M19: NULL | N19: NULL | O19: NULL | P19: =ifna(vlookup(A19,'Population & Church Numbers'!$A$189:$D$246,4,FALSE),"NULL") -> 43 | Q19: NULL
A20: Lassen | B20: {=VLOOKUP($A20,CA_DEMO,2,FALSE)} -> 32730 | C20: =vlookup(A20,'CA Data'!$A$3:$B$62,2,FALSE) -> 52 | D20: NULL | E20: =vlookup(A20,'CA Data'!$A$3:$D$62,3,FALSE) -> 35 | F20: =vlookup(A20,'CA Data'!$A$3:$D$62,4,FALSE) -> NULL | G20: NULL | H20: NULL | I20: =vlookup(A20,'CA Data'!$A$212:$B$271,2,FALSE) -> * | J20: NULL | K20: 0.62962963 | L20: =vlookup(A20,'CA Data'!$A$271:$D$338,4,FALSE) -> 0 | M20: NULL | N20: NULL | O20: NULL | P20: =ifna(vlookup(A20,'Population & Church Numbers'!$A$189:$D$246,4,FALSE),"NULL") -> 29 | Q20: NULL
A21: Los Angeles | B21: {=VLOOKUP($A21,CA_DEMO,2,FALSE)} -> 10014009 | C21: =vlookup(A21,'CA Data'!$A$3:$B$62,2,FALSE) -> 15018 | D21: NULL | E21: =vlookup(A21,'CA Data'!$A$3:$D$62,3,FALSE) -> 6150 | F21: =vlookup(A21,'CA Data'!$A$3:$D$62,4,FALSE) -> 6029 | G21: NULL | H21: NULL | I21: =vlookup(A21,'CA Data'!$A$212:$B$271,2,FALSE) -> 3563 | J21: NULL | K21: 0.48168193 | L21: =vlookup(A21,'CA Data'!$A$271:$D$338,4,FALSE) -> 6395 | M21: NULL | N21: NULL | O21: NULL | P21: =ifna(vlookup(A21,'Population & Church Numbers'!$A$189:$D$246,4,FALSE),"NULL") -> 3447 | Q21: NULL
A22: Madera | B22: {=VLOOKUP($A22,CA_DEMO,2,FALSE)} -> 156255 | C22: =vlookup(A22,'CA Data'!$A$3:$B$62,2,FALSE) -> 210 | D22: NULL | E22: =vlookup(A22,'CA Data'!$A$3:$D$62,3,FALSE) -> 95 | F22: =vlookup(A22,'CA Data'!$A$3:$D$62,4,FALSE) -> 57 | G22: NULL | H22: NULL | I22: =vlookup(A22,'CA Data'!$A$212:$B$271,2,FALSE) -> * | J22: NULL | K22: 0.50819672 | L22: =vlookup(A22,'CA Data'!$A$271:$D$338,4,FALSE) -> 93 | M22: NULL | N22: NULL | O22: NULL | P22: =ifna(vlookup(A22,'Population & Church Numbers'!$A$189:$D$246,4,FALSE),"NULL") -> 67 | Q22: NULL
A23: Marin | B23: {=VLOOKUP($A23,CA_DEMO,2,FALSE)} -> 262321 | C23: =vlookup(A23,'CA Data'!$A$3:$B$62,2,FALSE) -> 69 | D23: NULL | E23: =vlookup(A23,'CA Data'!$A$3:$D$62,3,FALSE) -> NULL | F23: =vlookup(A23,'CA Data'!$A$3:$D$62,4,FALSE) -> 26 | G23: NULL | H23: NULL | I23: =vlookup(A23,'CA Data'!$A$212:$B$271,2,FALSE) -> * | J23: NULL | K23: 0.36585366 | L23: =vlookup(A23,'CA Data'!$A$271:$D$338,4,FALSE) -> 31 | M23: NULL | N23: NULL | O23: NULL | P23: =ifna(vlookup(A23,'Population & Church Numbers'!$A$189:$D$246,4,FALSE),"NULL") -> 92 | Q23: NULL
A24: Mariposa | B24: {=VLOOKUP($A24,CA_DEMO,2,FALSE)} -> 17131 | C24: =vlookup(A24,'CA Data'!$A$3:$B$62,2,FALSE) -> 35 | D24: NULL | E24: =vlookup(A24,'CA Data'!$A$3:$D$62,3,FALSE) -> 14 | F24: =vlookup(A24,'CA Data'!$A$3:$D$62,4,FALSE) -> NULL | G24: NULL | H24: NULL | I24: =vlookup(A24,'CA Data'!$A$212:$B$271,2,FALSE) -> 0 | J24: NULL | K24: N/A | L24: =vlookup(A24,'CA Data'!$A$271:$D$338,4,FALSE) -> 0 | M24: NULL | N24: NULL | O24: NULL | P24: =ifna(vlookup(A24,'Population & Church Numbers'!$A$189:$D$246,4,FALSE),"NULL") -> 20 | Q24: NULL
A25: Mendocino | B25: {=VLOOKUP($A25,CA_DEMO,2,FALSE)} -> 91601 | C25: =vlookup(A25,'CA Data'!$A$3:$B$62,2,FALSE) -> 205 | D25: NULL | E25: =vlookup(A25,'CA Data'!$A$3:$D$62,3,FALSE) -> 94 | F25: =vlookup(A25,'CA Data'!$A$3:$D$62,4,FALSE) -> 36 | G25: NULL | H25: NULL | I25: =vlookup(A25,'CA Data'!$A$212:$B$271,2,FALSE) -> * | J25: NULL | K25: 0.5472973 | L25: =vlookup(A25,'CA Data'!$A$271:$D$338,4,FALSE) -> 60 | M25: NULL | N25: NULL | O25: NULL | P25: =ifna(vlookup(A25,'Population & Church Numbers'!$A$189:$D$246,4,FALSE),"NULL") -> 53 | Q25: NULL
A26: Merced | B26: {=VLOOKUP($A26,CA_DEMO,2,FALSE)} -> 281202 | C26: =vlookup(A26,'CA Data'!$A$3:$B$62,2,FALSE) -> 615 | D26: NULL | E26: =vlookup(A26,'CA Data'!$A$3:$D$62,3,FALSE) -> 285 | F26: =vlookup(A26,'CA Data'!$A$3:$D$62,4,FALSE) -> 224 | G26: NULL | H26: NULL | I26: =vlookup(A26,'CA Data'!$A$212:$B$271,2,FALSE) -> 81 | J26: NULL | K26: 0.58744395 | L26: =vlookup(A26,'CA Data'!$A$271:$D$338,4,FALSE) -> 76 | M26: NULL | N26: NULL | O26: NULL | P26: =ifna(vlookup(A26,'Population & Church Numbers'!$A$189:$D$246,4,FALSE),"NULL") -> 111 | Q26: NULL
A27: Modoc | B27: {=VLOOKUP($A27,CA_DEMO,2,FALSE)} -> 8700 | C27: =vlookup(A27,'CA Data'!$A$3:$B$62,2,FALSE) -> 18 | D27: NULL | E27: =vlookup(A27,'CA Data'!$A$3:$D$62,3,FALSE) -> NULL | F27: =vlookup(A27,'CA Data'!$A$3:$D$62,4,FALSE) -> NULL | G27: NULL | H27: NULL | I27: =vlookup(A27,'CA Data'!$A$212:$B$271,2,FALSE) -> * | J27: NULL | K27: 0.9 | L27: =vlookup(A27,'CA Data'!$A$271:$D$338,4,FALSE) -> 12 | M27: NULL | N27: NULL | O27: NULL | P27: =ifna(vlookup(A27,'Population & Church Numbers'!$A$189:$D$246,4,FALSE),"NULL") -> 12 | Q27: NULL
A28: Mono | B28: {=VLOOKUP($A28,CA_DEMO,2,FALSE)} -> 13195 | C28: =vlookup(A28,'CA Data'!$A$3:$B$62,2,FALSE) -> M | D28: NULL | E28: =vlookup(A28,'CA Data'!$A$3:$D$62,3,FALSE) -> NULL | F28: =vlookup(A28,'CA Data'!$A$3:$D$62,4,FALSE) -> NULL | G28: NULL | H28: NULL | I28: =vlookup(A28,'CA Data'!$A$212:$B$271,2,FALSE) -> 0 | J28: NULL | K28: N/A | L28: =vlookup(A28,'CA Data'!$A$271:$D$338,4,FALSE) -> 0 | M28: NULL | N28: NULL | O28: NULL | P28: =ifna(vlookup(A28,'Population & Church Numbers'!$A$189:$D$246,4,FALSE),"NULL") -> 12 | Q28: NULL
A29: Monterey | B29: {=VLOOKUP($A29,CA_DEMO,2,FALSE)} -> 439035 | C29: =vlookup(A29,'CA Data'!$A$3:$B$62,2,FALSE) -> 161 | D29: NULL | E29: =vlookup(A29,'CA Data'!$A$3:$D$62,3,FALSE) -> 84 | F29: =vlookup(A29,'CA Data'!$A$3:$D$62,4,FALSE) -> 32 | G29: NULL | H29: NULL | I29: =vlookup(A29,'CA Data'!$A$212:$B$271,2,FALSE) -> * | J29: NULL | K29: 0.33766234 | L29: =vlookup(A29,'CA Data'!$A$271:$D$338,4,FALSE) -> 57 | M29: NULL | N29: NULL | O29: NULL | P29: =ifna(vlookup(A29,'Population & Church Numbers'!$A$189:$D$246,4,FALSE),"NULL") -> 173 | Q29: NULL
A30: Napa | B30: {=VLOOKUP($A30,CA_DEMO,2,FALSE)} -> 138019 | C30: =vlookup(A30,'CA Data'!$A$3:$B$62,2,FALSE) -> 61 | D30: NULL | E30: =vlookup(A30,'CA Data'!$A$3:$D$62,3,FALSE) -> 15 | F30: =vlookup(A30,'CA Data'!$A$3:$D$62,4,FALSE) -> 19 | G30: NULL | H30: NULL | I30: =vlookup(A30,'CA Data'!$A$212:$B$271,2,FALSE) -> 16 | J30: NULL | K30: 0.48275862 | L30: =vlookup(A30,'CA Data'!$A$271:$D$338,4,FALSE) -> 32 | M30: NULL | N30: NULL | O30: NULL | P30: =ifna(vlookup(A30,'Population & Church Numbers'!$A$189:$D$246,4,FALSE),"NULL") -> 50 | Q30: NULL
A31: Nevada | B31: {=VLOOKUP($A31,CA_DEMO,2,FALSE)} -> 102241 | C31: =vlookup(A31,'CA Data'!$A$3:$B$62,2,FALSE) -> 36 | D31: NULL | E31: =vlookup(A31,'CA Data'!$A$3:$D$62,3,FALSE) -> 11 | F31: =vlookup(A31,'CA Data'!$A$3:$D$62,4,FALSE) -> 13 | G31: NULL | H31: NULL | I31: =vlookup(A31,'CA Data'!$A$212:$B$271,2,FALSE) -> * | J31: NULL | K31: N/A | L31: =vlookup(A31,'CA Data'!$A$271:$D$338,4,FALSE) -> 0 | M31: NULL | N31: NULL | O31: NULL | P31: =ifna(vlookup(A31,'Population & Church Numbers'!$A$189:$D$246,4,FALSE),"NULL") -> 44 | Q31: NULL
A32: Orange | B32: {=VLOOKUP($A32,CA_DEMO,2,FALSE)} -> 3186989 | C32: =vlookup(A32,'CA Data'!$A$3:$B$62,2,FALSE) -> 2205 | D32: NULL | E32: =vlookup(A32,'CA Data'!$A$3:$D$62,3,FALSE) -> 543 | F32: =vlookup(A32,'CA Data'!$A$3:$D$62,4,FALSE) -> 1107 | G32: NULL | H32: NULL | I32: =vlookup(A32,'CA Data'!$A$212:$B$271,2,FALSE) -> 344 | J32: NULL | K32: 0.52457695 | L32: =vlookup(A32,'CA Data'!$A$271:$D$338,4,FALSE) -> 1069 | M32: NULL | N32: NULL | O32: NULL | P32: =ifna(vlookup(A32,'Population & Church Numbers'!$A$189:$D$246,4,FALSE),"NULL") -> 856 | Q32: NULL
A33: Placer | B33: {=VLOOKUP($A33,CA_DEMO,2,FALSE)} -> 404739 | C33: =vlookup(A33,'CA Data'!$A$3:$B$62,2,FALSE) -> 153 | D33: NULL | E33: =vlookup(A33,'CA Data'!$A$3:$D$62,3,FALSE) -> 51 | F33: =vlookup(A33,'CA Data'!$A$3:$D$62,4,FALSE) -> 56 | G33: NULL | H33: NULL | I33: =vlookup(A33,'CA Data'!$A$212:$B$271,2,FALSE) -> * | J33: NULL | K33: 0.55445545 | L33: =vlookup(A33,'CA Data'!$A$271:$D$338,4,FALSE) -> 58 | M33: NULL | N33: NULL | O33: NULL | P33: =ifna(vlookup(A33,'Population & Church Numbers'!$A$189:$D$246,4,FALSE),"NULL") -> 142 | Q33: NULL
A34: Plumas | B34: {=VLOOKUP($A34,CA_DEMO,2,FALSE)} -> 19790 | C34: =vlookup(A34,'CA Data'!$A$3:$B$62,2,FALSE) -> 22 | D34: NULL | E34: =vlookup(A34,'CA Data'!$A$3:$D$62,3,FALSE) -> NULL | F34: =vlookup(A34,'CA Data'!$A$3:$D$62,4,FALSE) -> NULL | G34: NULL | H34: NULL | I34: =vlookup(A34,'CA Data'!$A$212:$B$271,2,FALSE) -> * | J34: NULL | K34: 0.72727273 | L34: =vlookup(A34,'CA Data'!$A$271:$D$338,4,FALSE) -> 14 | M34: NULL | N34: NULL | O34: NULL | P34: =ifna(vlookup(A34,'Population & Church Numbers'!$A$189:$D$246,4,FALSE),"NULL") -> 28 | Q34: NULL
A35: Riverside | B35: {=VLOOKUP($A35,CA_DEMO,2,FALSE)} -> 2418185 | C35: =vlookup(A35,'CA Data'!$A$3:$B$62,2,FALSE) -> 3119 | D35: NULL | E35: =vlookup(A35,'CA Data'!$A$3:$D$62,3,FALSE) -> 1320 | F35: =vlookup(A35,'CA Data'!$A$3:$D$62,4,FALSE) -> 1177 | G35: NULL | H35: NULL | I35: =vlookup(A35,'CA Data'!$A$212:$B$271,2,FALSE) -> 357 | J35: NULL | K35: 0.52603471 | L35: =vlookup(A35,'CA Data'!$A$271:$D$338,4,FALSE) -> 1706 | M35: NULL | N35: NULL | O35: NULL | P35: =ifna(vlookup(A35,'Population & Church Numbers'!$A$189:$D$246,4,FALSE),"NULL") -> 656 | Q35: NULL
A36: Sacramento | B36: {=VLOOKUP($A36,CA_DEMO,2,FALSE)} -> 1585055 | C36: =vlookup(A36,'CA Data'!$A$3:$B$62,2,FALSE) -> 1176 | D36: NULL | E36: =vlookup(A36,'CA Data'!$A$3:$D$62,3,FALSE) -> 457 | F36: =vlookup(A36,'CA Data'!$A$3:$D$62,4,FALSE) -> 277 | G36: NULL | H36: NULL | I36: =vlookup(A36,'CA Data'!$A$212:$B$271,2,FALSE) -> 166 | J36: NULL | K36: 0.4616307 | L36: =vlookup(A36,'CA Data'!$A$271:$D$338,4,FALSE) -> 469 | M36: NULL | N36: NULL | O36: NULL | P36: =ifna(vlookup(A36,'Population & Church Numbers'!$A$189:$D$246,4,FALSE),"NULL") -> 538 | Q36: NULL
A37: San Benito | B37: {=VLOOKUP($A37,CA_DEMO,2,FALSE)} -> 64209 | C37: =vlookup(A37,'CA Data'!$A$3:$B$62,2,FALSE) -> 26 | D37: NULL | E37: =vlookup(A37,'CA Data'!$A$3:$D$62,3,FALSE) -> NULL | F37: =vlookup(A37,'CA Data'!$A$3:$D$62,4,FALSE) -> 13 | G37: NULL | H37: NULL | I37: =vlookup(A37,'CA Data'!$A$212:$B$271,2,FALSE) -> 0 | J37: NULL | K37: 0.70833333 | L37: =vlookup(A37,'CA Data'!$A$271:$D$338,4,FALSE) -> 12 | M37: NULL | N37: NULL | O37: NULL | P37: =ifna(vlookup(A37,'Population & Church Numbers'!$A$189:$D$246,4,FALSE),"NULL") -> 23 | Q37: NULL
A38: San Bernardino | B38: {=VLOOKUP($A38,CA_DEMO,2,FALSE)} -> 2181654 | C38: =vlookup(A38,'CA Data'!$A$3:$B$62,2,FALSE) -> 4996 | D38: NULL | E38: =vlookup(A38,'CA Data'!$A$3:$D$62,3,FALSE) -> 2220 | F38: =vlookup(A38,'CA Data'!$A$3:$D$62,4,FALSE) -> 1544 | G38: NULL | H38: NULL | I38: =vlookup(A38,'CA Data'!$A$212:$B$271,2,FALSE) -> 643 | J38: NULL | K38: 0.45051635 | L38: =vlookup(A38,'CA Data'!$A$271:$D$338,4,FALSE) -> 795 | M38: NULL | N38: NULL | O38: NULL | P38: =ifna(vlookup(A38,'Population & Church Numbers'!$A$189:$D$246,4,FALSE),"NULL") -> 703 | Q38: NULL
A39: San Diego | B39: {=VLOOKUP($A39,CA_DEMO,2,FALSE)} -> 3298634 | C39: =vlookup(A39,'CA Data'!$A$3:$B$62,2,FALSE) -> 1655 | D39: NULL | E39: =vlookup(A39,'CA Data'!$A$3:$D$62,3,FALSE) -> 636 | F39: =vlookup(A39,'CA Data'!$A$3:$D$62,4,FALSE) -> 587 | G39: NULL | H39: NULL | I39: =vlookup(A39,'CA Data'!$A$212:$B$271,2,FALSE) -> 192 | J39: NULL | K39: 0.45605469 | L39: =vlookup(A39,'CA Data'!$A$271:$D$338,4,FALSE) -> 416 | M39: NULL | N39: NULL | O39: NULL | P39: =ifna(vlookup(A39,'Population & Church Numbers'!$A$189:$D$246,4,FALSE),"NULL") -> 991 | Q39: NULL
A40: San Francisco | B40: {=VLOOKUP($A40,CA_DEMO,2,FALSE)} -> 873965 | C40: =vlookup(A40,'CA Data'!$A$3:$B$62,2,FALSE) -> 620 | D40: NULL | E40: =vlookup(A40,'CA Data'!$A$3:$D$62,3,FALSE) -> 274 | F40: =vlookup(A40,'CA Data'!$A$3:$D$62,4,FALSE) -> 195 | G40: NULL | H40: NULL | I40: =vlookup(A40,'CA Data'!$A$212:$B$271,2,FALSE) -> 12 | J40: NULL | K40: 0.44939271 | L40: =vlookup(A40,'CA Data'!$A$271:$D$338,4,FALSE) -> 266 | M40: NULL | N40: NULL | O40: NULL | P40: =ifna(vlookup(A40,'Population & Church Numbers'!$A$189:$D$246,4,FALSE),"NULL") -> 276 | Q40: NULL
A41: San Joaquin | B41: {=VLOOKUP($A41,CA_DEMO,2,FALSE)} -> 779233 | C41: =vlookup(A41,'CA Data'!$A$3:$B$62,2,FALSE) -> 1170 | D41: NULL | E41: =vlookup(A41,'CA Data'!$A$3:$D$62,3,FALSE) -> 485 | F41: =vlookup(A41,'CA Data'!$A$3:$D$62,4,FALSE) -> 429 | G41: NULL | H41: NULL | I41: =vlookup(A41,'CA Data'!$A$212:$B$271,2,FALSE) -> 152 | J41: NULL | K41: 0.4488978 | L41: =vlookup(A41,'CA Data'!$A$271:$D$338,4,FALSE) -> 200 | M41: NULL | N41: NULL | O41: NULL | P41: =ifna(vlookup(A41,'Population & Church Numbers'!$A$189:$D$246,4,FALSE),"NULL") -> 271 | Q41: NULL
A42: San Luis Obispo | B42: {=VLOOKUP($A42,CA_DEMO,2,FALSE)} -> 282424 | C42: =vlookup(A42,'CA Data'!$A$3:$B$62,2,FALSE) -> 260 | D42: NULL | E42: =vlookup(A42,'CA Data'!$A$3:$D$62,3,FALSE) -> 106 | F42: =vlookup(A42,'CA Data'!$A$3:$D$62,4,FALSE) -> 98 | G42: NULL | H42: NULL | I42: =vlookup(A42,'CA Data'!$A$212:$B$271,2,FALSE) -> 33 | J42: NULL | K42: 0.55855856 | L42: =vlookup(A42,'CA Data'!$A$271:$D$338,4,FALSE) -> 73 | M42: NULL | N42: NULL | O42: NULL | P42: =ifna(vlookup(A42,'Population & Church Numbers'!$A$189:$D$246,4,FALSE),"NULL") -> 146 | Q42: NULL
A43: San Mateo | B43: {=VLOOKUP($A43,CA_DEMO,2,FALSE)} -> 764442 | C43: =vlookup(A43,'CA Data'!$A$3:$B$62,2,FALSE) -> 115 | D43: NULL | E43: =vlookup(A43,'CA Data'!$A$3:$D$62,3,FALSE) -> 45 | F43: =vlookup(A43,'CA Data'!$A$3:$D$62,4,FALSE) -> 25 | G43: NULL | H43: NULL | I43: =vlookup(A43,'CA Data'!$A$212:$B$271,2,FALSE) -> * | J43: NULL | K43: 0.44827586 | L43: =vlookup(A43,'CA Data'!$A$271:$D$338,4,FALSE) -> 60 | M43: NULL | N43: NULL | O43: NULL | P43: =ifna(vlookup(A43,'Population & Church Numbers'!$A$189:$D$246,4,FALSE),"NULL") -> 236 | Q43: NULL
... A47: Shasta | B47: {=VLOOKUP($A47,CA_DEMO,2,FALSE)} -> 182155 | C47: =vlookup(A47,'CA Data'!$A$3:$B$62,2,FALSE) -> 376 | D47: NULL | E47: =vlookup(A47,'CA Data'!$A$3:$D$62,3,FALSE) -> 179 | F47: =vlookup(A47,'CA Data'!$A$3:$D$62,4,FALSE) -> 127 | G47: NULL | H47: NULL | I47: =vlookup(A47,'CA Data'!$A$212:$B$271,2,FALSE) -> 43 | J47: NULL | K47: 0.51184834 | L47: =vlookup(A47,'CA Data'!$A$271:$D$338,4,FALSE) -> 39 | M47: NULL | N47: NULL | O47: NULL | P47: =ifna(vlookup(A47,'Population & Church Numbers'!$A$189:$D$246,4,FALSE),"NULL") -> 95 | Q47: NULL
A48: Sierra | B48: {=VLOOKUP($A48,CA_DEMO,2,FALSE)} -> 3236 | C48: =vlookup(A48,'CA Data'!$A$3:$B$62,2,FALSE) -> 11 | D48: NULL | E48: =vlookup(A48,'CA Data'!$A$3:$D$62,3,FALSE) -> NULL | F48: =vlookup(A48,'CA Data'!$A$3:$D$62,4,FALSE) -> NULL | G48: NULL | H48: NULL | I48: =vlookup(A48,'CA Data'!$A$212:$B$271,2,FALSE) -> 0 | J48: NULL | K48: N/A | L48: =vlookup(A48,'CA Data'!$A$271:$D$338,4,FALSE) -> 0 | M48: NULL | N48: NULL | O48: NULL | P48: =ifna(vlookup(A48,'Population & Church Numbers'!$A$189:$D$246,4,FALSE),"NULL") -> 4 | Q48: NULL
A49: Siskiyou | B49: {=VLOOKUP($A49,CA_DEMO,2,FALSE)} -> 44076 | C49: =vlookup(A49,'CA Data'!$A$3:$B$62,2,FALSE) -> 85 | D49: NULL | E49: =vlookup(A49,'CA Data'!$A$3:$D$62,3,FALSE) -> 49 | F49: =vlookup(A49,'CA Data'!$A$3:$D$62,4,FALSE) -> 18 | G49: NULL | H49: NULL | I49: =vlookup(A49,'CA Data'!$A$212:$B$271,2,FALSE) -> * | J49: NULL | K49: 0.66666667 | L49: =vlookup(A49,'CA Data'!$A$271:$D$338,4,FALSE) -> 0 | M49: NULL | N49: NULL | O49: NULL | P49: =ifna(vlookup(A49,'Population & Church Numbers'!$A$189:$D$246,4,FALSE),"NULL") -> 51 | Q49: NULL
A50: Solano | B50: {=VLOOKUP($A50,CA_DEMO,2,FALSE)} -> 453491 | C50: =vlookup(A50,'CA Data'!$A$3:$B$62,2,FALSE) -> 305 | D50: NULL | E50: =vlookup(A50,'CA Data'!$A$3:$D$62,3,FALSE) -> 133 | F50: =vlookup(A50,'CA Data'!$A$3:$D$62,4,FALSE) -> 95 | G50: NULL | H50: NULL | I50: =vlookup(A50,'CA Data'!$A$212:$B$271,2,FALSE) -> 60 | J50: NULL | K50: 0.28467153 | L50: =vlookup(A50,'CA Data'!$A$271:$D$338,4,FALSE) -> 55 | M50: NULL | N50: NULL | O50: NULL | P50: =ifna(vlookup(A50,'Population & Church Numbers'!$A$189:$D$246,4,FALSE),"NULL") -> 188 | Q50: NULL
A51: Sonoma | B51: {=VLOOKUP($A51,CA_DEMO,2,FALSE)} -> 488863 | C51: =vlookup(A51,'CA Data'!$A$3:$B$62,2,FALSE) -> 446 | D51: NULL | E51: =vlookup(A51,'CA Data'!$A$3:$D$62,3,FALSE) -> 167 | F51: =vlookup(A51,'CA Data'!$A$3:$D$62,4,FALSE) -> 122 | G51: NULL | H51: NULL | I51: =vlookup(A51,'CA Data'!$A$212:$B$271,2,FALSE) -> 132 | J51: NULL | K51: 0.484375 | L51: =vlookup(A51,'CA Data'!$A$271:$D$338,4,FALSE) -> 177 | M51: NULL | N51: NULL | O51: NULL | P51: =ifna(vlookup(A51,'Population & Church Numbers'!$A$189:$D$246,4,FALSE),"NULL") -> 155 | Q51: NULL
A52: Stanislaus | B52: {=VLOOKUP($A52,CA_DEMO,2,FALSE)} -> 552878 | C52: =vlookup(A52,'CA Data'!$A$3:$B$62,2,FALSE) -> 514 | D52: NULL | E52: =vlookup(A52,'CA Data'!$A$3:$D$62,3,FALSE) -> 252 | F52: =vlookup(A52,'CA Data'!$A$3:$D$62,4,FALSE) -> 65 | G52: NULL | H52: NULL | I52: =vlookup(A52,'CA Data'!$A$212:$B$271,2,FALSE) -> * | J52: NULL | K52: 0.4573991 | L52: =vlookup(A52,'CA Data'!$A$271:$D$338,4,FALSE) -> 114 | M52: NULL | N52: NULL | O52: NULL | P52: =ifna(vlookup(A52,'Population & Church Numbers'!$A$189:$D$246,4,FALSE),"NULL") -> 231 | Q52: NULL
A53: Sutter | B53: {=VLOOKUP($A53,CA_DEMO,2,FALSE)} -> 99633 | C53: =vlookup(A53,'CA Data'!$A$3:$B$62,2,FALSE) -> 96 | D53: NULL | E53: =vlookup(A53,'CA Data'!$A$3:$D$62,3,FALSE) -> 45 | F53: =vlookup(A53,'CA Data'!$A$3:$D$62,4,FALSE) -> 21 | G53: NULL | H53: NULL | I53: =vlookup(A53,'CA Data'!$A$212:$B$271,2,FALSE) -> * | J53: NULL | K53: 0.47916667 | L53: =vlookup(A53,'CA Data'!$A$271:$D$338,4,FALSE) -> 0 | M53: NULL | N53: NULL | O53: NULL | P53: =ifna(vlookup(A53,'Population & Church Numbers'!$A$189:$D$246,4,FALSE),"NULL") -> 37 | Q53: NULL
A54: Tehama | B54: {=VLOOKUP($A54,CA_DEMO,2,FALSE)} -> 65829 | C54: =vlookup(A54,'CA Data'!$A$3:$B$62,2,FALSE) -> 120 | D54: NULL | E54: =vlookup(A54,'CA Data'!$A$3:$D$62,3,FALSE) -> 59 | F54: =vlookup(A54,'CA Data'!$A$3:$D$62,4,FALSE) -> 16 | G54: NULL | H54: NULL | I54: =vlookup(A54,'CA Data'!$A$212:$B$271,2,FALSE) -> 15 | J54: NULL | K54: 0.62857143 | L54: =vlookup(A54,'CA Data'!$A$271:$D$338,4,FALSE) -> 13 | M54: NULL | N54: NULL | O54: NULL | P54: =ifna(vlookup(A54,'Population & Church Numbers'!$A$189:$D$246,4,FALSE),"NULL") -> 46 | Q54: NULL
A55: Trinity | B55: {=VLOOKUP($A55,CA_DEMO,2,FALSE)} -> 16112 | C55: =vlookup(A55,'CA Data'!$A$3:$B$62,2,FALSE) -> 26 | D55: NULL | E55: =vlookup(A55,'CA Data'!$A$3:$D$62,3,FALSE) -> NULL | F55: =vlookup(A55,'CA Data'!$A$3:$D$62,4,FALSE) -> NULL | G55: NULL | H55: NULL | I55: =vlookup(A55,'CA Data'!$A$212:$B$271,2,FALSE) -> * | J55: NULL | K55: N/A | L55: =vlookup(A55,'CA Data'!$A$271:$D$338,4,FALSE) -> 0 | M55: NULL | N55: NULL | O55: NULL | P55: =ifna(vlookup(A55,'Population & Church Numbers'!$A$189:$D$246,4,FALSE),"NULL") -> 13 | Q55: NULL
A56: Tulare | B56: {=VLOOKUP($A56,CA_DEMO,2,FALSE)} -> 473117 | C56: =vlookup(A56,'CA Data'!$A$3:$B$62,2,FALSE) -> 837 | D56: NULL | E56: =vlookup(A56,'CA Data'!$A$3:$D$62,3,FALSE) -> 416 | F56: =vlookup(A56,'CA Data'!$A$3:$D$62,4,FALSE) -> 239 | G56: NULL | H56: NULL | I56: =vlookup(A56,'CA Data'!$A$212:$B$271,2,FALSE) -> 126 | J56: NULL | K56: 0.37954545 | L56: =vlookup(A56,'CA Data'!$A$271:$D$338,4,FALSE) -> 278 | M56: NULL | N56: NULL | O56: NULL | P56: =ifna(vlookup(A56,'Population & Church Numbers'!$A$189:$D$246,4,FALSE),"NULL") -> 250 | Q56: NULL
A57: Tuolumne | B57: {=VLOOKUP($A57,CA_DEMO,2,FALSE)} -> 55620 | C57: =vlookup(A57,'CA Data'!$A$3:$B$62,2,FALSE) -> 63 | D57: NULL | E57: =vlookup(A57,'CA Data'!$A$3:$D$62,3,FALSE) -> 24 | F57: =vlookup(A57,'CA Data'!$A$3:$D$62,4,FALSE) -> 18 | G57: NULL | H57: NULL | I57: =vlookup(A57,'CA Data'!$A$212:$B$271,2,FALSE) -> * | J57: NULL | K57: N/A | L57: =vlookup(A57,'CA Data'!$A$271:$D$338,4,FALSE) -> 16 | M57: NULL | N57: NULL | O57: NULL | P57: =ifna(vlookup(A57,'Population & Church Numbers'!$A$189:$D$246,4,FALSE),"NULL") -> 41 | Q57: NULL
A58: Ventura | B58: {=VLOOKUP($A58,CA_DEMO,2,FALSE)} -> 843843 | C58: =vlookup(A58,'CA Data'!$A$3:$B$62,2,FALSE) -> 435 | D58: NULL | E58: =vlookup(A58,'CA Data'!$A$3:$D$62,3,FALSE) -> 107 | F58: =vlookup(A58,'CA Data'!$A$3:$D$62,4,FALSE) -> 193 | G58: NULL | H58: NULL | I58: =vlookup(A58,'CA Data'!$A$212:$B$271,2,FALSE) -> 58 | J58: NULL | K58: 0.29889299 | L58: =vlookup(A58,'CA Data'!$A$271:$D$338,4,FALSE) -> 164 | M58: NULL | N58: NULL | O58: NULL | P58: =ifna(vlookup(A58,'Population & Church Numbers'!$A$189:$D$246,4,FALSE),"NULL") -> 269 | Q58: NULL
A59: Yolo | B59: {=VLOOKUP($A59,CA_DEMO,2,FALSE)} -> 216403 | C59: =vlookup(A59,'CA Data'!$A$3:$B$62,2,FALSE) -> 244 | D59: NULL | E59: =vlookup(A59,'CA Data'!$A$3:$D$62,3,FALSE) -> 152 | F59: =vlookup(A59,'CA Data'!$A$3:$D$62,4,FALSE) -> 64 | G59: NULL | H59: NULL | I59: =vlookup(A59,'CA Data'!$A$212:$B$271,2,FALSE) -> 48 | J59: NULL | K59: 0.49112426 | L59: =vlookup(A59,'CA Data'!$A$271:$D$338,4,FALSE) -> 73 | M59: NULL | N59: NULL | O59: NULL | P59: =ifna(vlookup(A59,'Population & Church Numbers'!$A$189:$D$246,4,FALSE),"NULL") -> 87 | Q59: NULL
A60: Yuba | B60: {=VLOOKUP($A60,CA_DEMO,2,FALSE)} -> 81575 | C60: =vlookup(A60,'CA Data'!$A$3:$B$62,2,FALSE) -> 152 | D60: NULL | E60: =vlookup(A60,'CA Data'!$A$3:$D$62,3,FALSE) -> 87 | F60: =vlookup(A60,'CA Data'!$A$3:$D$62,4,FALSE) -> 21 | G60: NULL | H60: NULL | I60: =vlookup(A60,'CA Data'!$A$212:$B$271,2,FALSE) -> * | J60: NULL | K60: 0.56756757 | L60: =vlookup(A60,'CA Data'!$A$271:$D$338,4,FALSE) | M60: NULL | N60: NULL | O60: NULL | P60: =ifna(vlookup(A60,'Population & Church Numbers'!$A$189:$D$246,4,FALSE),"NULL") -> 39 | Q60: NULL
A62: TOTAL | C62: ='CA Data'!B4 -> 43633 | D62: NULL | E62: ='CA Data'!C4 -> 18246 | F62: ='CA Data'!D4 -> 15332 | G62: NULL | H62: =AFCARSCSC!D8 -> 34924 | I62: =AFCARSCSC!C8 -> 8180 | J62: NULL | K62: NULL | L62: NULL | M62: NULL | N62: NULL | O62: NULL | P62: NULL | Q62: NULL

Sheet CA Data
A1: NUMBER OF CHILDREN IN CARE | D1: California Child Welfare Indicators Project | G1: Date Collected: | H1: 45292 | J1: Date Updated: | K1: 45442
A3: County | B3: All OOHP | C3: Foster | D3: Relative or Kinship Care | E3: Congregate Care | F3: Other | I3: Placement Type | J3: California | K3: Alameda | L3: Butte | M3: Amador | N3: Calaveras | O3: Colusa | P3: Contra Costa | Q3: Del Norte | R3: El Dorado
A4: California | B4: 43633 | C4: =sum(J4+J6+J7) -> 18246 | D4: =J5 -> 15332 | H4: Foster | I4: Pre-Adopt | J4: 2457 | K4: 16 | L4: M | M4: M | N4: M | O4: 0 | P4: M | Q4: M | R4: 0
A5: Alameda | B5: 916 | C5: =K4+K6+K7 -> 294 | D5: =K5 -> 336 | H5: Relative | I5: Relative/NREFM | J5: 15332 | K5: 336 | L5: 92 | M5: 18 | N5: 15 | O5: M | P5: 122 | Q5: 17 | R5: 39
A6: Alpine | B6: 0 | C6: 0 | D6: 0 | H6: Foster | I6: Foster | J6: 7316 | K6: 84 | L6: 55 | M6: M | N6: 13 | O6: M | P6: 148 | Q6: 38 | R6: M
A7: Amador | B7: 54 | C7: =M7 -> 22 | D7: =M5 -> 18 | H7: Foster | I7: FFA | J7: 8473 | K7: 194 | L7: 92 | M7: 22 | N7: 13 | O7: 22 | P7: 71 | Q7: M | R7: 32
A8: Butte | B8: 347 | C8: =L6+L7 -> 147 | D8: =L5 -> 92 | H8: Other | I8: Court Specified Home | J8: 561 | K8: M | L8: M | M8: 0 | N8: 0 | O8: 0 | P8: 0 | Q8: M | R8: 0
A9: Calaveras | B9: 53 | C9: =N6+N7 -> 26 | D9: =N5 -> 15 | H9: Other | I9: Tribally Approved Home | J9: 151 | K9: 0 | L9: M | M9: 0 | N9: 0 | O9: 0 | P9: 0 | Q9: 0 | R9: 0
A10: Colusa | B10: 35 | C10: =O7 -> 22 | D10: NULL | H10: Cong. Care | I10: Group | J10: 1436 | K10: 55 | L10: 11 | M10: M | N10: M | O10: M | P10: 28 | Q10: M | R10: M
A11: Contra Costa | B11: 513 | C11: =P6+P7 -> 219 | D11: =P5 -> 122 | H11: Cong. Care | I11: Shelter | J11: 168 | K11: 0 | L11: 0 | M11: 0 | N11: 0 | O11: 0 | P11: 0 | Q11: 0 | R11: 0
A12: Del Norte | B12: 86 | C12: =Q6 -> 38 | D12: =Q5 -> 17 | H12: Other | I12: Non-FC | J12: 406 | K12: M | L12: M | M12: M | N12: 0 | O12: 0 | P12: 14 | Q12: 0 | R12: M
A13: El Dorado | B13: 99 | C13: =R7+R4 -> 32 | D13: =R5 -> 39 | H13: Other | I13: Guardian - Dependent | J13: 561 | K13: 0 | L13: M | M13: 0 | N13: M | O13: 0 | P13: M | Q13: 0 | R13: 0
A14: Fresno | B14: 2093 | C14: =J24+J26+J27 -> 979 | D14: =J25 -> 541 | H14: Other | I14: Guardian - Non-Dependent | J14: 240 | K14: 0 | L14: M | M14: 0 | N14: 0 | O14: 0 | P14: M | Q14: M | R14: 0
A15: Glenn | B15: 46 | C15: NULL | D15: =K25 -> 14 | H15: Other | I15: Runaway | J15: 525 | K15: 32 | L15: M | M15: 0 | N15: 0 | O15: 0 | P15: M | Q15: M | R15: 0
A16: Humboldt | B16: 281 | C16: =L24+L26+L27 -> 78 | D16: =L25 -> 93 | H16: REMOVE | I16: Trial Home Visit | J16: 494 | K16: M | L16: 13 | M16: 0 | N16: 0 | O16: 0 | P16: M | Q16: 0 | R16: 0
A17: Imperial | B17: 270 | C17: =M26+M27 -> 102 | D17: =M25 -> 102 | H17: Other | I17: SILP | J17: 2899 | K17: 75 | L17: M | M17: M | N17: M | O17: 0 | P17: 36 | Q17: M | R17: 12
A18: Inyo | B18: 33 | C18: =N26+N24 -> 12 | D18: =N25 -> 15 | H18: Other | I18: Transitional Housing | J18: 1898 | K18: 96 | L18: 41 | M18: 0 | N18: 0 | O18: M | P18: 56 | Q18: 0 | R18: M
A19: Kern | B19: 1728 | C19: =O24+O26+O27 -> 881 | D19: =O25 -> 512 | H19: Other | I19: Other | J19: 716 | K19: M | L19: M | M19: 0 | N19: M | O19: 0 | P19: M | Q19: M | R19: M
A20: Kings | B20: 298 | C20: =P26+P27 -> 121 | D20: =P25 -> 124 | H20: Other | I20: Missing | J20: 0 | K20: 0 | L20: 0 | M20: 0 | N20: 0 | O20: 0 | P20: 0 | Q20: 0 | R20: 0
A21: Lake | B21: 69 | C21: =Q26 -> 17 | D21: =Q25 -> 23 | I21: Total | J21: 43633 | K21: 916 | L21: 347 | M21: 54 | N21: 53 | O21: 35 | P21: 513 | Q21: 86 | R21: 99
A22: Lassen | B22: 52 | C22: =R24+R26+R27 -> 35 | D22: NULL
A23: Los Angeles | B23: 15018 | C23: =J44+J46+J47 -> 6150 | D23: =J45 -> 6029 | I23: Placement Type | J23: Fresno | K23: Glenn | L23: Humboldt | M23: Imperial | N23: Inyo | O23: Kern | P23: Kings | Q23: Lake | R23: Lassen
A24: Madera | B24: 210 | C24: =K46+K47 -> 95 | D24: =K45 -> 57 | H24: Foster | I24: Pre-Adopt | J24: 92 | K24: M | L24: 12 | M24: M | N24: 0 | O24: 27 | P24: M | Q24: M | R24: 0
A25: Marin | B25: 69 | C25: NULL | D25: =L45 -> 26 | H25: Relative | I25: Relative/NREFM | J25: 541 | K25: 14 | L25: 93 | M25: 102 | N25: 15 | O25: 512 | P25: 124 | Q25: 23 | R25: M
A26: Mariposa | B26: 35 | C26: =M46+M44 -> 14 | D26: NULL | H26: Foster | I26: Foster | J26: 256 | K26: M | L26: 42 | M26: 62 | N26: 12 | O26: 503 | P26: 81 | Q26: 17 | R26: 16
A27: Mendocino | B27: 205 | C27: =N46+N47 -> 94 | D27: =N45 -> 36 | H27: Foster | I27: FFA | J27: 631 | K27: M | L27: 24 | M27: 40 | N27: M | O27: 351 | P27: 40 | Q27: M | R27: 19
A28: Merced | B28: 615 | C28: =O44+O46+O47 -> 285 | D28: =O45 -> 224 | H28: Other | I28: Court Specified Home | J28: 32 | K28: 0 | L28: M | M28: 0 | N28: 0 | O28: M | P28: M | Q28: 0 | R28: 0
A29: Modoc | B29: 18 | C29: NULL | D29: NULL | H29: Other | J29: M | K29: M | L29: 41 | M29: 0 | N29: M | O29: 0 | P29: M | Q29: 0 | R29: M
A30: Mono | B30: M | C30: NULL | D30: NULL | H30: Cong. Care | I30: Group | J30: 70 | K30: M | L30: M | M30: 15 | N30: M | O30: 37 | P30: M | Q30: M | R30: M
A31: Monterey | B31: 161 | C31: =R46+R47 -> 84 | D31: =R45 -> 32 | H31: Cong. Care | I31: Shelter | J31: 0 | K31: 0 | L31: M | M31: M | N31: 0 | O31: M | P31: 0 | Q31: 0 | R31: 0
A32: Napa | B32: 61 | C32: =J64+J67 -> 15 | D32: =J65 -> 19 | H32: Other | I32: Non-FC | J32: M | K32: 0 | L32: 0 | M32: M | N32: 0 | O32: M | P32: M | Q32: 0 | R32: 0
A33: Nevada | B33: 36 | C33: =K64+K67 -> 11 | D33: =K65 -> 13 | H33: Other | I33: Guardian - Dependent | J33: 33 | K33: 0 | L33: M | M33: M | N33: 0 | O33: 12 | P33: 0 | Q33: 0 | R33: 0
A34: Orange | B34: 2205 | C34: =L64+L66+L67 -> 543 | D34: =L65 -> 1107 | H34: Other | I34: Guardian - Non-Dependent | J34: 15 | K34: 0 | L34: 0 | M34: M | N34: 0 | O34: M | P34: M | Q34: 0 | R34: 0
A35: Placer | B35: 153 | C35: =M64+M67 -> 51 | D35: =M65 -> 56 | H35: Other | I35: Runaway | J35: 40 | K35: M | L35: M | M35: M | N35: 0 | O35: 43 | P35: M | Q35: M | R35: 0
A36: Plumas | B36: 22 | C36: NULL | D36: NULL | H36: REMOVE | I36: Trial Home Visit | J36: 138 | K36: M | L36: 0 | M36: 0 | N36: 0 | O36: 0 | P36: 0 | Q36: 0 | R36: 0
A37: Riverside | B37: 3119 | C37: =O64+O66+O67 -> 1320 | D37: =O65 -> 1177 | H37: Other | I37: SILP | J37: 73 | K37: M | L37: 20 | M37: 27 | N37: 0 | O37: 99 | P37: 33 | Q37: M | R37: M
A38: Sacramento | B38: 1176 | C38: =P64+P66+P67 -> 457 | D38: =P65 -> 277 | H38: Other | I38: Transitional Housing | J38: 88 | K38: M | L38: 20 | M38: M | N38: 0 | O38: 71 | P38: M | Q38: M | R38: 0
A39: San Benito | B39: 26 | C39: NULL | D39: =Q65 -> 13 | H39: Other | I39: Other | J39: 71 | K39: M | L39: 20 | M39: M | N39: M | O39: 46 | P39: 0 | Q39: M | R39: M
A40: San Bernardino | B40: 4996 | C40: =R64+R66+R67 -> 2220 | D40: =R65 -> 1544 | H40: Other | I40: Missing | J40: 0 | K40: 0 | L40: 0 | M40: 0 | N40: 0 | O40: 0 | P40: 0 | Q40: 0 | R40: 0
A41: San Diego | B41: 1655 | C41: =J84+J86+J87 -> 636 | D41: =J85 -> 587 | I41: Total | J41: 2093 | K41: 46 | L41: 281 | M41: 270 | N41: 33 | O41: 1728 | P41: 298 | Q41: 69 | R41: 52
A42: San Francisco | B42: 620 | C42: =K86+K87 -> 274 | D42: =K85 -> 195
A43: San Joaquin | B43: 1170 | C43: =L84+L86+L87 -> 485 | D43: =L85 -> 429 | I43: Placement Type | J43: Los Angeles | K43: Madera | L43: Marin | M43: Mariposa | N43: Mendocino | O43: Merced | P43: Modoc | Q43: Mono | R43: Monterey
A44: San Luis Obispo | B44: 260 | C44: =M84+M86+M87 -> 106 | D44: =M85 -> 98 | H44: Foster | I44: Pre-Adopt | J44: 1810 | K44: M | L44: M | M44: 0 | N44: M | O44: 33 | P44: M | Q44: 0 | R44: M
A45: San Mateo | B45: 115 | C45: =N86+N87 -> 45 | D45: =N85 -> 25 | H45: Relative | I45: Relative/NREFM | J45: 6029 | K45: 57 | L45: 26 | M45: M | N45: 36 | O45: 224 | P45: M | Q45: M | R45: 32
A46: Santa Barbara | B46: 387 | C46: =O86+O87 -> 164 | D46: =O85 -> 137 | H46: Foster | I46: Foster | J46: 2663 | K46: 62 | L46: M | M46: 14 | N46: 48 | O46: 107 | P46: M | Q46: M | R46: 66
A47: Santa Clara | B47: 494 | C47: =P86+P87 -> 234 | D47: =P85 -> 111 | H47: Foster | I47: FFA | J47: 1677 | K47: 33 | L47: M | M47: M | N47: 46 | O47: 145 | P47: M | Q47: 0 | R47: 18
A48: Santa Cruz | B48: 116 | C48: =Q84+Q86 -> 34 | D48: =Q85 -> 46 | H48: Other | I48: Court Specified Home | J48: 229 | K48: 0 | L48: 0 | M48: 0 | N48: M | O48: M | P48: 0 | Q48: 0 | R48: 0
A49: Shasta | B49: 376 | C49: =R84+R86+R87 -> 179 | D49: =R85 -> 127 | H49: Other | J49: 0 | K49: M | L49: 0 | M49: 0 | N49: 23 | O49: 0 | P49: 0 | Q49: 0 | R49: 0
A50: Sierra | B50: 11 | C50: NULL | D50: NULL | H50: Cong. Care | I50: Group | J50: 246 | K50: M | L50: M | M50: M | N50: 12 | O50: 16 | P50: M | Q50: 0 | R50: M
A51: Siskiyou | B51: 85 | C51: =K104+K106+K107 -> 49 | D51: =K105 -> 18 | H51: Cong. Care | I51: Shelter | J51: 0 | K51: 0 | L51: 0 | M51: 0 | N51: M | O51: 0 | P51: 0 | Q51: 0 | R51: M
A52: Solano | B52: 305 | C52: =L104+L106+L107 -> 133 | D52: =L105 -> 95 | H52: Other | I52: Non-FC | J52: 108 | K52: M | L52: 0 | M52: 0 | N52: M | O52: 0 | P52: 0 | Q52: 0 | R52: M
A53: Sonoma | B53: 446 | C53: =M104+M106+M107 -> 167 | D53: =M105 -> 122 | H53: Other | I53: Guardian - Dependent | J53: 334 | K53: M | L53: 0 | M53: 0 | N53: M | O53: 0 | P53: 0 | Q53: 0 | R53: 0
A54: Stanislaus | B54: 514 | C54: =N106+N107 -> 252 | D54: =N105 -> 65 | H54: Other | I54: Guardian - Non-Dependent | J54: 96 | K54: M | L54: 0 | M54: 0 | N54: 0 | O54: M | P54: M | Q54: 0 | R54: 0
A55: Sutter | B55: 96 | C55: =O107 -> 45 | D55: =O105 -> 21 | H55: Other | I55: Runaway | J55: 120 | K55: M | L55: M | M55: 0 | N55: M | O55: M | P55: 0 | Q55: 0 | R55: M
A56: Tehama | B56: 120 | C56: =P106+P107 -> 59 | D56: =P105 -> 16 | H56: REMOVE | I56: Trial Home Visit | J56: 11 | K56: 0 | L56: 0 | M56: M | N56: M | O56: 11 | P56: 0 | Q56: M | R56: 0
A57: Trinity | B57: 26 | C57: NULL | D57: NULL | H57: Other | I57: SILP | J57: 1145 | K57: 14 | L57: M | M57: M | N57: 18 | O57: 24 | P57: 0 | Q57: 0 | R57: 17
A58: Tulare | B58: 837 | C58: =R104+R106+R107 -> 416 | D58: =R105 -> 239 | H58: Other | I58: Transitional Housing | J58: 368 | K58: 15 | L58: 12 | M58: 0 | N58: M | O58: 37 | P58: 0 | Q58: 0 | R58: M
A59: Tuolumne | B59: 63 | C59: =J124+J126 -> 24 | D59: =J125 -> 18 | H59: Other | I59: Other | J59: 182 | K59: M | L59: M | M59: 0 | N59: M | O59: M | P59: 0 | Q59: 0 | R59: M
A60: Ventura | B60: 435 | C60: =K126+K127 -> 107 | D60: =K125 -> 193 | H60: Other | I60: Missing | J60: 0 | K60: 0 | L60: 0 | M60: 0 | N60: 0 | O60: 0 | P60: 0 | Q60: 0 | R60: 0
A61: Yolo | B61: 244 | C61: =L126+L127 -> 152 | D61: =L125 -> 64 | I61: Total | J61: 15018 | K61: 210 | L61: 69 | M61: 35 | N61: 205 | O61: 615 | P61: 18 | Q61: M | R61: 161
A62: Yuba | B62: 152 | C62: =M126+M127 -> 87 | D62: =M125 -> 21
I63: Placement Type | J63: Napa | K63: Nevada | L63: Orange | M63: Placer | N63: Plumas | O63: Riverside | P63: Sacramento | Q63: San Benito | R63: San Bernardino
H64: Foster | I64: Pre-Adopt | J64: 0 | K64: 0 | L64: 59 | M64: 0 | N64: 0 | O64: 37 | P64: 22 | Q64: 0 | R64: 57
H65: Relative | I65: Relative/NREFM | J65: 19 | K65: 13 | L65: 1107 | M65: 56 | N65: M | O65: 1177 | P65: 277 | Q65: 13 | R65: 1544
H66: Foster | I66: Foster | J66: M | K66: M | L66: 283 | M66: M | N66: M | O66: 216 | P66: 190 | Q66: M | R66: 463
H67: Foster | I67: FFA | J67: 15 | K67: 11 | L67: 201 | M67: 51 | N67: M | O67: 1067 | P67: 245 | Q67: M | R67: 1700
H68: Other | I68: Court Specified Home | J68: M | K68: 0 | L68: M | M68: M | N68: 0 | O68: 49 | P68: 34 | Q68: 0 | R68: 77
H69: Other | J69: 0 | K69: 0 | L69: 0 | M69: M | N69: 0 | O69: M | P69: M | Q69: 0 | R69: M
H70: Cong. Care | I70: Group | J70: M | K70: M | L70: 62 | M70: M | N70: M | O70: 119 | P70: 58 | Q70: 0 | R70: 324
H71: Cong. Care | I71: Shelter | J71: 0 | K71: 0 | L71: 74 | M71: 0 | N71: 0 | O71: 0 | P71: 0 | Q71: 0 | R71: 0
H72: Other | I72: Non-FC | J72: M | K72: M | L72: 49 | M72: M | N72: 0 | O72: 44 | P72: 23 | Q72: 0 | R72: 72
H73: Other | I73: Guardian - Dependent | J73: 0 | K73: 0 | L73: M | M73: 0 | N73: 0 | O73: 17 | P73: 50 | Q73: 0 | R73: 33
H74: Other | I74: Guardian - Non-Dependent | J74: 0 | K74: 0 | L74: 0 | M74: M | N74: 0 | O74: M | P74: M | Q74: 0 | R74: M
H75: Other | I75: Runaway | J75: 0 | K75: 0 | L75: 18 | M75: M | N75: 0 | O75: 25 | P75: 24 | Q75: M | R75: 76
H76: REMOVE | I76: Trial Home Visit | J76: 0 | K76: 0 | L76: 89 | M76: 0 | N76: M | O76: 17 | P76: 0 | Q76: 0 | R76: 108
H77: Other | I77: SILP | J77: M | K77: M | L77: 129 | M77: M | N77: M | O77: 145 | P77: 99 | Q77: M | R77: 262
H78: Other | I78: Transitional Housing | J78: M | K78: 0 | L78: 91 | M78: 15 | N78: M | O78: 144 | P78: 123 | Q78: 0 | R78: 155
H79: Other | I79: Other | J79: 0 | K79: 0 | L79: 18 | M79: M | N79: M | O79: 52 | P79: 24 | Q79: M | R79: 101
H80: Other | I80: Missing | J80: 0 | K80: 0 | L80: 0 | M80: 0 | N80: 0 | O80: 0 | P80: 0 | Q80: 0 | R80: 0
I81: Total | J81: 61 | K81: 36 | L81: 2205 | M81: 153 | N81: 22 | O81: 3119 | P81: 1176 | Q81: 26 | R81: 4996
I83: Placement Type | J83: San Diego | K83: San Francisco | L83: San Joaquin | M83: San Luis Obispo | N83: San Mateo | O83: Santa Barbara | P83: Santa Clara | Q83: Santa Cruz | R83: Shasta
H84: Foster | I84: Pre-Adopt | J84: 60 | K84: M | L84: 24 | M84: 12 | N84: M | O84: M | P84: M | Q84: 0 | R84: 11
H85: Relative | I85: Relative/NREFM | J85: 587 | K85: 195 | L85: 429 | M85: 98 | N85: 25 | O85: 137 | P85: 111 | Q85: 46 | R85: 127
H86: Foster | I86: Foster | J86: 448 | K86: 66 | L86: 150 | M86: 75 | N86: 29 | O86: 128 | P86: 148 | Q86: 34 | R86: 84
H87: Foster | I87: FFA | J87: 128 | K87: 208 | L87: 311 | M87: 19 | N87: 16 | O87: 36 | P87: 86 | Q87: M | R87: 84
H88: Other | I88: Court Specified Home | J88: 45 | K88: 0 | L88: 0 | M88: 0 | N88: 0 | O88: M | P88: M | Q88: 0 | R88: M
H89: Other | J89: M | K89: 0 | L89: 0 | M89: 0 | N89: 0 | O89: 0 | P89: 0 | Q89: 0 | R89: M
H90: Cong. Care | I90: Group | J90: 107 | K90: M | L90: 48 | M90: M | N90: M | O90: 13 | P90: 14 | Q90: M | R90: M
H91: Cong. Care | I91: Shelter | J91: 34 | K91: 0 | L91: 16 | M91: 0 | N91: M | O91: 0 | P91: 0 | Q91: 0 | R91: 0
H92: Other | I92: Non-FC | J92: 12 | K92: M | L92: M | M92: M | N92: 0 | O92: M | P92: M | Q92: 0 | R92: M
H93: Other | I93: Guardian - Dependent | J93: M | K93: 0 | L93: 0 | M93: 0 | N93: 0 | O93: 0 | P93: 0 | Q93: M | R93: M
H94: Other | I94: Guardian - Non-Dependent | J94: M | K94: M | L94: 0 | M94: 0 | N94: 0 | O94: 0 | P94: M | Q94: 0 | R94: M
H95: Other | I95: Runaway | J95: 17 | K95: 14 | L95: 12 | M95: M | N95: M | O95: M | P95: M | Q95: M | R95: M
